Workbook

Sheet Data
A1: Código LT | B1: Periodo | C1: Mes Izipay | D1: Fecha de Ingreso | E1: Fecha de Instalación | F1: Código | G1: Serie | H1: Ruc | I1: Razón Social | J1: Nombre Comercial | K1: Estado | L1: Estado LT | M1: Tipo de Venta | N1: Producto | O1: Tipo Cliente | P1: GPV Mensual | Q1: GPV Mensual LT | R1: Ejecutivo | S1: DNI Ejecutivo | T1: Correo Ejecutivo | U1: Categoría | V1: Zona | W1: Supervisor | X1: Jefatura | Y1: DNI Supervisor | Z1: Correo Supervisor | AA1: DNI Referido | AB1: Referido | AC1: Código DNI | AD1: CIIU | AE1: Detalle CIIU | AF1: Vol M0 | AG1: Vol QR M0 | AH1: Vol TJ M0 | AI1: Vol M1 | AJ1: Vol QR M1 | AK1: Vol TJ M1 | AL1: Vol M2 | AM1: Vol QR M2 | AN1: Vol TJ M2 | AO1: Vol M3 | AP1: Vol QR M3 | AQ1: Vol TJ M3 | AR1: Ruc Activo
A2: =CONCATENATE(Data.[[#This Row],[Código]],Data.[[#This Row],[Ruc]]) -> 105841310424714441 | B2: 46143 | C2: =IFERROR(VLOOKUP(Data.[[#This Row],[Código LT]],Reportería.[],71,0),"") | D2: =IFERROR(VLOOKUP(Data.[[#This Row],[Código]],BV!A:C,2,0),"") -> 46153 | E2: =IFERROR(VLOOKUP(Data.[[#This Row],[Código]],BV!A:C,3,0),"") -> 46160 | F2: 1058413 | G2: 233WFD870802 | H2: 10424714441 | I2: CARRION CAVERO LUIS ALBERTO | J2: LOS DULCES DE VALE | K2: =IF(Data.[[#This Row],[Tipo de Venta]]<>"POS","Atendido",IF(Data.[[#This Row],[Fecha de Instalación]]<>"","Atendido","Ingresado")) -> Atendido | L2: =Data.[[#This Row],[Estado]] -> Atendido | M2: POS | N2: =IFERROR(VLOOKUP(Data.[[#This Row],[Código LT]],Reportería.[],20,0),"") | O2: =IFERROR(VLOOKUP(Data.[[#This Row],[Código LT]],Reportería.[],5,0),"") | P2: =Data.[[#This Row],[GPV Mensual LT]]/COUNTIFS(H:H,Data.[[#This Row],[Ruc]],B:B,Data.[[#This Row],[Periodo]]) -> 60000 | Q2: 60000 | R2: Milagros Rocha | S2: =VLOOKUP(Data.[[#This Row],[Ejecutivo]],Productividad!D:N,11,0) -> 43661391 | T2: =VLOOKUP(Data.[[#This Row],[DNI Ejecutivo]],Productividad!C:U,8,0) -> mrochar@lozapay.com.pe | U2: =VLOOKUP(Data.[[#This Row],[DNI Ejecutivo]],Productividad!C:U,4,0) -> Elite | V2: =IFERROR(VLOOKUP(Data.[[#This Row],[DNI Ejecutivo]],Ejecutivos.[],11,0),"") -> Lima Palomino | W2: Carlos Palomino | X2: {=IFERROR(_xlfn.IFS(Data.[[#This Row],[Supervisor]]="Jonathan Lapoint","Norte",Data.[[#This Row],[Supervisor]]="Jorge Fuentes","Norte"),"Lima")} -> Lima | Y2: =VLOOKUP(Data.[[#This Row],[Supervisor]],Ejecutivos!B:S,17,0) -> 41718975 | Z2: =VLOOKUP(Data.[[#This Row],[DNI Supervisor]],Productividad!C:U,8,0) -> carlos.palomino@lozapay.com.pe | AB2: MILAGROS EVELYN ROCHA RODRIGUEZ | AC2: =IFERROR(CONCATENATE(Data.[[#This Row],[DNI Ejecutivo]],Data.[[#This Row],[Periodo]]),"") -> 4366139146143 | AD2: =IFERROR(VLOOKUP(Data.[[#This Row],[Código LT]],Reportería.[],10,0),"") | AE2: =IFERROR(VLOOKUP(Data.[[#This Row],[Código LT]],Reportería.[],11,0),"") | AF2: 1150.6 | AI2: =IF(TEXT(Data.[[#This Row],[Periodo]],"mmm-yy")="may-26",VLOOKUP(Data.[[#This Row],[Código]],Reportería!A:BV,57,0),0) -> 0 | AL2: =IF(Data.[[#This Row],[Vol M0]]="",0,0) -> 0 | AM2: =IF(Data.[[#This Row],[Vol M0]]="",0,0) -> 0 | AN2: =IF(Data.[[#This Row],[Vol M0]]="",0,0) -> 0 | AO2: =IF(Data.[[#This Row],[Vol M0]]="",0,0) -> 0 | AP2: =IF(Data.[[#This Row],[Vol M0]]="",0,0) -> 0 | AQ2: =IF(Data.[[#This Row],[Vol M0]]="",0,0) -> 0 | AR2: =IFERROR(IF(OR(AND(OR(Data.[[#This Row],[Categoría]]="Hunter",Data.[[#This Row],[Categoría]]="Senior"),OR(SUMIFS(AF:AF,H:H,Data.[[#This Row],[Ruc]],B:B,Data.[[#This Row],[Periodo]])>=15000,SUMIFS(AI:AI,H:H,Data.[[#This Row],[Ruc]],B:B,Data.[[#This Row],[Periodo]])>=15000,SUMIFS(AL:AL,H:H,Data.[[#This Row],[Ruc]],B:B,Data.[[#This Row],[Periodo]])>=15000,SUMIFS(AO:AO,H:H,Data.[[#This Row],[Ruc]],B:B,Data.[[#This Row],[Periodo]])>=15000)),AND(Data.[[#This Row],[Categoría]]="Elite",OR(SUMIFS(AF:AF,H:H,Data.[[#This Row],[Ruc]],B:B,Data.[[#This Row],[Periodo]])>=25000,SUMIFS(AI:AI,H:H,Data.[[#This Row],[Ruc]],B:B,Data.[[#This Row],[Periodo]])>=25000,SUMIFS(AL:AL,H:H,Data.[[#This Row],[Ruc]],B:B,Data.[[#This Row],[Periodo]])>=25000,SUMIFS(AO:AO,H:H,Data.[[#This Row],[Ruc]],B:B,Data.[[#This Row],[Periodo]])>=25000))),1,0)/COUNTIFS(H:H,Data.[[#This Row],[Ruc]],B:B,Data.[[#This Row],[Periodo]]),0) -> 0
A3: =CONCATENATE(Data.[[#This Row],[Código]],Data.[[#This Row],[Ruc]]) -> 594666620533799401 | B3: 46143 | C3: =IFERROR(VLOOKUP(Data.[[#This Row],[Código LT]],Reportería.[],71,0),"") | D3: =IFERROR(VLOOKUP(Data.[[#This Row],[Código]],BV!A:C,2,0),"") -> 46153 | E3: =IFERROR(VLOOKUP(Data.[[#This Row],[Código]],BV!A:C,3,0),"") -> 46157 | F3: 5946666 | G3: TJ33261A20815 | H3: 20533799401 | I3: PRB CORPORATION S.R.L. | J3: DISCOBAR | K3: =IF(Data.[[#This Row],[Tipo de Venta]]<>"POS","Atendido",IF(Data.[[#This Row],[Fecha de Instalación]]<>"","Atendido","Ingresado")) -> Atendido | L3: =Data.[[#This Row],[Estado]] -> Atendido | M3: POS | N3: =IFERROR(VLOOKUP(Data.[[#This Row],[Código LT]],Reportería.[],20,0),"") | O3: =IFERROR(VLOOKUP(Data.[[#This Row],[Código LT]],Reportería.[],5,0),"") | P3: =Data.[[#This Row],[GPV Mensual LT]]/COUNTIFS(H:H,Data.[[#This Row],[Ruc]],B:B,Data.[[#This Row],[Periodo]]) -> 112500 | Q3: 225000 | R3: Jose Mujica | S3: =VLOOKUP(Data.[[#This Row],[Ejecutivo]],Productividad!D:N,11,0) -> 002409208 | T3: =VLOOKUP(Data.[[#This Row],[DNI Ejecutivo]],Productividad!C:U,8,0) -> jose.mujica@lozapay.com.pe | U3: =VLOOKUP(Data.[[#This Row],[DNI Ejecutivo]],Productividad!C:U,4,0) -> Senior | V3: =IFERROR(VLOOKUP(Data.[[#This Row],[DNI Ejecutivo]],Ejecutivos.[],11,0),"") -> Norte Fuentes | W3: Jorge Fuentes | X3: {=IFERROR(_xlfn.IFS(Data.[[#This Row],[Supervisor]]="Jonathan Lapoint","Norte",Data.[[#This Row],[Supervisor]]="Jorge Fuentes","Norte"),"Lima")} -> Norte | Y3: =VLOOKUP(Data.[[#This Row],[Supervisor]],Ejecutivos!B:S,17,0) -> 70059865 | Z3: =VLOOKUP(Data.[[#This Row],[DNI Supervisor]],Productividad!C:U,8,0) -> jfuentes@lozapay.com.pe | AB3: JOSE GREGORIO MUJICA RUIZ | AC3: =IFERROR(CONCATENATE(Data.[[#This Row],[DNI Ejecutivo]],Data.[[#This Row],[Periodo]]),"") -> 00240920846143 | AD3: =IFERROR(VLOOKUP(Data.[[#This Row],[Código LT]],Reportería.[],10,0),"") | AE3: =IFERROR(VLOOKUP(Data.[[#This Row],[Código LT]],Reportería.[],11,0),"") | AF3: 28136 | AI3: =IF(TEXT(Data.[[#This Row],[Periodo]],"mmm-yy")="may-26",VLOOKUP(Data.[[#This Row],[Código]],Reportería!A:BV,57,0),0) -> 16342 | AL3: =IF(Data.[[#This Row],[Vol M0]]="",0,0) -> 0 | AM3: =IF(Data.[[#This Row],[Vol M0]]="",0,0) -> 0 | AN3: =IF(Data.[[#This Row],[Vol M0]]="",0,0) -> 0 | AO3: =IF(Data.[[#This Row],[Vol M0]]="",0,0) -> 0 | AP3: =IF(Data.[[#This Row],[Vol M0]]="",0,0) -> 0 | AQ3: =IF(Data.[[#This Row],[Vol M0]]="",0,0) -> 0 | AR3: =IFERROR(IF(OR(AND(OR(Data.[[#This Row],[Categoría]]="Hunter",Data.[[#This Row],[Categoría]]="Senior"),OR(SUMIFS(AF:AF,H:H,Data.[[#This Row],[Ruc]],B:B,Data.[[#This Row],[Periodo]])>=15000,SUMIFS(AI:AI,H:H,Data.[[#This Row],[Ruc]],B:B,Data.[[#This Row],[Periodo]])>=15000,SUMIFS(AL:AL,H:H,Data.[[#This Row],[Ruc]],B:B,Data.[[#This Row],[Periodo]])>=15000,SUMIFS(AO:AO,H:H,Data.[[#This Row],[Ruc]],B:B,Data.[[#This Row],[Periodo]])>=15000)),AND(Data.[[#This Row],[Categoría]]="Elite",OR(SUMIFS(AF:AF,H:H,Data.[[#This Row],[Ruc]],B:B,Data.[[#This Row],[Periodo]])>=25000,SUMIFS(AI:AI,H:H,Data.[[#This Row],[Ruc]],B:B,Data.[[#This Row],[Periodo]])>=25000,SUMIFS(AL:AL,H:H,Data.[[#This Row],[Ruc]],B:B,Data.[[#This Row],[Periodo]])>=25000,SUMIFS(AO:AO,H:H,Data.[[#This Row],[Ruc]],B:B,Data.[[#This Row],[Periodo]])>=25000))),1,0)/COUNTIFS(H:H,Data.[[#This Row],[Ruc]],B:B,Data.[[#This Row],[Periodo]]),0) -> 0.5
A4: =CONCATENATE(Data.[[#This Row],[Código]],Data.[[#This Row],[Ruc]]) -> 594637720533799401 | B4: 46143 | C4: =IFERROR(VLOOKUP(Data.[[#This Row],[Código LT]],Reportería.[],71,0),"") | D4: =IFERROR(VLOOKUP(Data.[[#This Row],[Código]],BV!A:C,2,0),"") -> 46153 | E4: =IFERROR(VLOOKUP(Data.[[#This Row],[Código]],BV!A:C,3,0),"") -> 46157 | F4: 5946377 | G4: TJ33261C21711 | H4: 20533799401 | I4: PRB CORPORATION S.R.L. | J4: DISCOBAR | K4: =IF(Data.[[#This Row],[Tipo de Venta]]<>"POS","Atendido",IF(Data.[[#This Row],[Fecha de Instalación]]<>"","Atendido","Ingresado")) -> Atendido | L4: =Data.[[#This Row],[Estado]] -> Atendido | M4: POS | N4: =IFERROR(VLOOKUP(Data.[[#This Row],[Código LT]],Reportería.[],20,0),"") | O4: =IFERROR(VLOOKUP(Data.[[#This Row],[Código LT]],Reportería.[],5,0),"") | P4: =Data.[[#This Row],[GPV Mensual LT]]/COUNTIFS(H:H,Data.[[#This Row],[Ruc]],B:B,Data.[[#This Row],[Periodo]]) -> 112500 | Q4: 225000 | R4: Jose Mujica | S4: =VLOOKUP(Data.[[#This Row],[Ejecutivo]],Productividad!D:N,11,0) -> 002409208 | T4: =VLOOKUP(Data.[[#This Row],[DNI Ejecutivo]],Productividad!C:U,8,0) -> jose.mujica@lozapay.com.pe | U4: =VLOOKUP(Data.[[#This Row],[DNI Ejecutivo]],Productividad!C:U,4,0) -> Senior | V4: =IFERROR(VLOOKUP(Data.[[#This Row],[DNI Ejecutivo]],Ejecutivos.[],11,0),"") -> Norte Fuentes | W4: Jorge Fuentes | X4: {=IFERROR(_xlfn.IFS(Data.[[#This Row],[Supervisor]]="Jonathan Lapoint","Norte",Data.[[#This Row],[Supervisor]]="Jorge Fuentes","Norte"),"Lima")} -> Norte | Y4: =VLOOKUP(Data.[[#This Row],[Supervisor]],Ejecutivos!B:S,17,0) -> 70059865 | Z4: =VLOOKUP(Data.[[#This Row],[DNI Supervisor]],Productividad!C:U,8,0) -> jfuentes@lozapay.com.pe | AB4: JOSE GREGORIO MUJICA RUIZ | AC4: =IFERROR(CONCATENATE(Data.[[#This Row],[DNI Ejecutivo]],Data.[[#This Row],[Periodo]]),"") -> 00240920846143 | AD4: =IFERROR(VLOOKUP(Data.[[#This Row],[Código LT]],Reportería.[],10,0),"") | AE4: =IFERROR(VLOOKUP(Data.[[#This Row],[Código LT]],Reportería.[],11,0),"") | AF4: 19372 | AI4: =IF(TEXT(Data.[[#This Row],[Periodo]],"mmm-yy")="may-26",VLOOKUP(Data.[[#This Row],[Código]],Reportería!A:BV,57,0),0) -> 15326 | AL4: =IF(Data.[[#This Row],[Vol M0]]="",0,0) -> 0 | AM4: =IF(Data.[[#This Row],[Vol M0]]="",0,0) -> 0 | AN4: =IF(Data.[[#This Row],[Vol M0]]="",0,0) -> 0 | AO4: =IF(Data.[[#This Row],[Vol M0]]="",0,0) -> 0 | AP4: =IF(Data.[[#This Row],[Vol M0]]="",0,0) -> 0 | AQ4: =IF(Data.[[#This Row],[Vol M0]]="",0,0) -> 0 | AR4: =IFERROR(IF(OR(AND(OR(Data.[[#This Row],[Categoría]]="Hunter",Data.[[#This Row],[Categoría]]="Senior"),OR(SUMIFS(AF:AF,H:H,Data.[[#This Row],[Ruc]],B:B,Data.[[#This Row],[Periodo]])>=15000,SUMIFS(AI:AI,H:H,Data.[[#This Row],[Ruc]],B:B,Data.[[#This Row],[Periodo]])>=15000,SUMIFS(AL:AL,H:H,Data.[[#This Row],[Ruc]],B:B,Data.[[#This Row],[Periodo]])>=15000,SUMIFS(AO:AO,H:H,Data.[[#This Row],[Ruc]],B:B,Data.[[#This Row],[Periodo]])>=15000)),AND(Data.[[#This Row],[Categoría]]="Elite",OR(SUMIFS(AF:AF,H:H,Data.[[#This Row],[Ruc]],B:B,Data.[[#This Row],[Periodo]])>=25000,SUMIFS(AI:AI,H:H,Data.[[#This Row],[Ruc]],B:B,Data.[[#This Row],[Periodo]])>=25000,SUMIFS(AL:AL,H:H,Data.[[#This Row],[Ruc]],B:B,Data.[[#This Row],[Periodo]])>=25000,SUMIFS(AO:AO,H:H,Data.[[#This Row],[Ruc]],B:B,Data.[[#This Row],[Periodo]])>=25000))),1,0)/COUNTIFS(H:H,Data.[[#This Row],[Ruc]],B:B,Data.[[#This Row],[Periodo]]),0) -> 0.5
A5: =CONCATENATE(Data.[[#This Row],[Código]],Data.[[#This Row],[Ruc]]) -> 105849820612897949 | B5: 46143 | C5: =IFERROR(VLOOKUP(Data.[[#This Row],[Código LT]],Reportería.[],71,0),"") | D5: =IFERROR(VLOOKUP(Data.[[#This Row],[Código]],BV!A:C,2,0),"") -> 46154 | E5: =IFERROR(VLOOKUP(Data.[[#This Row],[Código]],BV!A:C,3,0),"") -> 46163 | F5: 1058498 | H5: 20612897949 | I5: MIAMI IMPORT RM S.A.C. | J5: MIAMI IMPORT RM | K5: =IF(Data.[[#This Row],[Tipo de Venta]]<>"POS","Atendido",IF(Data.[[#This Row],[Fecha de Instalación]]<>"","Atendido","Ingresado")) -> Atendido | L5: =Data.[[#This Row],[Estado]] -> Atendido | M5: POS | N5: =IFERROR(VLOOKUP(Data.[[#This Row],[Código LT]],Reportería.[],20,0),"") | O5: =IFERROR(VLOOKUP(Data.[[#This Row],[Código LT]],Reportería.[],5,0),"") | P5: =Data.[[#This Row],[GPV Mensual LT]]/COUNTIFS(H:H,Data.[[#This Row],[Ruc]],B:B,Data.[[#This Row],[Periodo]]) -> 100000 | Q5: 100000 | R5: Jackeline Matos | S5: =VLOOKUP(Data.[[#This Row],[Ejecutivo]],Productividad!D:N,11,0) -> 44881019 | T5: =VLOOKUP(Data.[[#This Row],[DNI Ejecutivo]],Productividad!C:U,8,0) -> jackeline.matos@lozapay.com.pe | U5: =VLOOKUP(Data.[[#This Row],[DNI Ejecutivo]],Productividad!C:U,4,0) -> Senior | V5: =IFERROR(VLOOKUP(Data.[[#This Row],[DNI Ejecutivo]],Ejecutivos.[],11,0),"") -> Lima Hamm | W5: Hamm Ramirez | X5: {=IFERROR(_xlfn.IFS(Data.[[#This Row],[Supervisor]]="Jonathan Lapoint","Norte",Data.[[#This Row],[Supervisor]]="Jorge Fuentes","Norte"),"Lima")} -> Lima | Y5: =VLOOKUP(Data.[[#This Row],[Supervisor]],Ejecutivos!B:S,17,0) -> 44818200 | Z5: =VLOOKUP(Data.[[#This Row],[DNI Supervisor]],Productividad!C:U,8,0) -> hramirezp@lozapay.com.pe | AB5: JACKELINE SOLANGE MATOS QUIÑONES | AC5: =IFERROR(CONCATENATE(Data.[[#This Row],[DNI Ejecutivo]],Data.[[#This Row],[Periodo]]),"") -> 4488101946143 | AD5: =IFERROR(VLOOKUP(Data.[[#This Row],[Código LT]],Reportería.[],10,0),"") | AE5: =IFERROR(VLOOKUP(Data.[[#This Row],[Código LT]],Reportería.[],11,0),"") | AF5: 2505 | AI5: =IF(TEXT(Data.[[#This Row],[Periodo]],"mmm-yy")="may-26",VLOOKUP(Data.[[#This Row],[Código]],Reportería!A:BV,57,0),0) -> 27810 | AL5: =IF(Data.[[#This Row],[Vol M0]]="",0,0) -> 0 | AM5: =IF(Data.[[#This Row],[Vol M0]]="",0,0) -> 0 | AN5: =IF(Data.[[#This Row],[Vol M0]]="",0,0) -> 0 | AO5: =IF(Data.[[#This Row],[Vol M0]]="",0,0) -> 0 | AP5: =IF(Data.[[#This Row],[Vol M0]]="",0,0) -> 0 | AQ5: =IF(Data.[[#This Row],[Vol M0]]="",0,0) -> 0 | AR5: =IFERROR(IF(OR(AND(OR(Data.[[#This Row],[Categoría]]="Hunter",Data.[[#This Row],[Categoría]]="Senior"),OR(SUMIFS(AF:AF,H:H,Data.[[#This Row],[Ruc]],B:B,Data.[[#This Row],[Periodo]])>=15000,SUMIFS(AI:AI,H:H,Data.[[#This Row],[Ruc]],B:B,Data.[[#This Row],[Periodo]])>=15000,SUMIFS(AL:AL,H:H,Data.[[#This Row],[Ruc]],B:B,Data.[[#This Row],[Periodo]])>=15000,SUMIFS(AO:AO,H:H,Data.[[#This Row],[Ruc]],B:B,Data.[[#This Row],[Periodo]])>=15000)),AND(Data.[[#This Row],[Categoría]]="Elite",OR(SUMIFS(AF:AF,H:H,Data.[[#This Row],[Ruc]],B:B,Data.[[#This Row],[Periodo]])>=25000,SUMIFS(AI:AI,H:H,Data.[[#This Row],[Ruc]],B:B,Data.[[#This Row],[Periodo]])>=25000,SUMIFS(AL:AL,H:H,Data.[[#This Row],[Ruc]],B:B,Data.[[#This Row],[Periodo]])>=25000,SUMIFS(AO:AO,H:H,Data.[[#This Row],[Ruc]],B:B,Data.[[#This Row],[Periodo]])>=25000))),1,0)/COUNTIFS(H:H,Data.[[#This Row],[Ruc]],B:B,Data.[[#This Row],[Periodo]]),0) -> 1
A6: =CONCATENATE(Data.[[#This Row],[Código]],Data.[[#This Row],[Ruc]]) -> 105844120610935932 | B6: 46143 | C6: =IFERROR(VLOOKUP(Data.[[#This Row],[Código LT]],Reportería.[],71,0),"") | D6: =IFERROR(VLOOKUP(Data.[[#This Row],[Código]],BV!A:C,2,0),"") -> 46154 | E6: =IFERROR(VLOOKUP(Data.[[#This Row],[Código]],BV!A:C,3,0),"") -> 46161 | F6: 1058441 | H6: 20610935932 | I6: SERVICIOS GENERALES OPTIMAX E.I.R.L. | J6: SERVICIOS GENERALES OPTIMAX (CA TENIENTE FERRE 112 TDA D) | K6: =IF(Data.[[#This Row],[Tipo de Venta]]<>"POS","Atendido",IF(Data.[[#This Row],[Fecha de Instalación]]<>"","Atendido","Ingresado")) -> Atendido | L6: =Data.[[#This Row],[Estado]] -> Atendido | M6: POS | N6: =IFERROR(VLOOKUP(Data.[[#This Row],[Código LT]],Reportería.[],20,0),"") | O6: =IFERROR(VLOOKUP(Data.[[#This Row],[Código LT]],Reportería.[],5,0),"") | P6: =Data.[[#This Row],[GPV Mensual LT]]/COUNTIFS(H:H,Data.[[#This Row],[Ruc]],B:B,Data.[[#This Row],[Periodo]]) -> 40000 | Q6: 240000 | R6: Antoni Sifuentes | S6: =VLOOKUP(Data.[[#This Row],[Ejecutivo]],Productividad!D:N,11,0) -> 47045287 | T6: =VLOOKUP(Data.[[#This Row],[DNI Ejecutivo]],Productividad!C:U,8,0) -> asifuentesu@lozapay.com.pe | U6: =VLOOKUP(Data.[[#This Row],[DNI Ejecutivo]],Productividad!C:U,4,0) -> Elite | V6: =IFERROR(VLOOKUP(Data.[[#This Row],[DNI Ejecutivo]],Ejecutivos.[],11,0),"") -> Norte Fuentes | W6: Jorge Fuentes | X6: {=IFERROR(_xlfn.IFS(Data.[[#This Row],[Supervisor]]="Jonathan Lapoint","Norte",Data.[[#This Row],[Supervisor]]="Jorge Fuentes","Norte"),"Lima")} -> Norte | Y6: =VLOOKUP(Data.[[#This Row],[Supervisor]],Ejecutivos!B:S,17,0) -> 70059865 | Z6: =VLOOKUP(Data.[[#This Row],[DNI Supervisor]],Productividad!C:U,8,0) -> jfuentes@lozapay.com.pe | AB6: EDINSON WILLIAMS CHUYES ALDANA | AC6: =IFERROR(CONCATENATE(Data.[[#This Row],[DNI Ejecutivo]],Data.[[#This Row],[Periodo]]),"") -> 4704528746143 | AD6: =IFERROR(VLOOKUP(Data.[[#This Row],[Código LT]],Reportería.[],10,0),"") | AE6: =IFERROR(VLOOKUP(Data.[[#This Row],[Código LT]],Reportería.[],11,0),"") | AF6: 1799.2 | AI6: =IF(TEXT(Data.[[#This Row],[Periodo]],"mmm-yy")="may-26",VLOOKUP(Data.[[#This Row],[Código]],Reportería!A:BV,57,0),0) -> 4323.5 | AL6: =IF(Data.[[#This Row],[Vol M0]]="",0,0) -> 0 | AM6: =IF(Data.[[#This Row],[Vol M0]]="",0,0) -> 0 | AN6: =IF(Data.[[#This Row],[Vol M0]]="",0,0) -> 0 | AO6: =IF(Data.[[#This Row],[Vol M0]]="",0,0) -> 0 | AP6: =IF(Data.[[#This Row],[Vol M0]]="",0,0) -> 0 | AQ6: =IF(Data.[[#This Row],[Vol M0]]="",0,0) -> 0 | AR6: =IFERROR(IF(OR(AND(OR(Data.[[#This Row],[Categoría]]="Hunter",Data.[[#This Row],[Categoría]]="Senior"),OR(SUMIFS(AF:AF,H:H,Data.[[#This Row],[Ruc]],B:B,Data.[[#This Row],[Periodo]])>=15000,SUMIFS(AI:AI,H:H,Data.[[#This Row],[Ruc]],B:B,Data.[[#This Row],[Periodo]])>=15000,SUMIFS(AL:AL,H:H,Data.[[#This Row],[Ruc]],B:B,Data.[[#This Row],[Periodo]])>=15000,SUMIFS(AO:AO,H:H,Data.[[#This Row],[Ruc]],B:B,Data.[[#This Row],[Periodo]])>=15000)),AND(Data.[[#This Row],[Categoría]]="Elite",OR(SUMIFS(AF:AF,H:H,Data.[[#This Row],[Ruc]],B:B,Data.[[#This Row],[Periodo]])>=25000,SUMIFS(AI:AI,H:H,Data.[[#This Row],[Ruc]],B:B,Data.[[#This Row],[Periodo]])>=25000,SUMIFS(AL:AL,H:H,Data.[[#This Row],[Ruc]],B:B,Data.[[#This Row],[Periodo]])>=25000,SUMIFS(AO:AO,H:H,Data.[[#This Row],[Ruc]],B:B,Data.[[#This Row],[Periodo]])>=25000))),1,0)/COUNTIFS(H:H,Data.[[#This Row],[Ruc]],B:B,Data.[[#This Row],[Periodo]]),0) -> 0.16666667
A7: =CONCATENATE(Data.[[#This Row],[Código]],Data.[[#This Row],[Ruc]]) -> 105845720610935932 | B7: 46143 | C7: =IFERROR(VLOOKUP(Data.[[#This Row],[Código LT]],Reportería.[],71,0),"") | D7: =IFERROR(VLOOKUP(Data.[[#This Row],[Código]],BV!A:C,2,0),"") -> 46154 | E7: =IFERROR(VLOOKUP(Data.[[#This Row],[Código]],BV!A:C,3,0),"") -> 46161 | F7: 1058457 | H7: 20610935932 | I7: SERVICIOS GENERALES OPTIMAX E.I.R.L. | J7: SERVICIOS GENERALES OPTIMAX (CA ELIAS AGUIRRE 320 TDA 1) | K7: =IF(Data.[[#This Row],[Tipo de Venta]]<>"POS","Atendido",IF(Data.[[#This Row],[Fecha de Instalación]]<>"","Atendido","Ingresado")) -> Atendido | L7: =Data.[[#This Row],[Estado]] -> Atendido | M7: POS | N7: =IFERROR(VLOOKUP(Data.[[#This Row],[Código LT]],Reportería.[],20,0),"") | O7: =IFERROR(VLOOKUP(Data.[[#This Row],[Código LT]],Reportería.[],5,0),"") | P7: =Data.[[#This Row],[GPV Mensual LT]]/COUNTIFS(H:H,Data.[[#This Row],[Ruc]],B:B,Data.[[#This Row],[Periodo]]) -> 40000 | Q7: 240000 | R7: Antoni Sifuentes | S7: =VLOOKUP(Data.[[#This Row],[Ejecutivo]],Productividad!D:N,11,0) -> 47045287 | T7: =VLOOKUP(Data.[[#This Row],[DNI Ejecutivo]],Productividad!C:U,8,0) -> asifuentesu@lozapay.com.pe | U7: =VLOOKUP(Data.[[#This Row],[DNI Ejecutivo]],Productividad!C:U,4,0) -> Elite | V7: =IFERROR(VLOOKUP(Data.[[#This Row],[DNI Ejecutivo]],Ejecutivos.[],11,0),"") -> Norte Fuentes | W7: Jorge Fuentes | X7: {=IFERROR(_xlfn.IFS(Data.[[#This Row],[Supervisor]]="Jonathan Lapoint","Norte",Data.[[#This Row],[Supervisor]]="Jorge Fuentes","Norte"),"Lima")} -> Norte | Y7: =VLOOKUP(Data.[[#This Row],[Supervisor]],Ejecutivos!B:S,17,0) -> 70059865 | Z7: =VLOOKUP(Data.[[#This Row],[DNI Supervisor]],Productividad!C:U,8,0) -> jfuentes@lozapay.com.pe | AB7: EDINSON WILLIAMS CHUYES ALDANA | AC7: =IFERROR(CONCATENATE(Data.[[#This Row],[DNI Ejecutivo]],Data.[[#This Row],[Periodo]]),"") -> 4704528746143 | AD7: =IFERROR(VLOOKUP(Data.[[#This Row],[Código LT]],Reportería.[],10,0),"") | AE7: =IFERROR(VLOOKUP(Data.[[#This Row],[Código LT]],Reportería.[],11,0),"") | AF7: 918.9 | AI7: =IF(TEXT(Data.[[#This Row],[Periodo]],"mmm-yy")="may-26",VLOOKUP(Data.[[#This Row],[Código]],Reportería!A:BV,57,0),0) -> 3145.5 | AL7: =IF(Data.[[#This Row],[Vol M0]]="",0,0) -> 0 | AM7: =IF(Data.[[#This Row],[Vol M0]]="",0,0) -> 0 | AN7: =IF(Data.[[#This Row],[Vol M0]]="",0,0) -> 0 | AO7: =IF(Data.[[#This Row],[Vol M0]]="",0,0) -> 0 | AP7: =IF(Data.[[#This Row],[Vol M0]]="",0,0) -> 0 | AQ7: =IF(Data.[[#This Row],[Vol M0]]="",0,0) -> 0 | AR7: =IFERROR(IF(OR(AND(OR(Data.[[#This Row],[Categoría]]="Hunter",Data.[[#This Row],[Categoría]]="Senior"),OR(SUMIFS(AF:AF,H:H,Data.[[#This Row],[Ruc]],B:B,Data.[[#This Row],[Periodo]])>=15000,SUMIFS(AI:AI,H:H,Data.[[#This Row],[Ruc]],B:B,Data.[[#This Row],[Periodo]])>=15000,SUMIFS(AL:AL,H:H,Data.[[#This Row],[Ruc]],B:B,Data.[[#This Row],[Periodo]])>=15000,SUMIFS(AO:AO,H:H,Data.[[#This Row],[Ruc]],B:B,Data.[[#This Row],[Periodo]])>=15000)),AND(Data.[[#This Row],[Categoría]]="Elite",OR(SUMIFS(AF:AF,H:H,Data.[[#This Row],[Ruc]],B:B,Data.[[#This Row],[Periodo]])>=25000,SUMIFS(AI:AI,H:H,Data.[[#This Row],[Ruc]],B:B,Data.[[#This Row],[Periodo]])>=25000,SUMIFS(AL:AL,H:H,Data.[[#This Row],[Ruc]],B:B,Data.[[#This Row],[Periodo]])>=25000,SUMIFS(AO:AO,H:H,Data.[[#This Row],[Ruc]],B:B,Data.[[#This Row],[Periodo]])>=25000))),1,0)/COUNTIFS(H:H,Data.[[#This Row],[Ruc]],B:B,Data.[[#This Row],[Periodo]]),0) -> 0.16666667
A8: =CONCATENATE(Data.[[#This Row],[Código]],Data.[[#This Row],[Ruc]]) -> 105845820610935932 | B8: 46143 | C8: =IFERROR(VLOOKUP(Data.[[#This Row],[Código LT]],Reportería.[],71,0),"") | D8: =IFERROR(VLOOKUP(Data.[[#This Row],[Código]],BV!A:C,2,0),"") -> 46154 | E8: =IFERROR(VLOOKUP(Data.[[#This Row],[Código]],BV!A:C,3,0),"") -> 46161 | F8: 1058458 | H8: 20610935932 | I8: SERVICIOS GENERALES OPTIMAX E.I.R.L. | J8: SERVICIOS GENERALES OPTIMAX (CA ELIAS AGUIRRE 300 INT A) | K8: =IF(Data.[[#This Row],[Tipo de Venta]]<>"POS","Atendido",IF(Data.[[#This Row],[Fecha de Instalación]]<>"","Atendido","Ingresado")) -> Atendido | L8: =Data.[[#This Row],[Estado]] -> Atendido | M8: POS | N8: =IFERROR(VLOOKUP(Data.[[#This Row],[Código LT]],Reportería.[],20,0),"") | O8: =IFERROR(VLOOKUP(Data.[[#This Row],[Código LT]],Reportería.[],5,0),"") | P8: =Data.[[#This Row],[GPV Mensual LT]]/COUNTIFS(H:H,Data.[[#This Row],[Ruc]],B:B,Data.[[#This Row],[Periodo]]) -> 40000 | Q8: 240000 | R8: Antoni Sifuentes | S8: =VLOOKUP(Data.[[#This Row],[Ejecutivo]],Productividad!D:N,11,0) -> 47045287 | T8: =VLOOKUP(Data.[[#This Row],[DNI Ejecutivo]],Productividad!C:U,8,0) -> asifuentesu@lozapay.com.pe | U8: =VLOOKUP(Data.[[#This Row],[DNI Ejecutivo]],Productividad!C:U,4,0) -> Elite | V8: =IFERROR(VLOOKUP(Data.[[#This Row],[DNI Ejecutivo]],Ejecutivos.[],11,0),"") -> Norte Fuentes | W8: Jorge Fuentes | X8: {=IFERROR(_xlfn.IFS(Data.[[#This Row],[Supervisor]]="Jonathan Lapoint","Norte",Data.[[#This Row],[Supervisor]]="Jorge Fuentes","Norte"),"Lima")} -> Norte | Y8: =VLOOKUP(Data.[[#This Row],[Supervisor]],Ejecutivos!B:S,17,0) -> 70059865 | Z8: =VLOOKUP(Data.[[#This Row],[DNI Supervisor]],Productividad!C:U,8,0) -> jfuentes@lozapay.com.pe | AB8: EDINSON WILLIAMS CHUYES ALDANA | AC8: =IFERROR(CONCATENATE(Data.[[#This Row],[DNI Ejecutivo]],Data.[[#This Row],[Periodo]]),"") -> 4704528746143 | AD8: =IFERROR(VLOOKUP(Data.[[#This Row],[Código LT]],Reportería.[],10,0),"") | AE8: =IFERROR(VLOOKUP(Data.[[#This Row],[Código LT]],Reportería.[],11,0),"") | AF8: 6232 | AI8: =IF(TEXT(Data.[[#This Row],[Periodo]],"mmm-yy")="may-26",VLOOKUP(Data.[[#This Row],[Código]],Reportería!A:BV,57,0),0) -> 4649 | AL8: =IF(Data.[[#This Row],[Vol M0]]="",0,0) -> 0 | AM8: =IF(Data.[[#This Row],[Vol M0]]="",0,0) -> 0 | AN8: =IF(Data.[[#This Row],[Vol M0]]="",0,0) -> 0 | AO8: =IF(Data.[[#This Row],[Vol M0]]="",0,0) -> 0 | AP8: =IF(Data.[[#This Row],[Vol M0]]="",0,0) -> 0 | AQ8: =IF(Data.[[#This Row],[Vol M0]]="",0,0) -> 0 | AR8: =IFERROR(IF(OR(AND(OR(Data.[[#This Row],[Categoría]]="Hunter",Data.[[#This Row],[Categoría]]="Senior"),OR(SUMIFS(AF:AF,H:H,Data.[[#This Row],[Ruc]],B:B,Data.[[#This Row],[Periodo]])>=15000,SUMIFS(AI:AI,H:H,Data.[[#This Row],[Ruc]],B:B,Data.[[#This Row],[Periodo]])>=15000,SUMIFS(AL:AL,H:H,Data.[[#This Row],[Ruc]],B:B,Data.[[#This Row],[Periodo]])>=15000,SUMIFS(AO:AO,H:H,Data.[[#This Row],[Ruc]],B:B,Data.[[#This Row],[Periodo]])>=15000)),AND(Data.[[#This Row],[Categoría]]="Elite",OR(SUMIFS(AF:AF,H:H,Data.[[#This Row],[Ruc]],B:B,Data.[[#This Row],[Periodo]])>=25000,SUMIFS(AI:AI,H:H,Data.[[#This Row],[Ruc]],B:B,Data.[[#This Row],[Periodo]])>=25000,SUMIFS(AL:AL,H:H,Data.[[#This Row],[Ruc]],B:B,Data.[[#This Row],[Periodo]])>=25000,SUMIFS(AO:AO,H:H,Data.[[#This Row],[Ruc]],B:B,Data.[[#This Row],[Periodo]])>=25000))),1,0)/COUNTIFS(H:H,Data.[[#This Row],[Ruc]],B:B,Data.[[#This Row],[Periodo]]),0) -> 0.16666667
A9: =CONCATENATE(Data.[[#This Row],[Código]],Data.[[#This Row],[Ruc]]) -> 105845920610935932 | B9: 46143 | C9: =IFERROR(VLOOKUP(Data.[[#This Row],[Código LT]],Reportería.[],71,0),"") | D9: =IFERROR(VLOOKUP(Data.[[#This Row],[Código]],BV!A:C,2,0),"") -> 46154 | E9: =IFERROR(VLOOKUP(Data.[[#This Row],[Código]],BV!A:C,3,0),"") -> 46161 | F9: 1058459 | H9: 20610935932 | I9: SERVICIOS GENERALES OPTIMAX E.I.R.L. | J9: SERVICIOS GENERALES OPTIMAX (CA ELIAS AGUIRRE 320 TDA 4) | K9: =IF(Data.[[#This Row],[Tipo de Venta]]<>"POS","Atendido",IF(Data.[[#This Row],[Fecha de Instalación]]<>"","Atendido","Ingresado")) -> Atendido | L9: =Data.[[#This Row],[Estado]] -> Atendido | M9: POS | N9: =IFERROR(VLOOKUP(Data.[[#This Row],[Código LT]],Reportería.[],20,0),"") | O9: =IFERROR(VLOOKUP(Data.[[#This Row],[Código LT]],Reportería.[],5,0),"") | P9: =Data.[[#This Row],[GPV Mensual LT]]/COUNTIFS(H:H,Data.[[#This Row],[Ruc]],B:B,Data.[[#This Row],[Periodo]]) -> 40000 | Q9: 240000 | R9: Antoni Sifuentes | S9: =VLOOKUP(Data.[[#This Row],[Ejecutivo]],Productividad!D:N,11,0) -> 47045287 | T9: =VLOOKUP(Data.[[#This Row],[DNI Ejecutivo]],Productividad!C:U,8,0) -> asifuentesu@lozapay.com.pe | U9: =VLOOKUP(Data.[[#This Row],[DNI Ejecutivo]],Productividad!C:U,4,0) -> Elite | V9: =IFERROR(VLOOKUP(Data.[[#This Row],[DNI Ejecutivo]],Ejecutivos.[],11,0),"") -> Norte Fuentes | W9: Jorge Fuentes | X9: {=IFERROR(_xlfn.IFS(Data.[[#This Row],[Supervisor]]="Jonathan Lapoint","Norte",Data.[[#This Row],[Supervisor]]="Jorge Fuentes","Norte"),"Lima")} -> Norte | Y9: =VLOOKUP(Data.[[#This Row],[Supervisor]],Ejecutivos!B:S,17,0) -> 70059865 | Z9: =VLOOKUP(Data.[[#This Row],[DNI Supervisor]],Productividad!C:U,8,0) -> jfuentes@lozapay.com.pe | AB9: EDINSON WILLIAMS CHUYES ALDANA | AC9: =IFERROR(CONCATENATE(Data.[[#This Row],[DNI Ejecutivo]],Data.[[#This Row],[Periodo]]),"") -> 4704528746143 | AD9: =IFERROR(VLOOKUP(Data.[[#This Row],[Código LT]],Reportería.[],10,0),"") | AE9: =IFERROR(VLOOKUP(Data.[[#This Row],[Código LT]],Reportería.[],11,0),"") | AF9: 3007 | AI9: =IF(TEXT(Data.[[#This Row],[Periodo]],"mmm-yy")="may-26",VLOOKUP(Data.[[#This Row],[Código]],Reportería!A:BV,57,0),0) -> 4848 | AL9: =IF(Data.[[#This Row],[Vol M0]]="",0,0) -> 0 | AM9: =IF(Data.[[#This Row],[Vol M0]]="",0,0) -> 0 | AN9: =IF(Data.[[#This Row],[Vol M0]]="",0,0) -> 0 | AO9: =IF(Data.[[#This Row],[Vol M0]]="",0,0) -> 0 | AP9: =IF(Data.[[#This Row],[Vol M0]]="",0,0) -> 0 | AQ9: =IF(Data.[[#This Row],[Vol M0]]="",0,0) -> 0 | AR9: =IFERROR(IF(OR(AND(OR(Data.[[#This Row],[Categoría]]="Hunter",Data.[[#This Row],[Categoría]]="Senior"),OR(SUMIFS(AF:AF,H:H,Data.[[#This Row],[Ruc]],B:B,Data.[[#This Row],[Periodo]])>=15000,SUMIFS(AI:AI,H:H,Data.[[#This Row],[Ruc]],B:B,Data.[[#This Row],[Periodo]])>=15000,SUMIFS(AL:AL,H:H,Data.[[#This Row],[Ruc]],B:B,Data.[[#This Row],[Periodo]])>=15000,SUMIFS(AO:AO,H:H,Data.[[#This Row],[Ruc]],B:B,Data.[[#This Row],[Periodo]])>=15000)),AND(Data.[[#This Row],[Categoría]]="Elite",OR(SUMIFS(AF:AF,H:H,Data.[[#This Row],[Ruc]],B:B,Data.[[#This Row],[Periodo]])>=25000,SUMIFS(AI:AI,H:H,Data.[[#This Row],[Ruc]],B:B,Data.[[#This Row],[Periodo]])>=25000,SUMIFS(AL:AL,H:H,Data.[[#This Row],[Ruc]],B:B,Data.[[#This Row],[Periodo]])>=25000,SUMIFS(AO:AO,H:H,Data.[[#This Row],[Ruc]],B:B,Data.[[#This Row],[Periodo]])>=25000))),1,0)/COUNTIFS(H:H,Data.[[#This Row],[Ruc]],B:B,Data.[[#This Row],[Periodo]]),0) -> 0.16666667
A10: =CONCATENATE(Data.[[#This Row],[Código]],Data.[[#This Row],[Ruc]]) -> 105846020610935932 | B10: 46143 | C10: =IFERROR(VLOOKUP(Data.[[#This Row],[Código LT]],Reportería.[],71,0),"") | D10: =IFERROR(VLOOKUP(Data.[[#This Row],[Código]],BV!A:C,2,0),"") -> 46154 | E10: =IFERROR(VLOOKUP(Data.[[#This Row],[Código]],BV!A:C,3,0),"") -> 46161 | F10: 1058460 | H10: 20610935932 | I10: SERVICIOS GENERALES OPTIMAX E.I.R.L. | J10: SERVICIOS GENERALES OPTIMAX (CA ELIAS AGUIRRE 304-306 INT FONTE) | K10: =IF(Data.[[#This Row],[Tipo de Venta]]<>"POS","Atendido",IF(Data.[[#This Row],[Fecha de Instalación]]<>"","Atendido","Ingresado")) -> Atendido | L10: =Data.[[#This Row],[Estado]] -> Atendido | M10: POS | N10: =IFERROR(VLOOKUP(Data.[[#This Row],[Código LT]],Reportería.[],20,0),"") | O10: =IFERROR(VLOOKUP(Data.[[#This Row],[Código LT]],Reportería.[],5,0),"") | P10: =Data.[[#This Row],[GPV Mensual LT]]/COUNTIFS(H:H,Data.[[#This Row],[Ruc]],B:B,Data.[[#This Row],[Periodo]]) -> 40000 | Q10: 240000 | R10: Antoni Sifuentes | S10: =VLOOKUP(Data.[[#This Row],[Ejecutivo]],Productividad!D:N,11,0) -> 47045287 | T10: =VLOOKUP(Data.[[#This Row],[DNI Ejecutivo]],Productividad!C:U,8,0) -> asifuentesu@lozapay.com.pe | U10: =VLOOKUP(Data.[[#This Row],[DNI Ejecutivo]],Productividad!C:U,4,0) -> Elite | V10: =IFERROR(VLOOKUP(Data.[[#This Row],[DNI Ejecutivo]],Ejecutivos.[],11,0),"") -> Norte Fuentes | W10: Jorge Fuentes | X10: {=IFERROR(_xlfn.IFS(Data.[[#This Row],[Supervisor]]="Jonathan Lapoint","Norte",Data.[[#This Row],[Supervisor]]="Jorge Fuentes","Norte"),"Lima")} -> Norte | Y10: =VLOOKUP(Data.[[#This Row],[Supervisor]],Ejecutivos!B:S,17,0) -> 70059865 | Z10: =VLOOKUP(Data.[[#This Row],[DNI Supervisor]],Productividad!C:U,8,0) -> jfuentes@lozapay.com.pe | AB10: EDINSON WILLIAMS CHUYES ALDANA | AC10: =IFERROR(CONCATENATE(Data.[[#This Row],[DNI Ejecutivo]],Data.[[#This Row],[Periodo]]),"") -> 4704528746143 | AD10: =IFERROR(VLOOKUP(Data.[[#This Row],[Código LT]],Reportería.[],10,0),"") | AE10: =IFERROR(VLOOKUP(Data.[[#This Row],[Código LT]],Reportería.[],11,0),"") | AF10: 4045 | AI10: =IF(TEXT(Data.[[#This Row],[Periodo]],"mmm-yy")="may-26",VLOOKUP(Data.[[#This Row],[Código]],Reportería!A:BV,57,0),0) -> 8115.3 | AL10: =IF(Data.[[#This Row],[Vol M0]]="",0,0) -> 0 | AM10: =IF(Data.[[#This Row],[Vol M0]]="",0,0) -> 0 | AN10: =IF(Data.[[#This Row],[Vol M0]]="",0,0) -> 0 | AO10: =IF(Data.[[#This Row],[Vol M0]]="",0,0) -> 0 | AP10: =IF(Data.[[#This Row],[Vol M0]]="",0,0) -> 0 | AQ10: =IF(Data.[[#This Row],[Vol M0]]="",0,0) -> 0 | AR10: =IFERROR(IF(OR(AND(OR(Data.[[#This Row],[Categoría]]="Hunter",Data.[[#This Row],[Categoría]]="Senior"),OR(SUMIFS(AF:AF,H:H,Data.[[#This Row],[Ruc]],B:B,Data.[[#This Row],[Periodo]])>=15000,SUMIFS(AI:AI,H:H,Data.[[#This Row],[Ruc]],B:B,Data.[[#This Row],[Periodo]])>=15000,SUMIFS(AL:AL,H:H,Data.[[#This Row],[Ruc]],B:B,Data.[[#This Row],[Periodo]])>=15000,SUMIFS(AO:AO,H:H,Data.[[#This Row],[Ruc]],B:B,Data.[[#This Row],[Periodo]])>=15000)),AND(Data.[[#This Row],[Categoría]]="Elite",OR(SUMIFS(AF:AF,H:H,Data.[[#This Row],[Ruc]],B:B,Data.[[#This Row],[Periodo]])>=25000,SUMIFS(AI:AI,H:H,Data.[[#This Row],[Ruc]],B:B,Data.[[#This Row],[Periodo]])>=25000,SUMIFS(AL:AL,H:H,Data.[[#This Row],[Ruc]],B:B,Data.[[#This Row],[Periodo]])>=25000,SUMIFS(AO:AO,H:H,Data.[[#This Row],[Ruc]],B:B,Data.[[#This Row],[Periodo]])>=25000))),1,0)/COUNTIFS(H:H,Data.[[#This Row],[Ruc]],B:B,Data.[[#This Row],[Periodo]]),0) -> 0.16666667
A11: =CONCATENATE(Data.[[#This Row],[Código]],Data.[[#This Row],[Ruc]]) -> 105846220610935932 | B11: 46143 | C11: =IFERROR(VLOOKUP(Data.[[#This Row],[Código LT]],Reportería.[],71,0),"") | D11: =IFERROR(VLOOKUP(Data.[[#This Row],[Código]],BV!A:C,2,0),"") -> 46154 | E11: =IFERROR(VLOOKUP(Data.[[#This Row],[Código]],BV!A:C,3,0),"") -> 46161 | F11: 1058462 | H11: 20610935932 | I11: SERVICIOS GENERALES OPTIMAX E.I.R.L. | J11: SERVICIOS GENERALES OPTIMAX (CA ELIAS AGUIRRE 306) | K11: =IF(Data.[[#This Row],[Tipo de Venta]]<>"POS","Atendido",IF(Data.[[#This Row],[Fecha de Instalación]]<>"","Atendido","Ingresado")) -> Atendido | L11: =Data.[[#This Row],[Estado]] -> Atendido | M11: POS | N11: =IFERROR(VLOOKUP(Data.[[#This Row],[Código LT]],Reportería.[],20,0),"") | O11: =IFERROR(VLOOKUP(Data.[[#This Row],[Código LT]],Reportería.[],5,0),"") | P11: =Data.[[#This Row],[GPV Mensual LT]]/COUNTIFS(H:H,Data.[[#This Row],[Ruc]],B:B,Data.[[#This Row],[Periodo]]) -> 40000 | Q11: 240000 | R11: Antoni Sifuentes | S11: =VLOOKUP(Data.[[#This Row],[Ejecutivo]],Productividad!D:N,11,0) -> 47045287 | T11: =VLOOKUP(Data.[[#This Row],[DNI Ejecutivo]],Productividad!C:U,8,0) -> asifuentesu@lozapay.com.pe | U11: =VLOOKUP(Data.[[#This Row],[DNI Ejecutivo]],Productividad!C:U,4,0) -> Elite | V11: =IFERROR(VLOOKUP(Data.[[#This Row],[DNI Ejecutivo]],Ejecutivos.[],11,0),"") -> Norte Fuentes | W11: Jorge Fuentes | X11: {=IFERROR(_xlfn.IFS(Data.[[#This Row],[Supervisor]]="Jonathan Lapoint","Norte",Data.[[#This Row],[Supervisor]]="Jorge Fuentes","Norte"),"Lima")} -> Norte | Y11: =VLOOKUP(Data.[[#This Row],[Supervisor]],Ejecutivos!B:S,17,0) -> 70059865 | Z11: =VLOOKUP(Data.[[#This Row],[DNI Supervisor]],Productividad!C:U,8,0) -> jfuentes@lozapay.com.pe | AB11: EDINSON WILLIAMS CHUYES ALDANA | AC11: =IFERROR(CONCATENATE(Data.[[#This Row],[DNI Ejecutivo]],Data.[[#This Row],[Periodo]]),"") -> 4704528746143 | AD11: =IFERROR(VLOOKUP(Data.[[#This Row],[Código LT]],Reportería.[],10,0),"") | AE11: =IFERROR(VLOOKUP(Data.[[#This Row],[Código LT]],Reportería.[],11,0),"") | AF11: 2733 | AI11: =IF(TEXT(Data.[[#This Row],[Periodo]],"mmm-yy")="may-26",VLOOKUP(Data.[[#This Row],[Código]],Reportería!A:BV,57,0),0) -> 3942 | AL11: =IF(Data.[[#This Row],[Vol M0]]="",0,0) -> 0 | AM11: =IF(Data.[[#This Row],[Vol M0]]="",0,0) -> 0 | AN11: =IF(Data.[[#This Row],[Vol M0]]="",0,0) -> 0 | AO11: =IF(Data.[[#This Row],[Vol M0]]="",0,0) -> 0 | AP11: =IF(Data.[[#This Row],[Vol M0]]="",0,0) -> 0 | AQ11: =IF(Data.[[#This Row],[Vol M0]]="",0,0) -> 0 | AR11: =IFERROR(IF(OR(AND(OR(Data.[[#This Row],[Categoría]]="Hunter",Data.[[#This Row],[Categoría]]="Senior"),OR(SUMIFS(AF:AF,H:H,Data.[[#This Row],[Ruc]],B:B,Data.[[#This Row],[Periodo]])>=15000,SUMIFS(AI:AI,H:H,Data.[[#This Row],[Ruc]],B:B,Data.[[#This Row],[Periodo]])>=15000,SUMIFS(AL:AL,H:H,Data.[[#This Row],[Ruc]],B:B,Data.[[#This Row],[Periodo]])>=15000,SUMIFS(AO:AO,H:H,Data.[[#This Row],[Ruc]],B:B,Data.[[#This Row],[Periodo]])>=15000)),AND(Data.[[#This Row],[Categoría]]="Elite",OR(SUMIFS(AF:AF,H:H,Data.[[#This Row],[Ruc]],B:B,Data.[[#This Row],[Periodo]])>=25000,SUMIFS(AI:AI,H:H,Data.[[#This Row],[Ruc]],B:B,Data.[[#This Row],[Periodo]])>=25000,SUMIFS(AL:AL,H:H,Data.[[#This Row],[Ruc]],B:B,Data.[[#This Row],[Periodo]])>=25000,SUMIFS(AO:AO,H:H,Data.[[#This Row],[Ruc]],B:B,Data.[[#This Row],[Periodo]])>=25000))),1,0)/COUNTIFS(H:H,Data.[[#This Row],[Ruc]],B:B,Data.[[#This Row],[Periodo]]),0) -> 0.16666667
A12: =CONCATENATE(Data.[[#This Row],[Código]],Data.[[#This Row],[Ruc]]) -> 594683820615538222 | B12: 46143 | C12: =IFERROR(VLOOKUP(Data.[[#This Row],[Código LT]],Reportería.[],71,0),"") | D12: =IFERROR(VLOOKUP(Data.[[#This Row],[Código]],BV!A:C,2,0),"") -> 46154 | E12: =IFERROR(VLOOKUP(Data.[[#This Row],[Código]],BV!A:C,3,0),"") -> 46155 | F12: 5946838 | G12: TJ33261A21090 | H12: 20615538222 | I12: D & C GROUP SOLUTIONS S.A.C. | J12: D&C GROUP SOLUTIONS | K12: =IF(Data.[[#This Row],[Tipo de Venta]]<>"POS","Atendido",IF(Data.[[#This Row],[Fecha de Instalación]]<>"","Atendido","Ingresado")) -> Atendido | L12: =Data.[[#This Row],[Estado]] -> Atendido | M12: POS | N12: =IFERROR(VLOOKUP(Data.[[#This Row],[Código LT]],Reportería.[],20,0),"") | O12: =IFERROR(VLOOKUP(Data.[[#This Row],[Código LT]],Reportería.[],5,0),"") | P12: =Data.[[#This Row],[GPV Mensual LT]]/COUNTIFS(H:H,Data.[[#This Row],[Ruc]],B:B,Data.[[#This Row],[Periodo]]) -> 27000 | Q12: 27000 | R12: Richard Benites | S12: =VLOOKUP(Data.[[#This Row],[Ejecutivo]],Productividad!D:N,11,0) -> 70151010 | T12: =VLOOKUP(Data.[[#This Row],[DNI Ejecutivo]],Productividad!C:U,8,0) -> richard.benites@lozapay.com.pe | U12: =VLOOKUP(Data.[[#This Row],[DNI Ejecutivo]],Productividad!C:U,4,0) -> Hunter | V12: =IFERROR(VLOOKUP(Data.[[#This Row],[DNI Ejecutivo]],Ejecutivos.[],11,0),"") -> Lima Jean | W12: Jean Aguilar | X12: {=IFERROR(_xlfn.IFS(Data.[[#This Row],[Supervisor]]="Jonathan Lapoint","Norte",Data.[[#This Row],[Supervisor]]="Jorge Fuentes","Norte"),"Lima")} -> Lima | Y12: =VLOOKUP(Data.[[#This Row],[Supervisor]],Ejecutivos!B:S,17,0) -> 47688341 | Z12: =VLOOKUP(Data.[[#This Row],[DNI Supervisor]],Productividad!C:U,8,0) -> jaguilar@lozapay.com.pe | AB12: RICHARD PABLO BENITES JURADO | AC12: =IFERROR(CONCATENATE(Data.[[#This Row],[DNI Ejecutivo]],Data.[[#This Row],[Periodo]]),"") -> 7015101046143 | AD12: =IFERROR(VLOOKUP(Data.[[#This Row],[Código LT]],Reportería.[],10,0),"") | AE12: =IFERROR(VLOOKUP(Data.[[#This Row],[Código LT]],Reportería.[],11,0),"") | AF12: 0 | AI12: =IF(TEXT(Data.[[#This Row],[Periodo]],"mmm-yy")="may-26",VLOOKUP(Data.[[#This Row],[Código]],Reportería!A:BV,57,0),0) -> 1000 | AL12: =IF(Data.[[#This Row],[Vol M0]]="",0,0) -> 0 | AM12: =IF(Data.[[#This Row],[Vol M0]]="",0,0) -> 0 | AN12: =IF(Data.[[#This Row],[Vol M0]]="",0,0) -> 0 | AO12: =IF(Data.[[#This Row],[Vol M0]]="",0,0) -> 0 | AP12: =IF(Data.[[#This Row],[Vol M0]]="",0,0) -> 0 | AQ12: =IF(Data.[[#This Row],[Vol M0]]="",0,0) -> 0 | AR12: =IFERROR(IF(OR(AND(OR(Data.[[#This Row],[Categoría]]="Hunter",Data.[[#This Row],[Categoría]]="Senior"),OR(SUMIFS(AF:AF,H:H,Data.[[#This Row],[Ruc]],B:B,Data.[[#This Row],[Periodo]])>=15000,SUMIFS(AI:AI,H:H,Data.[[#This Row],[Ruc]],B:B,Data.[[#This Row],[Periodo]])>=15000,SUMIFS(AL:AL,H:H,Data.[[#This Row],[Ruc]],B:B,Data.[[#This Row],[Periodo]])>=15000,SUMIFS(AO:AO,H:H,Data.[[#This Row],[Ruc]],B:B,Data.[[#This Row],[Periodo]])>=15000)),AND(Data.[[#This Row],[Categoría]]="Elite",OR(SUMIFS(AF:AF,H:H,Data.[[#This Row],[Ruc]],B:B,Data.[[#This Row],[Periodo]])>=25000,SUMIFS(AI:AI,H:H,Data.[[#This Row],[Ruc]],B:B,Data.[[#This Row],[Periodo]])>=25000,SUMIFS(AL:AL,H:H,Data.[[#This Row],[Ruc]],B:B,Data.[[#This Row],[Periodo]])>=25000,SUMIFS(AO:AO,H:H,Data.[[#This Row],[Ruc]],B:B,Data.[[#This Row],[Periodo]])>=25000))),1,0)/COUNTIFS(H:H,Data.[[#This Row],[Ruc]],B:B,Data.[[#This Row],[Periodo]]),0) -> 0
A13: =CONCATENATE(Data.[[#This Row],[Código]],Data.[[#This Row],[Ruc]]) -> 594682710413980076 | B13: 46143 | C13: =IFERROR(VLOOKUP(Data.[[#This Row],[Código LT]],Reportería.[],71,0),"") | D13: =IFERROR(VLOOKUP(Data.[[#This Row],[Código]],BV!A:C,2,0),"") -> 46154 | E13: =IFERROR(VLOOKUP(Data.[[#This Row],[Código]],BV!A:C,3,0),"") -> 46155 | F13: 5946827 | G13: TJ33261920006 | H13: 10413980076 | I13: DAVALOS GUTIERREZ MIRIAN KARINA | J13: Arilustore | K13: =IF(Data.[[#This Row],[Tipo de Venta]]<>"POS","Atendido",IF(Data.[[#This Row],[Fecha de Instalación]]<>"","Atendido","Ingresado")) -> Atendido | L13: =Data.[[#This Row],[Estado]] -> Atendido | M13: POS | N13: =IFERROR(VLOOKUP(Data.[[#This Row],[Código LT]],Reportería.[],20,0),"") | O13: =IFERROR(VLOOKUP(Data.[[#This Row],[Código LT]],Reportería.[],5,0),"") | P13: =Data.[[#This Row],[GPV Mensual LT]]/COUNTIFS(H:H,Data.[[#This Row],[Ruc]],B:B,Data.[[#This Row],[Periodo]]) -> 25000 | Q13: 25000 | R13: Jonathan Lavado | S13: =VLOOKUP(Data.[[#This Row],[Ejecutivo]],Productividad!D:N,11,0) -> 41309076 | T13: =VLOOKUP(Data.[[#This Row],[DNI Ejecutivo]],Productividad!C:U,8,0) -> jonathan.lavado@lozapay.com.pe | U13: =VLOOKUP(Data.[[#This Row],[DNI Ejecutivo]],Productividad!C:U,4,0) -> Hunter | V13: =IFERROR(VLOOKUP(Data.[[#This Row],[DNI Ejecutivo]],Ejecutivos.[],11,0),"") -> Lima Jean | W13: Jean Aguilar | X13: {=IFERROR(_xlfn.IFS(Data.[[#This Row],[Supervisor]]="Jonathan Lapoint","Norte",Data.[[#This Row],[Supervisor]]="Jorge Fuentes","Norte"),"Lima")} -> Lima | Y13: =VLOOKUP(Data.[[#This Row],[Supervisor]],Ejecutivos!B:S,17,0) -> 47688341 | Z13: =VLOOKUP(Data.[[#This Row],[DNI Supervisor]],Productividad!C:U,8,0) -> jaguilar@lozapay.com.pe | AB13: JONATHAN ALEXANDER LAVADO CADERO | AC13: =IFERROR(CONCATENATE(Data.[[#This Row],[DNI Ejecutivo]],Data.[[#This Row],[Periodo]]),"") -> 4130907646143 | AD13: =IFERROR(VLOOKUP(Data.[[#This Row],[Código LT]],Reportería.[],10,0),"") | AE13: =IFERROR(VLOOKUP(Data.[[#This Row],[Código LT]],Reportería.[],11,0),"") | AF13: 486 | AI13: =IF(TEXT(Data.[[#This Row],[Periodo]],"mmm-yy")="may-26",VLOOKUP(Data.[[#This Row],[Código]],Reportería!A:BV,57,0),0) -> 976 | AL13: =IF(Data.[[#This Row],[Vol M0]]="",0,0) -> 0 | AM13: =IF(Data.[[#This Row],[Vol M0]]="",0,0) -> 0 | AN13: =IF(Data.[[#This Row],[Vol M0]]="",0,0) -> 0 | AO13: =IF(Data.[[#This Row],[Vol M0]]="",0,0) -> 0 | AP13: =IF(Data.[[#This Row],[Vol M0]]="",0,0) -> 0 | AQ13: =IF(Data.[[#This Row],[Vol M0]]="",0,0) -> 0 | AR13: =IFERROR(IF(OR(AND(OR(Data.[[#This Row],[Categoría]]="Hunter",Data.[[#This Row],[Categoría]]="Senior"),OR(SUMIFS(AF:AF,H:H,Data.[[#This Row],[Ruc]],B:B,Data.[[#This Row],[Periodo]])>=15000,SUMIFS(AI:AI,H:H,Data.[[#This Row],[Ruc]],B:B,Data.[[#This Row],[Periodo]])>=15000,SUMIFS(AL:AL,H:H,Data.[[#This Row],[Ruc]],B:B,Data.[[#This Row],[Periodo]])>=15000,SUMIFS(AO:AO,H:H,Data.[[#This Row],[Ruc]],B:B,Data.[[#This Row],[Periodo]])>=15000)),AND(Data.[[#This Row],[Categoría]]="Elite",OR(SUMIFS(AF:AF,H:H,Data.[[#This Row],[Ruc]],B:B,Data.[[#This Row],[Periodo]])>=25000,SUMIFS(AI:AI,H:H,Data.[[#This Row],[Ruc]],B:B,Data.[[#This Row],[Periodo]])>=25000,SUMIFS(AL:AL,H:H,Data.[[#This Row],[Ruc]],B:B,Data.[[#This Row],[Periodo]])>=25000,SUMIFS(AO:AO,H:H,Data.[[#This Row],[Ruc]],B:B,Data.[[#This Row],[Periodo]])>=25000))),1,0)/COUNTIFS(H:H,Data.[[#This Row],[Ruc]],B:B,Data.[[#This Row],[Periodo]]),0) -> 0
A14: =CONCATENATE(Data.[[#This Row],[Código]],Data.[[#This Row],[Ruc]]) -> 594764920614514338 | B14: 46143 | C14: =IFERROR(VLOOKUP(Data.[[#This Row],[Código LT]],Reportería.[],71,0),"") | D14: =IFERROR(VLOOKUP(Data.[[#This Row],[Código]],BV!A:C,2,0),"") -> 46156 | E14: =IFERROR(VLOOKUP(Data.[[#This Row],[Código]],BV!A:C,3,0),"") -> 46157 | F14: 5947649 | G14: TJ33261C21165 | H14: 20614514338 | I14: S. Y M. GRUPO CORPORACION INTERAMERICANA S.A.C. | J14: BRANS CHICKEN 1 | K14: =IF(Data.[[#This Row],[Tipo de Venta]]<>"POS","Atendido",IF(Data.[[#This Row],[Fecha de Instalación]]<>"","Atendido","Ingresado")) -> Atendido | L14: =Data.[[#This Row],[Estado]] -> Atendido | M14: POS | N14: =IFERROR(VLOOKUP(Data.[[#This Row],[Código LT]],Reportería.[],20,0),"") | O14: =IFERROR(VLOOKUP(Data.[[#This Row],[Código LT]],Reportería.[],5,0),"") | P14: =Data.[[#This Row],[GPV Mensual LT]]/COUNTIFS(H:H,Data.[[#This Row],[Ruc]],B:B,Data.[[#This Row],[Periodo]]) -> 25000 | Q14: 50000 | R14: Edinson Chuyes | S14: =VLOOKUP(Data.[[#This Row],[Ejecutivo]],Productividad!D:N,11,0) -> 45311691 | T14: =VLOOKUP(Data.[[#This Row],[DNI Ejecutivo]],Productividad!C:U,8,0) -> edinson.chuyes@lozapay.com.pe | U14: =VLOOKUP(Data.[[#This Row],[DNI Ejecutivo]],Productividad!C:U,4,0) -> Elite | V14: =IFERROR(VLOOKUP(Data.[[#This Row],[DNI Ejecutivo]],Ejecutivos.[],11,0),"") -> Lima Jean | W14: Jean Aguilar | X14: {=IFERROR(_xlfn.IFS(Data.[[#This Row],[Supervisor]]="Jonathan Lapoint","Norte",Data.[[#This Row],[Supervisor]]="Jorge Fuentes","Norte"),"Lima")} -> Lima | Y14: =VLOOKUP(Data.[[#This Row],[Supervisor]],Ejecutivos!B:S,17,0) -> 47688341 | Z14: =VLOOKUP(Data.[[#This Row],[DNI Supervisor]],Productividad!C:U,8,0) -> jaguilar@lozapay.com.pe | AB14: EDINSON WILLIAMS CHUYES ALDANA | AC14: =IFERROR(CONCATENATE(Data.[[#This Row],[DNI Ejecutivo]],Data.[[#This Row],[Periodo]]),"") -> 4531169146143 | AD14: =IFERROR(VLOOKUP(Data.[[#This Row],[Código LT]],Reportería.[],10,0),"") | AE14: =IFERROR(VLOOKUP(Data.[[#This Row],[Código LT]],Reportería.[],11,0),"") | AF14: 21455.5 | AI14: =IF(TEXT(Data.[[#This Row],[Periodo]],"mmm-yy")="may-26",VLOOKUP(Data.[[#This Row],[Código]],Reportería!A:BV,57,0),0) -> 14201.5 | AL14: =IF(Data.[[#This Row],[Vol M0]]="",0,0) -> 0 | AM14: =IF(Data.[[#This Row],[Vol M0]]="",0,0) -> 0 | AN14: =IF(Data.[[#This Row],[Vol M0]]="",0,0) -> 0 | AO14: =IF(Data.[[#This Row],[Vol M0]]="",0,0) -> 0 | AP14: =IF(Data.[[#This Row],[Vol M0]]="",0,0) -> 0 | AQ14: =IF(Data.[[#This Row],[Vol M0]]="",0,0) -> 0 | AR14: =IFERROR(IF(OR(AND(OR(Data.[[#This Row],[Categoría]]="Hunter",Data.[[#This Row],[Categoría]]="Senior"),OR(SUMIFS(AF:AF,H:H,Data.[[#This Row],[Ruc]],B:B,Data.[[#This Row],[Periodo]])>=15000,SUMIFS(AI:AI,H:H,Data.[[#This Row],[Ruc]],B:B,Data.[[#This Row],[Periodo]])>=15000,SUMIFS(AL:AL,H:H,Data.[[#This Row],[Ruc]],B:B,Data.[[#This Row],[Periodo]])>=15000,SUMIFS(AO:AO,H:H,Data.[[#This Row],[Ruc]],B:B,Data.[[#This Row],[Periodo]])>=15000)),AND(Data.[[#This Row],[Categoría]]="Elite",OR(SUMIFS(AF:AF,H:H,Data.[[#This Row],[Ruc]],B:B,Data.[[#This Row],[Periodo]])>=25000,SUMIFS(AI:AI,H:H,Data.[[#This Row],[Ruc]],B:B,Data.[[#This Row],[Periodo]])>=25000,SUMIFS(AL:AL,H:H,Data.[[#This Row],[Ruc]],B:B,Data.[[#This Row],[Periodo]])>=25000,SUMIFS(AO:AO,H:H,Data.[[#This Row],[Ruc]],B:B,Data.[[#This Row],[Periodo]])>=25000))),1,0)/COUNTIFS(H:H,Data.[[#This Row],[Ruc]],B:B,Data.[[#This Row],[Periodo]]),0) -> 0.5
A15: =CONCATENATE(Data.[[#This Row],[Código]],Data.[[#This Row],[Ruc]]) -> 594779320614514338 | B15: 46143 | C15: =IFERROR(VLOOKUP(Data.[[#This Row],[Código LT]],Reportería.[],71,0),"") | D15: =IFERROR(VLOOKUP(Data.[[#This Row],[Código]],BV!A:C,2,0),"") -> 46156 | E15: =IFERROR(VLOOKUP(Data.[[#This Row],[Código]],BV!A:C,3,0),"") -> 46160 | F15: 5947793 | G15: TJ33261C21512 | H15: 20614514338 | I15: S. Y M. GRUPO CORPORACION INTERAMERICANA S.A.C. | J15: BRANS CHICKEN 2 | K15: =IF(Data.[[#This Row],[Tipo de Venta]]<>"POS","Atendido",IF(Data.[[#This Row],[Fecha de Instalación]]<>"","Atendido","Ingresado")) -> Atendido | L15: =Data.[[#This Row],[Estado]] -> Atendido | M15: POS | N15: =IFERROR(VLOOKUP(Data.[[#This Row],[Código LT]],Reportería.[],20,0),"") | O15: =IFERROR(VLOOKUP(Data.[[#This Row],[Código LT]],Reportería.[],5,0),"") | P15: =Data.[[#This Row],[GPV Mensual LT]]/COUNTIFS(H:H,Data.[[#This Row],[Ruc]],B:B,Data.[[#This Row],[Periodo]]) -> 25000 | Q15: 50000 | R15: Edinson Chuyes | S15: =VLOOKUP(Data.[[#This Row],[Ejecutivo]],Productividad!D:N,11,0) -> 45311691 | T15: =VLOOKUP(Data.[[#This Row],[DNI Ejecutivo]],Productividad!C:U,8,0) -> edinson.chuyes@lozapay.com.pe | U15: =VLOOKUP(Data.[[#This Row],[DNI Ejecutivo]],Productividad!C:U,4,0) -> Elite | V15: =IFERROR(VLOOKUP(Data.[[#This Row],[DNI Ejecutivo]],Ejecutivos.[],11,0),"") -> Lima Jean | W15: Jean Aguilar | X15: {=IFERROR(_xlfn.IFS(Data.[[#This Row],[Supervisor]]="Jonathan Lapoint","Norte",Data.[[#This Row],[Supervisor]]="Jorge Fuentes","Norte"),"Lima")} -> Lima | Y15: =VLOOKUP(Data.[[#This Row],[Supervisor]],Ejecutivos!B:S,17,0) -> 47688341 | Z15: =VLOOKUP(Data.[[#This Row],[DNI Supervisor]],Productividad!C:U,8,0) -> jaguilar@lozapay.com.pe | AB15: EDINSON WILLIAMS CHUYES ALDANA | AC15: =IFERROR(CONCATENATE(Data.[[#This Row],[DNI Ejecutivo]],Data.[[#This Row],[Periodo]]),"") -> 4531169146143 | AD15: =IFERROR(VLOOKUP(Data.[[#This Row],[Código LT]],Reportería.[],10,0),"") | AE15: =IFERROR(VLOOKUP(Data.[[#This Row],[Código LT]],Reportería.[],11,0),"") | AF15: 14455 | AI15: =IF(TEXT(Data.[[#This Row],[Periodo]],"mmm-yy")="may-26",VLOOKUP(Data.[[#This Row],[Código]],Reportería!A:BV,57,0),0) -> 12849.5 | AL15: =IF(Data.[[#This Row],[Vol M0]]="",0,0) -> 0 | AM15: =IF(Data.[[#This Row],[Vol M0]]="",0,0) -> 0 | AN15: =IF(Data.[[#This Row],[Vol M0]]="",0,0) -> 0 | AO15: =IF(Data.[[#This Row],[Vol M0]]="",0,0) -> 0 | AP15: =IF(Data.[[#This Row],[Vol M0]]="",0,0) -> 0 | AQ15: =IF(Data.[[#This Row],[Vol M0]]="",0,0) -> 0 | AR15: =IFERROR(IF(OR(AND(OR(Data.[[#This Row],[Categoría]]="Hunter",Data.[[#This Row],[Categoría]]="Senior"),OR(SUMIFS(AF:AF,H:H,Data.[[#This Row],[Ruc]],B:B,Data.[[#This Row],[Periodo]])>=15000,SUMIFS(AI:AI,H:H,Data.[[#This Row],[Ruc]],B:B,Data.[[#This Row],[Periodo]])>=15000,SUMIFS(AL:AL,H:H,Data.[[#This Row],[Ruc]],B:B,Data.[[#This Row],[Periodo]])>=15000,SUMIFS(AO:AO,H:H,Data.[[#This Row],[Ruc]],B:B,Data.[[#This Row],[Periodo]])>=15000)),AND(Data.[[#This Row],[Categoría]]="Elite",OR(SUMIFS(AF:AF,H:H,Data.[[#This Row],[Ruc]],B:B,Data.[[#This Row],[Periodo]])>=25000,SUMIFS(AI:AI,H:H,Data.[[#This Row],[Ruc]],B:B,Data.[[#This Row],[Periodo]])>=25000,SUMIFS(AL:AL,H:H,Data.[[#This Row],[Ruc]],B:B,Data.[[#This Row],[Periodo]])>=25000,SUMIFS(AO:AO,H:H,Data.[[#This Row],[Ruc]],B:B,Data.[[#This Row],[Periodo]])>=25000))),1,0)/COUNTIFS(H:H,Data.[[#This Row],[Ruc]],B:B,Data.[[#This Row],[Periodo]]),0) -> 0.5
A16: =CONCATENATE(Data.[[#This Row],[Código]],Data.[[#This Row],[Ruc]]) -> 594765120612598780 | B16: 46143 | C16: =IFERROR(VLOOKUP(Data.[[#This Row],[Código LT]],Reportería.[],71,0),"") | D16: =IFERROR(VLOOKUP(Data.[[#This Row],[Código]],BV!A:C,2,0),"") -> 46157 | E16: =IFERROR(VLOOKUP(Data.[[#This Row],[Código]],BV!A:C,3,0),"") -> 46160 | F16: 5947651 | G16: TJ33261A20003 | H16: 20612598780 | I16: ANSOF COMPANY S.A.C.S. | J16: SAUNA TOKIO | K16: =IF(Data.[[#This Row],[Tipo de Venta]]<>"POS","Atendido",IF(Data.[[#This Row],[Fecha de Instalación]]<>"","Atendido","Ingresado")) -> Atendido | L16: =Data.[[#This Row],[Estado]] -> Atendido | M16: POS | N16: =IFERROR(VLOOKUP(Data.[[#This Row],[Código LT]],Reportería.[],20,0),"") | O16: =IFERROR(VLOOKUP(Data.[[#This Row],[Código LT]],Reportería.[],5,0),"") | P16: =Data.[[#This Row],[GPV Mensual LT]]/COUNTIFS(H:H,Data.[[#This Row],[Ruc]],B:B,Data.[[#This Row],[Periodo]]) -> 90000 | Q16: 180000 | R16: Maria Godoy | S16: =VLOOKUP(Data.[[#This Row],[Ejecutivo]],Productividad!D:N,11,0) -> 46998250 | T16: =VLOOKUP(Data.[[#This Row],[DNI Ejecutivo]],Productividad!C:U,8,0) -> mgodoyc@lozapay.com.pe | U16: =VLOOKUP(Data.[[#This Row],[DNI Ejecutivo]],Productividad!C:U,4,0) -> Elite | V16: =IFERROR(VLOOKUP(Data.[[#This Row],[DNI Ejecutivo]],Ejecutivos.[],11,0),"") -> Lima Palomino | W16: Carlos Palomino | X16: {=IFERROR(_xlfn.IFS(Data.[[#This Row],[Supervisor]]="Jonathan Lapoint","Norte",Data.[[#This Row],[Supervisor]]="Jorge Fuentes","Norte"),"Lima")} -> Lima | Y16: =VLOOKUP(Data.[[#This Row],[Supervisor]],Ejecutivos!B:S,17,0) -> 41718975 | Z16: =VLOOKUP(Data.[[#This Row],[DNI Supervisor]],Productividad!C:U,8,0) -> carlos.palomino@lozapay.com.pe | AB16: MARIA JOHANA GODOY CRUZ | AC16: =IFERROR(CONCATENATE(Data.[[#This Row],[DNI Ejecutivo]],Data.[[#This Row],[Periodo]]),"") -> 4699825046143 | AD16: =IFERROR(VLOOKUP(Data.[[#This Row],[Código LT]],Reportería.[],10,0),"") | AE16: =IFERROR(VLOOKUP(Data.[[#This Row],[Código LT]],Reportería.[],11,0),"") | AF16: 17809 | AI16: =IF(TEXT(Data.[[#This Row],[Periodo]],"mmm-yy")="may-26",VLOOKUP(Data.[[#This Row],[Código]],Reportería!A:BV,57,0),0) -> 19100 | AL16: =IF(Data.[[#This Row],[Vol M0]]="",0,0) -> 0 | AM16: =IF(Data.[[#This Row],[Vol M0]]="",0,0) -> 0 | AN16: =IF(Data.[[#This Row],[Vol M0]]="",0,0) -> 0 | AO16: =IF(Data.[[#This Row],[Vol M0]]="",0,0) -> 0 | AP16: =IF(Data.[[#This Row],[Vol M0]]="",0,0) -> 0 | AQ16: =IF(Data.[[#This Row],[Vol M0]]="",0,0) -> 0 | AR16: =IFERROR(IF(OR(AND(OR(Data.[[#This Row],[Categoría]]="Hunter",Data.[[#This Row],[Categoría]]="Senior"),OR(SUMIFS(AF:AF,H:H,Data.[[#This Row],[Ruc]],B:B,Data.[[#This Row],[Periodo]])>=15000,SUMIFS(AI:AI,H:H,Data.[[#This Row],[Ruc]],B:B,Data.[[#This Row],[Periodo]])>=15000,SUMIFS(AL:AL,H:H,Data.[[#This Row],[Ruc]],B:B,Data.[[#This Row],[Periodo]])>=15000,SUMIFS(AO:AO,H:H,Data.[[#This Row],[Ruc]],B:B,Data.[[#This Row],[Periodo]])>=15000)),AND(Data.[[#This Row],[Categoría]]="Elite",OR(SUMIFS(AF:AF,H:H,Data.[[#This Row],[Ruc]],B:B,Data.[[#This Row],[Periodo]])>=25000,SUMIFS(AI:AI,H:H,Data.[[#This Row],[Ruc]],B:B,Data.[[#This Row],[Periodo]])>=25000,SUMIFS(AL:AL,H:H,Data.[[#This Row],[Ruc]],B:B,Data.[[#This Row],[Periodo]])>=25000,SUMIFS(AO:AO,H:H,Data.[[#This Row],[Ruc]],B:B,Data.[[#This Row],[Periodo]])>=25000))),1,0)/COUNTIFS(H:H,Data.[[#This Row],[Ruc]],B:B,Data.[[#This Row],[Periodo]]),0) -> 0
A17: =CONCATENATE(Data.[[#This Row],[Código]],Data.[[#This Row],[Ruc]]) -> 594777520612598780 | B17: 46143 | C17: =IFERROR(VLOOKUP(Data.[[#This Row],[Código LT]],Reportería.[],71,0),"") | D17: =IFERROR(VLOOKUP(Data.[[#This Row],[Código]],BV!A:C,2,0),"") -> 46157 | E17: =IFERROR(VLOOKUP(Data.[[#This Row],[Código]],BV!A:C,3,0),"") -> 46160 | F17: 5947775 | G17: TJ33261A20244 | H17: 20612598780 | I17: ANSOF COMPANY S.A.C.S. | J17: SAUNA TOKIO | K17: =IF(Data.[[#This Row],[Tipo de Venta]]<>"POS","Atendido",IF(Data.[[#This Row],[Fecha de Instalación]]<>"","Atendido","Ingresado")) -> Atendido | L17: =Data.[[#This Row],[Estado]] -> Atendido | M17: POS | N17: =IFERROR(VLOOKUP(Data.[[#This Row],[Código LT]],Reportería.[],20,0),"") | O17: =IFERROR(VLOOKUP(Data.[[#This Row],[Código LT]],Reportería.[],5,0),"") | P17: =Data.[[#This Row],[GPV Mensual LT]]/COUNTIFS(H:H,Data.[[#This Row],[Ruc]],B:B,Data.[[#This Row],[Periodo]]) -> 90000 | Q17: 180000 | R17: Maria Godoy | S17: =VLOOKUP(Data.[[#This Row],[Ejecutivo]],Productividad!D:N,11,0) -> 46998250 | T17: =VLOOKUP(Data.[[#This Row],[DNI Ejecutivo]],Productividad!C:U,8,0) -> mgodoyc@lozapay.com.pe | U17: =VLOOKUP(Data.[[#This Row],[DNI Ejecutivo]],Productividad!C:U,4,0) -> Elite | V17: =IFERROR(VLOOKUP(Data.[[#This Row],[DNI Ejecutivo]],Ejecutivos.[],11,0),"") -> Lima Palomino | W17: Carlos Palomino | X17: {=IFERROR(_xlfn.IFS(Data.[[#This Row],[Supervisor]]="Jonathan Lapoint","Norte",Data.[[#This Row],[Supervisor]]="Jorge Fuentes","Norte"),"Lima")} -> Lima | Y17: =VLOOKUP(Data.[[#This Row],[Supervisor]],Ejecutivos!B:S,17,0) -> 41718975 | Z17: =VLOOKUP(Data.[[#This Row],[DNI Supervisor]],Productividad!C:U,8,0) -> carlos.palomino@lozapay.com.pe | AB17: MARIA JOHANA GODOY CRUZ | AC17: =IFERROR(CONCATENATE(Data.[[#This Row],[DNI Ejecutivo]],Data.[[#This Row],[Periodo]]),"") -> 4699825046143 | AD17: =IFERROR(VLOOKUP(Data.[[#This Row],[Código LT]],Reportería.[],10,0),"") | AE17: =IFERROR(VLOOKUP(Data.[[#This Row],[Código LT]],Reportería.[],11,0),"") | AF17: 2931 | AI17: =IF(TEXT(Data.[[#This Row],[Periodo]],"mmm-yy")="may-26",VLOOKUP(Data.[[#This Row],[Código]],Reportería!A:BV,57,0),0) -> 2844.9 | AL17: =IF(Data.[[#This Row],[Vol M0]]="",0,0) -> 0 | AM17: =IF(Data.[[#This Row],[Vol M0]]="",0,0) -> 0 | AN17: =IF(Data.[[#This Row],[Vol M0]]="",0,0) -> 0 | AO17: =IF(Data.[[#This Row],[Vol M0]]="",0,0) -> 0 | AP17: =IF(Data.[[#This Row],[Vol M0]]="",0,0) -> 0 | AQ17: =IF(Data.[[#This Row],[Vol M0]]="",0,0) -> 0 | AR17: =IFERROR(IF(OR(AND(OR(Data.[[#This Row],[Categoría]]="Hunter",Data.[[#This Row],[Categoría]]="Senior"),OR(SUMIFS(AF:AF,H:H,Data.[[#This Row],[Ruc]],B:B,Data.[[#This Row],[Periodo]])>=15000,SUMIFS(AI:AI,H:H,Data.[[#This Row],[Ruc]],B:B,Data.[[#This Row],[Periodo]])>=15000,SUMIFS(AL:AL,H:H,Data.[[#This Row],[Ruc]],B:B,Data.[[#This Row],[Periodo]])>=15000,SUMIFS(AO:AO,H:H,Data.[[#This Row],[Ruc]],B:B,Data.[[#This Row],[Periodo]])>=15000)),AND(Data.[[#This Row],[Categoría]]="Elite",OR(SUMIFS(AF:AF,H:H,Data.[[#This Row],[Ruc]],B:B,Data.[[#This Row],[Periodo]])>=25000,SUMIFS(AI:AI,H:H,Data.[[#This Row],[Ruc]],B:B,Data.[[#This Row],[Periodo]])>=25000,SUMIFS(AL:AL,H:H,Data.[[#This Row],[Ruc]],B:B,Data.[[#This Row],[Periodo]])>=25000,SUMIFS(AO:AO,H:H,Data.[[#This Row],[Ruc]],B:B,Data.[[#This Row],[Periodo]])>=25000))),1,0)/COUNTIFS(H:H,Data.[[#This Row],[Ruc]],B:B,Data.[[#This Row],[Periodo]]),0) -> 0
A18: =CONCATENATE(Data.[[#This Row],[Código]],Data.[[#This Row],[Ruc]]) -> 594769420615727165 | B18: 46143 | C18: =IFERROR(VLOOKUP(Data.[[#This Row],[Código LT]],Reportería.[],71,0),"") | D18: =IFERROR(VLOOKUP(Data.[[#This Row],[Código]],BV!A:C,2,0),"") -> 46157 | E18: =IFERROR(VLOOKUP(Data.[[#This Row],[Código]],BV!A:C,3,0),"") -> 46157 | F18: 5947694 | G18: TJ33261A21031 | H18: 20615727165 | I18: POLLERIAS B3 S.A.C. | J18: POWER GYM | K18: =IF(Data.[[#This Row],[Tipo de Venta]]<>"POS","Atendido",IF(Data.[[#This Row],[Fecha de Instalación]]<>"","Atendido","Ingresado")) -> Atendido | L18: =Data.[[#This Row],[Estado]] -> Atendido | M18: POS | N18: =IFERROR(VLOOKUP(Data.[[#This Row],[Código LT]],Reportería.[],20,0),"") | O18: =IFERROR(VLOOKUP(Data.[[#This Row],[Código LT]],Reportería.[],5,0),"") | P18: =Data.[[#This Row],[GPV Mensual LT]]/COUNTIFS(H:H,Data.[[#This Row],[Ruc]],B:B,Data.[[#This Row],[Periodo]]) -> 10000 | Q18: 10000 | R18: Guadalupe Del Pino | S18: =VLOOKUP(Data.[[#This Row],[Ejecutivo]],Productividad!D:N,11,0) -> 77016095 | T18: =VLOOKUP(Data.[[#This Row],[DNI Ejecutivo]],Productividad!C:U,8,0) -> nelly.delpino@lozapay.com.pe | U18: =VLOOKUP(Data.[[#This Row],[DNI Ejecutivo]],Productividad!C:U,4,0) -> Hunter | V18: =IFERROR(VLOOKUP(Data.[[#This Row],[DNI Ejecutivo]],Ejecutivos.[],11,0),"") -> Lima Jean | W18: Jean Aguilar | X18: {=IFERROR(_xlfn.IFS(Data.[[#This Row],[Supervisor]]="Jonathan Lapoint","Norte",Data.[[#This Row],[Supervisor]]="Jorge Fuentes","Norte"),"Lima")} -> Lima | Y18: =VLOOKUP(Data.[[#This Row],[Supervisor]],Ejecutivos!B:S,17,0) -> 47688341 | Z18: =VLOOKUP(Data.[[#This Row],[DNI Supervisor]],Productividad!C:U,8,0) -> jaguilar@lozapay.com.pe | AB18: NELLY GUADALUPE DEL PINO MONDRAGON | AC18: =IFERROR(CONCATENATE(Data.[[#This Row],[DNI Ejecutivo]],Data.[[#This Row],[Periodo]]),"") -> 7701609546143 | AD18: =IFERROR(VLOOKUP(Data.[[#This Row],[Código LT]],Reportería.[],10,0),"") | AE18: =IFERROR(VLOOKUP(Data.[[#This Row],[Código LT]],Reportería.[],11,0),"") | AF18: 3144.2 | AI18: =IF(TEXT(Data.[[#This Row],[Periodo]],"mmm-yy")="may-26",VLOOKUP(Data.[[#This Row],[Código]],Reportería!A:BV,57,0),0) -> 7190 | AL18: =IF(Data.[[#This Row],[Vol M0]]="",0,0) -> 0 | AM18: =IF(Data.[[#This Row],[Vol M0]]="",0,0) -> 0 | AN18: =IF(Data.[[#This Row],[Vol M0]]="",0,0) -> 0 | AO18: =IF(Data.[[#This Row],[Vol M0]]="",0,0) -> 0 | AP18: =IF(Data.[[#This Row],[Vol M0]]="",0,0) -> 0 | AQ18: =IF(Data.[[#This Row],[Vol M0]]="",0,0) -> 0 | AR18: =IFERROR(IF(OR(AND(OR(Data.[[#This Row],[Categoría]]="Hunter",Data.[[#This Row],[Categoría]]="Senior"),OR(SUMIFS(AF:AF,H:H,Data.[[#This Row],[Ruc]],B:B,Data.[[#This Row],[Periodo]])>=15000,SUMIFS(AI:AI,H:H,Data.[[#This Row],[Ruc]],B:B,Data.[[#This Row],[Periodo]])>=15000,SUMIFS(AL:AL,H:H,Data.[[#This Row],[Ruc]],B:B,Data.[[#This Row],[Periodo]])>=15000,SUMIFS(AO:AO,H:H,Data.[[#This Row],[Ruc]],B:B,Data.[[#This Row],[Periodo]])>=15000)),AND(Data.[[#This Row],[Categoría]]="Elite",OR(SUMIFS(AF:AF,H:H,Data.[[#This Row],[Ruc]],B:B,Data.[[#This Row],[Periodo]])>=25000,SUMIFS(AI:AI,H:H,Data.[[#This Row],[Ruc]],B:B,Data.[[#This Row],[Periodo]])>=25000,SUMIFS(AL:AL,H:H,Data.[[#This Row],[Ruc]],B:B,Data.[[#This Row],[Periodo]])>=25000,SUMIFS(AO:AO,H:H,Data.[[#This Row],[Ruc]],B:B,Data.[[#This Row],[Periodo]])>=25000))),1,0)/COUNTIFS(H:H,Data.[[#This Row],[Ruc]],B:B,Data.[[#This Row],[Periodo]]),0) -> 0
A19: =CONCATENATE(Data.[[#This Row],[Código]],Data.[[#This Row],[Ruc]]) -> 594781120613703439 | B19: 46143 | C19: =IFERROR(VLOOKUP(Data.[[#This Row],[Código LT]],Reportería.[],71,0),"") | D19: =IFERROR(VLOOKUP(Data.[[#This Row],[Código]],BV!A:C,2,0),"") -> 46157 | E19: =IFERROR(VLOOKUP(Data.[[#This Row],[Código]],BV!A:C,3,0),"") -> 46160 | F19: 5947811 | G19: TJ33261C20699 | H19: 20613703439 | I19: XNOX GROUP S.A.C.S | J19: Xnox centro cívico | K19: =IF(Data.[[#This Row],[Tipo de Venta]]<>"POS","Atendido",IF(Data.[[#This Row],[Fecha de Instalación]]<>"","Atendido","Ingresado")) -> Atendido | L19: =Data.[[#This Row],[Estado]] -> Atendido | M19: POS | N19: =IFERROR(VLOOKUP(Data.[[#This Row],[Código LT]],Reportería.[],20,0),"") | O19: =IFERROR(VLOOKUP(Data.[[#This Row],[Código LT]],Reportería.[],5,0),"") | P19: =Data.[[#This Row],[GPV Mensual LT]]/COUNTIFS(H:H,Data.[[#This Row],[Ruc]],B:B,Data.[[#This Row],[Periodo]]) -> 180000 | Q19: 180000 | R19: Maria Godoy | S19: =VLOOKUP(Data.[[#This Row],[Ejecutivo]],Productividad!D:N,11,0) -> 46998250 | T19: =VLOOKUP(Data.[[#This Row],[DNI Ejecutivo]],Productividad!C:U,8,0) -> mgodoyc@lozapay.com.pe | U19: =VLOOKUP(Data.[[#This Row],[DNI Ejecutivo]],Productividad!C:U,4,0) -> Elite | V19: =IFERROR(VLOOKUP(Data.[[#This Row],[DNI Ejecutivo]],Ejecutivos.[],11,0),"") -> Lima Palomino | W19: Carlos Palomino | X19: {=IFERROR(_xlfn.IFS(Data.[[#This Row],[Supervisor]]="Jonathan Lapoint","Norte",Data.[[#This Row],[Supervisor]]="Jorge Fuentes","Norte"),"Lima")} -> Lima | Y19: =VLOOKUP(Data.[[#This Row],[Supervisor]],Ejecutivos!B:S,17,0) -> 41718975 | Z19: =VLOOKUP(Data.[[#This Row],[DNI Supervisor]],Productividad!C:U,8,0) -> carlos.palomino@lozapay.com.pe | AB19: MARIA JOHANA GODOY CRUZ | AC19: =IFERROR(CONCATENATE(Data.[[#This Row],[DNI Ejecutivo]],Data.[[#This Row],[Periodo]]),"") -> 4699825046143 | AD19: =IFERROR(VLOOKUP(Data.[[#This Row],[Código LT]],Reportería.[],10,0),"") | AE19: =IFERROR(VLOOKUP(Data.[[#This Row],[Código LT]],Reportería.[],11,0),"") | AF19: 66628.38 | AI19: =IF(TEXT(Data.[[#This Row],[Periodo]],"mmm-yy")="may-26",VLOOKUP(Data.[[#This Row],[Código]],Reportería!A:BV,57,0),0) -> 70243 | AL19: =IF(Data.[[#This Row],[Vol M0]]="",0,0) -> 0 | AM19: =IF(Data.[[#This Row],[Vol M0]]="",0,0) -> 0 | AN19: =IF(Data.[[#This Row],[Vol M0]]="",0,0) -> 0 | AO19: =IF(Data.[[#This Row],[Vol M0]]="",0,0) -> 0 | AP19: =IF(Data.[[#This Row],[Vol M0]]="",0,0) -> 0 | AQ19: =IF(Data.[[#This Row],[Vol M0]]="",0,0) -> 0 | AR19: =IFERROR(IF(OR(AND(OR(Data.[[#This Row],[Categoría]]="Hunter",Data.[[#This Row],[Categoría]]="Senior"),OR(SUMIFS(AF:AF,H:H,Data.[[#This Row],[Ruc]],B:B,Data.[[#This Row],[Periodo]])>=15000,SUMIFS(AI:AI,H:H,Data.[[#This Row],[Ruc]],B:B,Data.[[#This Row],[Periodo]])>=15000,SUMIFS(AL:AL,H:H,Data.[[#This Row],[Ruc]],B:B,Data.[[#This Row],[Periodo]])>=15000,SUMIFS(AO:AO,H:H,Data.[[#This Row],[Ruc]],B:B,Data.[[#This Row],[Periodo]])>=15000)),AND(Data.[[#This Row],[Categoría]]="Elite",OR(SUMIFS(AF:AF,H:H,Data.[[#This Row],[Ruc]],B:B,Data.[[#This Row],[Periodo]])>=25000,SUMIFS(AI:AI,H:H,Data.[[#This Row],[Ruc]],B:B,Data.[[#This Row],[Periodo]])>=25000,SUMIFS(AL:AL,H:H,Data.[[#This Row],[Ruc]],B:B,Data.[[#This Row],[Periodo]])>=25000,SUMIFS(AO:AO,H:H,Data.[[#This Row],[Ruc]],B:B,Data.[[#This Row],[Periodo]])>=25000))),1,0)/COUNTIFS(H:H,Data.[[#This Row],[Ruc]],B:B,Data.[[#This Row],[Periodo]]),0) -> 1
A20: =CONCATENATE(Data.[[#This Row],[Código]],Data.[[#This Row],[Ruc]]) -> 594783320612913359 | B20: 46143 | C20: =IFERROR(VLOOKUP(Data.[[#This Row],[Código LT]],Reportería.[],71,0),"") | D20: =IFERROR(VLOOKUP(Data.[[#This Row],[Código]],BV!A:C,2,0),"") -> 46157 | E20: =IFERROR(VLOOKUP(Data.[[#This Row],[Código]],BV!A:C,3,0),"") -> 46160 | F20: 5947833 | G20: TJ33261A20350 | H20: 20612913359 | I20: VOLCAN CAPITAL S.A.C.S. | J20: Xnox alisos | K20: =IF(Data.[[#This Row],[Tipo de Venta]]<>"POS","Atendido",IF(Data.[[#This Row],[Fecha de Instalación]]<>"","Atendido","Ingresado")) -> Atendido | L20: =Data.[[#This Row],[Estado]] -> Atendido | M20: POS | N20: =IFERROR(VLOOKUP(Data.[[#This Row],[Código LT]],Reportería.[],20,0),"") | O20: =IFERROR(VLOOKUP(Data.[[#This Row],[Código LT]],Reportería.[],5,0),"") | P20: =Data.[[#This Row],[GPV Mensual LT]]/COUNTIFS(H:H,Data.[[#This Row],[Ruc]],B:B,Data.[[#This Row],[Periodo]]) -> 90000 | Q20: 180000 | R20: Maria Godoy | S20: =VLOOKUP(Data.[[#This Row],[Ejecutivo]],Productividad!D:N,11,0) -> 46998250 | T20: =VLOOKUP(Data.[[#This Row],[DNI Ejecutivo]],Productividad!C:U,8,0) -> mgodoyc@lozapay.com.pe | U20: =VLOOKUP(Data.[[#This Row],[DNI Ejecutivo]],Productividad!C:U,4,0) -> Elite | V20: =IFERROR(VLOOKUP(Data.[[#This Row],[DNI Ejecutivo]],Ejecutivos.[],11,0),"") -> Lima Palomino | W20: Carlos Palomino | X20: {=IFERROR(_xlfn.IFS(Data.[[#This Row],[Supervisor]]="Jonathan Lapoint","Norte",Data.[[#This Row],[Supervisor]]="Jorge Fuentes","Norte"),"Lima")} -> Lima | Y20: =VLOOKUP(Data.[[#This Row],[Supervisor]],Ejecutivos!B:S,17,0) -> 41718975 | Z20: =VLOOKUP(Data.[[#This Row],[DNI Supervisor]],Productividad!C:U,8,0) -> carlos.palomino@lozapay.com.pe | AB20: MARIA JOHANA GODOY CRUZ | AC20: =IFERROR(CONCATENATE(Data.[[#This Row],[DNI Ejecutivo]],Data.[[#This Row],[Periodo]]),"") -> 4699825046143 | AD20: =IFERROR(VLOOKUP(Data.[[#This Row],[Código LT]],Reportería.[],10,0),"") | AE20: =IFERROR(VLOOKUP(Data.[[#This Row],[Código LT]],Reportería.[],11,0),"") | AF20: 40828 | AI20: =IF(TEXT(Data.[[#This Row],[Periodo]],"mmm-yy")="may-26",VLOOKUP(Data.[[#This Row],[Código]],Reportería!A:BV,57,0),0) -> 47624 | AL20: =IF(Data.[[#This Row],[Vol M0]]="",0,0) -> 0 | AM20: =IF(Data.[[#This Row],[Vol M0]]="",0,0) -> 0 | AN20: =IF(Data.[[#This Row],[Vol M0]]="",0,0) -> 0 | AO20: =IF(Data.[[#This Row],[Vol M0]]="",0,0) -> 0 | AP20: =IF(Data.[[#This Row],[Vol M0]]="",0,0) -> 0 | AQ20: =IF(Data.[[#This Row],[Vol M0]]="",0,0) -> 0 | AR20: =IFERROR(IF(OR(AND(OR(Data.[[#This Row],[Categoría]]="Hunter",Data.[[#This Row],[Categoría]]="Senior"),OR(SUMIFS(AF:AF,H:H,Data.[[#This Row],[Ruc]],B:B,Data.[[#This Row],[Periodo]])>=15000,SUMIFS(AI:AI,H:H,Data.[[#This Row],[Ruc]],B:B,Data.[[#This Row],[Periodo]])>=15000,SUMIFS(AL:AL,H:H,Data.[[#This Row],[Ruc]],B:B,Data.[[#This Row],[Periodo]])>=15000,SUMIFS(AO:AO,H:H,Data.[[#This Row],[Ruc]],B:B,Data.[[#This Row],[Periodo]])>=15000)),AND(Data.[[#This Row],[Categoría]]="Elite",OR(SUMIFS(AF:AF,H:H,Data.[[#This Row],[Ruc]],B:B,Data.[[#This Row],[Periodo]])>=25000,SUMIFS(AI:AI,H:H,Data.[[#This Row],[Ruc]],B:B,Data.[[#This Row],[Periodo]])>=25000,SUMIFS(AL:AL,H:H,Data.[[#This Row],[Ruc]],B:B,Data.[[#This Row],[Periodo]])>=25000,SUMIFS(AO:AO,H:H,Data.[[#This Row],[Ruc]],B:B,Data.[[#This Row],[Periodo]])>=25000))),1,0)/COUNTIFS(H:H,Data.[[#This Row],[Ruc]],B:B,Data.[[#This Row],[Periodo]]),0) -> 0.5
A21: =CONCATENATE(Data.[[#This Row],[Código]],Data.[[#This Row],[Ruc]]) -> 594836320539185901 | B21: 46143 | C21: =IFERROR(VLOOKUP(Data.[[#This Row],[Código LT]],Reportería.[],71,0),"") | D21: =IFERROR(VLOOKUP(Data.[[#This Row],[Código]],BV!A:C,2,0),"") -> 46160 | E21: =IFERROR(VLOOKUP(Data.[[#This Row],[Código]],BV!A:C,3,0),"") -> 46160 | F21: 5948363 | G21: TJ33261C20014 | H21: 20539185901 | I21: JB DIVERSIONES SAC | J21: AKAFALA KARAOKE | K21: =IF(Data.[[#This Row],[Tipo de Venta]]<>"POS","Atendido",IF(Data.[[#This Row],[Fecha de Instalación]]<>"","Atendido","Ingresado")) -> Atendido | L21: =Data.[[#This Row],[Estado]] -> Atendido | M21: POS | N21: =IFERROR(VLOOKUP(Data.[[#This Row],[Código LT]],Reportería.[],20,0),"") | O21: =IFERROR(VLOOKUP(Data.[[#This Row],[Código LT]],Reportería.[],5,0),"") | P21: =Data.[[#This Row],[GPV Mensual LT]]/COUNTIFS(H:H,Data.[[#This Row],[Ruc]],B:B,Data.[[#This Row],[Periodo]]) -> 35000 | Q21: 35000 | R21: Alberto Chaname | S21: =VLOOKUP(Data.[[#This Row],[Ejecutivo]],Productividad!D:N,11,0) -> 76032645 | T21: =VLOOKUP(Data.[[#This Row],[DNI Ejecutivo]],Productividad!C:U,8,0) -> alberto.chaname@lozapay.com.pe | U21: =VLOOKUP(Data.[[#This Row],[DNI Ejecutivo]],Productividad!C:U,4,0) -> Senior | V21: =IFERROR(VLOOKUP(Data.[[#This Row],[DNI Ejecutivo]],Ejecutivos.[],11,0),"") -> Norte Lapoint | W21: Jonathan Lapoint | X21: {=IFERROR(_xlfn.IFS(Data.[[#This Row],[Supervisor]]="Jonathan Lapoint","Norte",Data.[[#This Row],[Supervisor]]="Jorge Fuentes","Norte"),"Lima")} -> Norte | Y21: =VLOOKUP(Data.[[#This Row],[Supervisor]],Ejecutivos!B:S,17,0) -> 70430554 | Z21: =VLOOKUP(Data.[[#This Row],[DNI Supervisor]],Productividad!C:U,8,0) -> jlapointp@lozapay.com.pe | AB21: ALBERTO LUIGUI ALEXANDER CHANAME CASTRO | AC21: =IFERROR(CONCATENATE(Data.[[#This Row],[DNI Ejecutivo]],Data.[[#This Row],[Periodo]]),"") -> 7603264546143 | AD21: =IFERROR(VLOOKUP(Data.[[#This Row],[Código LT]],Reportería.[],10,0),"") | AE21: =IFERROR(VLOOKUP(Data.[[#This Row],[Código LT]],Reportería.[],11,0),"") | AF21: 12267.08 | AI21: =IF(TEXT(Data.[[#This Row],[Periodo]],"mmm-yy")="may-26",VLOOKUP(Data.[[#This Row],[Código]],Reportería!A:BV,57,0),0) -> 250 | AL21: =IF(Data.[[#This Row],[Vol M0]]="",0,0) -> 0 | AM21: =IF(Data.[[#This Row],[Vol M0]]="",0,0) -> 0 | AN21: =IF(Data.[[#This Row],[Vol M0]]="",0,0) -> 0 | AO21: =IF(Data.[[#This Row],[Vol M0]]="",0,0) -> 0 | AP21: =IF(Data.[[#This Row],[Vol M0]]="",0,0) -> 0 | AQ21: =IF(Data.[[#This Row],[Vol M0]]="",0,0) -> 0 | AR21: =IFERROR(IF(OR(AND(OR(Data.[[#This Row],[Categoría]]="Hunter",Data.[[#This Row],[Categoría]]="Senior"),OR(SUMIFS(AF:AF,H:H,Data.[[#This Row],[Ruc]],B:B,Data.[[#This Row],[Periodo]])>=15000,SUMIFS(AI:AI,H:H,Data.[[#This Row],[Ruc]],B:B,Data.[[#This Row],[Periodo]])>=15000,SUMIFS(AL:AL,H:H,Data.[[#This Row],[Ruc]],B:B,Data.[[#This Row],[Periodo]])>=15000,SUMIFS(AO:AO,H:H,Data.[[#This Row],[Ruc]],B:B,Data.[[#This Row],[Periodo]])>=15000)),AND(Data.[[#This Row],[Categoría]]="Elite",OR(SUMIFS(AF:AF,H:H,Data.[[#This Row],[Ruc]],B:B,Data.[[#This Row],[Periodo]])>=25000,SUMIFS(AI:AI,H:H,Data.[[#This Row],[Ruc]],B:B,Data.[[#This Row],[Periodo]])>=25000,SUMIFS(AL:AL,H:H,Data.[[#This Row],[Ruc]],B:B,Data.[[#This Row],[Periodo]])>=25000,SUMIFS(AO:AO,H:H,Data.[[#This Row],[Ruc]],B:B,Data.[[#This Row],[Periodo]])>=25000))),1,0)/COUNTIFS(H:H,Data.[[#This Row],[Ruc]],B:B,Data.[[#This Row],[Periodo]]),0) -> 0
A22: =CONCATENATE(Data.[[#This Row],[Código]],Data.[[#This Row],[Ruc]]) -> 594872720611563435 | B22: 46143 | C22: =IFERROR(VLOOKUP(Data.[[#This Row],[Código LT]],Reportería.[],71,0),"") | D22: =IFERROR(VLOOKUP(Data.[[#This Row],[Código]],BV!A:C,2,0),"") -> 46160 | E22: =IFERROR(VLOOKUP(Data.[[#This Row],[Código]],BV!A:C,3,0),"") -> 46162 | F22: 5948727 | G22: TJ33261920069 | H22: 20611563435 | I22: ALIMENTOS DEL PEDREGAL S.A.C. | J22: Alimentos del Pedregal | K22: =IF(Data.[[#This Row],[Tipo de Venta]]<>"POS","Atendido",IF(Data.[[#This Row],[Fecha de Instalación]]<>"","Atendido","Ingresado")) -> Atendido | L22: =Data.[[#This Row],[Estado]] -> Atendido | M22: POS | N22: =IFERROR(VLOOKUP(Data.[[#This Row],[Código LT]],Reportería.[],20,0),"") | O22: =IFERROR(VLOOKUP(Data.[[#This Row],[Código LT]],Reportería.[],5,0),"") | P22: =Data.[[#This Row],[GPV Mensual LT]]/COUNTIFS(H:H,Data.[[#This Row],[Ruc]],B:B,Data.[[#This Row],[Periodo]]) -> 100000 | Q22: 100000 | R22: Leonardo Torres | S22: =VLOOKUP(Data.[[#This Row],[Ejecutivo]],Productividad!D:N,11,0) -> 72895762 | T22: =VLOOKUP(Data.[[#This Row],[DNI Ejecutivo]],Productividad!C:U,8,0) -> leonardo.honorio@lozapay.com.pe | U22: =VLOOKUP(Data.[[#This Row],[DNI Ejecutivo]],Productividad!C:U,4,0) -> Senior | V22: =IFERROR(VLOOKUP(Data.[[#This Row],[DNI Ejecutivo]],Ejecutivos.[],11,0),"") -> Lima Palomino | W22: Carlos Palomino | X22: {=IFERROR(_xlfn.IFS(Data.[[#This Row],[Supervisor]]="Jonathan Lapoint","Norte",Data.[[#This Row],[Supervisor]]="Jorge Fuentes","Norte"),"Lima")} -> Lima | Y22: =VLOOKUP(Data.[[#This Row],[Supervisor]],Ejecutivos!B:S,17,0) -> 41718975 | Z22: =VLOOKUP(Data.[[#This Row],[DNI Supervisor]],Productividad!C:U,8,0) -> carlos.palomino@lozapay.com.pe | AB22: LEONARDO ARTURO TORRES HONORIO | AC22: =IFERROR(CONCATENATE(Data.[[#This Row],[DNI Ejecutivo]],Data.[[#This Row],[Periodo]]),"") -> 7289576246143 | AD22: =IFERROR(VLOOKUP(Data.[[#This Row],[Código LT]],Reportería.[],10,0),"") | AE22: =IFERROR(VLOOKUP(Data.[[#This Row],[Código LT]],Reportería.[],11,0),"") | AF22: 1.1 | AI22: =IF(TEXT(Data.[[#This Row],[Periodo]],"mmm-yy")="may-26",VLOOKUP(Data.[[#This Row],[Código]],Reportería!A:BV,57,0),0) -> 0 | AL22: =IF(Data.[[#This Row],[Vol M0]]="",0,0) -> 0 | AM22: =IF(Data.[[#This Row],[Vol M0]]="",0,0) -> 0 | AN22: =IF(Data.[[#This Row],[Vol M0]]="",0,0) -> 0 | AO22: =IF(Data.[[#This Row],[Vol M0]]="",0,0) -> 0 | AP22: =IF(Data.[[#This Row],[Vol M0]]="",0,0) -> 0 | AQ22: =IF(Data.[[#This Row],[Vol M0]]="",0,0) -> 0 | AR22: =IFERROR(IF(OR(AND(OR(Data.[[#This Row],[Categoría]]="Hunter",Data.[[#This Row],[Categoría]]="Senior"),OR(SUMIFS(AF:AF,H:H,Data.[[#This Row],[Ruc]],B:B,Data.[[#This Row],[Periodo]])>=15000,SUMIFS(AI:AI,H:H,Data.[[#This Row],[Ruc]],B:B,Data.[[#This Row],[Periodo]])>=15000,SUMIFS(AL:AL,H:H,Data.[[#This Row],[Ruc]],B:B,Data.[[#This Row],[Periodo]])>=15000,SUMIFS(AO:AO,H:H,Data.[[#This Row],[Ruc]],B:B,Data.[[#This Row],[Periodo]])>=15000)),AND(Data.[[#This Row],[Categoría]]="Elite",OR(SUMIFS(AF:AF,H:H,Data.[[#This Row],[Ruc]],B:B,Data.[[#This Row],[Periodo]])>=25000,SUMIFS(AI:AI,H:H,Data.[[#This Row],[Ruc]],B:B,Data.[[#This Row],[Periodo]])>=25000,SUMIFS(AL:AL,H:H,Data.[[#This Row],[Ruc]],B:B,Data.[[#This Row],[Periodo]])>=25000,SUMIFS(AO:AO,H:H,Data.[[#This Row],[Ruc]],B:B,Data.[[#This Row],[Periodo]])>=25000))),1,0)/COUNTIFS(H:H,Data.[[#This Row],[Ruc]],B:B,Data.[[#This Row],[Periodo]]),0) -> 0
A23: =CONCATENATE(Data.[[#This Row],[Código]],Data.[[#This Row],[Ruc]]) -> 594863320612913359 | B23: 46143 | C23: =IFERROR(VLOOKUP(Data.[[#This Row],[Código LT]],Reportería.[],71,0),"") | D23: =IFERROR(VLOOKUP(Data.[[#This Row],[Código]],BV!A:C,2,0),"") -> 46161 | E23: =IFERROR(VLOOKUP(Data.[[#This Row],[Código]],BV!A:C,3,0),"") -> 46161 | F23: 5948633 | G23: TJ33261C20488 | H23: 20612913359 | I23: VOLCAN CAPITAL S.A.C.S. | J23: Xnox naranjal | K23: =IF(Data.[[#This Row],[Tipo de Venta]]<>"POS","Atendido",IF(Data.[[#This Row],[Fecha de Instalación]]<>"","Atendido","Ingresado")) -> Atendido | L23: =Data.[[#This Row],[Estado]] -> Atendido | M23: POS | N23: =IFERROR(VLOOKUP(Data.[[#This Row],[Código LT]],Reportería.[],20,0),"") | O23: =IFERROR(VLOOKUP(Data.[[#This Row],[Código LT]],Reportería.[],5,0),"") | P23: =Data.[[#This Row],[GPV Mensual LT]]/COUNTIFS(H:H,Data.[[#This Row],[Ruc]],B:B,Data.[[#This Row],[Periodo]]) -> 90000 | Q23: 180000 | R23: Maria Godoy | S23: =VLOOKUP(Data.[[#This Row],[Ejecutivo]],Productividad!D:N,11,0) -> 46998250 | T23: =VLOOKUP(Data.[[#This Row],[DNI Ejecutivo]],Productividad!C:U,8,0) -> mgodoyc@lozapay.com.pe | U23: =VLOOKUP(Data.[[#This Row],[DNI Ejecutivo]],Productividad!C:U,4,0) -> Elite | V23: =IFERROR(VLOOKUP(Data.[[#This Row],[DNI Ejecutivo]],Ejecutivos.[],11,0),"") -> Lima Palomino | W23: Carlos Palomino | X23: {=IFERROR(_xlfn.IFS(Data.[[#This Row],[Supervisor]]="Jonathan Lapoint","Norte",Data.[[#This Row],[Supervisor]]="Jorge Fuentes","Norte"),"Lima")} -> Lima | Y23: =VLOOKUP(Data.[[#This Row],[Supervisor]],Ejecutivos!B:S,17,0) -> 41718975 | Z23: =VLOOKUP(Data.[[#This Row],[DNI Supervisor]],Productividad!C:U,8,0) -> carlos.palomino@lozapay.com.pe | AB23: MARIA JOHANA GODOY CRUZ | AC23: =IFERROR(CONCATENATE(Data.[[#This Row],[DNI Ejecutivo]],Data.[[#This Row],[Periodo]]),"") -> 4699825046143 | AD23: =IFERROR(VLOOKUP(Data.[[#This Row],[Código LT]],Reportería.[],10,0),"") | AE23: =IFERROR(VLOOKUP(Data.[[#This Row],[Código LT]],Reportería.[],11,0),"") | AF23: 17443.2 | AI23: =IF(TEXT(Data.[[#This Row],[Periodo]],"mmm-yy")="may-26",VLOOKUP(Data.[[#This Row],[Código]],Reportería!A:BV,57,0),0) -> 24717.8 | AL23: =IF(Data.[[#This Row],[Vol M0]]="",0,0) -> 0 | AM23: =IF(Data.[[#This Row],[Vol M0]]="",0,0) -> 0 | AN23: =IF(Data.[[#This Row],[Vol M0]]="",0,0) -> 0 | AO23: =IF(Data.[[#This Row],[Vol M0]]="",0,0) -> 0 | AP23: =IF(Data.[[#This Row],[Vol M0]]="",0,0) -> 0 | AQ23: =IF(Data.[[#This Row],[Vol M0]]="",0,0) -> 0 | AR23: =IFERROR(IF(OR(AND(OR(Data.[[#This Row],[Categoría]]="Hunter",Data.[[#This Row],[Categoría]]="Senior"),OR(SUMIFS(AF:AF,H:H,Data.[[#This Row],[Ruc]],B:B,Data.[[#This Row],[Periodo]])>=15000,SUMIFS(AI:AI,H:H,Data.[[#This Row],[Ruc]],B:B,Data.[[#This Row],[Periodo]])>=15000,SUMIFS(AL:AL,H:H,Data.[[#This Row],[Ruc]],B:B,Data.[[#This Row],[Periodo]])>=15000,SUMIFS(AO:AO,H:H,Data.[[#This Row],[Ruc]],B:B,Data.[[#This Row],[Periodo]])>=15000)),AND(Data.[[#This Row],[Categoría]]="Elite",OR(SUMIFS(AF:AF,H:H,Data.[[#This Row],[Ruc]],B:B,Data.[[#This Row],[Periodo]])>=25000,SUMIFS(AI:AI,H:H,Data.[[#This Row],[Ruc]],B:B,Data.[[#This Row],[Periodo]])>=25000,SUMIFS(AL:AL,H:H,Data.[[#This Row],[Ruc]],B:B,Data.[[#This Row],[Periodo]])>=25000,SUMIFS(AO:AO,H:H,Data.[[#This Row],[Ruc]],B:B,Data.[[#This Row],[Periodo]])>=25000))),1,0)/COUNTIFS(H:H,Data.[[#This Row],[Ruc]],B:B,Data.[[#This Row],[Periodo]]),0) -> 0.5
... A26: =CONCATENATE(Data.[[#This Row],[Código]],Data.[[#This Row],[Ruc]]) -> 594956810718173561 | B26: 46143 | C26: =IFERROR(VLOOKUP(Data.[[#This Row],[Código LT]],Reportería.[],71,0),"") | D26: =IFERROR(VLOOKUP(Data.[[#This Row],[Código]],BV!A:C,2,0),"") -> 46163 | E26: =IFERROR(VLOOKUP(Data.[[#This Row],[Código]],BV!A:C,3,0),"") -> 46163 | F26: 5949568 | G26: TJ33261C21266 | H26: 10718173561 | I26: MUNDACA INGA KARINA STEFANI | J26: KARINA MUNDACA | K26: =IF(Data.[[#This Row],[Tipo de Venta]]<>"POS","Atendido",IF(Data.[[#This Row],[Fecha de Instalación]]<>"","Atendido","Ingresado")) -> Atendido | L26: =Data.[[#This Row],[Estado]] -> Atendido | M26: POS | N26: =IFERROR(VLOOKUP(Data.[[#This Row],[Código LT]],Reportería.[],20,0),"") | O26: =IFERROR(VLOOKUP(Data.[[#This Row],[Código LT]],Reportería.[],5,0),"") | P26: =Data.[[#This Row],[GPV Mensual LT]]/COUNTIFS(H:H,Data.[[#This Row],[Ruc]],B:B,Data.[[#This Row],[Periodo]]) -> 20000 | Q26: 20000 | R26: Katherine Zuloeta | S26: =VLOOKUP(Data.[[#This Row],[Ejecutivo]],Productividad!D:N,11,0) -> 72641569 | T26: =VLOOKUP(Data.[[#This Row],[DNI Ejecutivo]],Productividad!C:U,8,0) -> katherine.zuloeta@lozapay.com.pe | U26: =VLOOKUP(Data.[[#This Row],[DNI Ejecutivo]],Productividad!C:U,4,0) -> Hunter | V26: =IFERROR(VLOOKUP(Data.[[#This Row],[DNI Ejecutivo]],Ejecutivos.[],11,0),"") -> Norte Lapoint | W26: Jonathan Lapoint | X26: {=IFERROR(_xlfn.IFS(Data.[[#This Row],[Supervisor]]="Jonathan Lapoint","Norte",Data.[[#This Row],[Supervisor]]="Jorge Fuentes","Norte"),"Lima")} -> Norte | Y26: =VLOOKUP(Data.[[#This Row],[Supervisor]],Ejecutivos!B:S,17,0) -> 70430554 | Z26: =VLOOKUP(Data.[[#This Row],[DNI Supervisor]],Productividad!C:U,8,0) -> jlapointp@lozapay.com.pe | AB26: MARLON ERICK MARTINEZ VALDERRAMA | AC26: =IFERROR(CONCATENATE(Data.[[#This Row],[DNI Ejecutivo]],Data.[[#This Row],[Periodo]]),"") -> 7264156946143 | AD26: =IFERROR(VLOOKUP(Data.[[#This Row],[Código LT]],Reportería.[],10,0),"") | AE26: =IFERROR(VLOOKUP(Data.[[#This Row],[Código LT]],Reportería.[],11,0),"") | AF26: 285.3 | AI26: =IF(TEXT(Data.[[#This Row],[Periodo]],"mmm-yy")="may-26",VLOOKUP(Data.[[#This Row],[Código]],Reportería!A:BV,57,0),0) -> 0 | AL26: =IF(Data.[[#This Row],[Vol M0]]="",0,0) -> 0 | AM26: =IF(Data.[[#This Row],[Vol M0]]="",0,0) -> 0 | AN26: =IF(Data.[[#This Row],[Vol M0]]="",0,0) -> 0 | AO26: =IF(Data.[[#This Row],[Vol M0]]="",0,0) -> 0 | AP26: =IF(Data.[[#This Row],[Vol M0]]="",0,0) -> 0 | AQ26: =IF(Data.[[#This Row],[Vol M0]]="",0,0) -> 0 | AR26: =IFERROR(IF(OR(AND(OR(Data.[[#This Row],[Categoría]]="Hunter",Data.[[#This Row],[Categoría]]="Senior"),OR(SUMIFS(AF:AF,H:H,Data.[[#This Row],[Ruc]],B:B,Data.[[#This Row],[Periodo]])>=15000,SUMIFS(AI:AI,H:H,Data.[[#This Row],[Ruc]],B:B,Data.[[#This Row],[Periodo]])>=15000,SUMIFS(AL:AL,H:H,Data.[[#This Row],[Ruc]],B:B,Data.[[#This Row],[Periodo]])>=15000,SUMIFS(AO:AO,H:H,Data.[[#This Row],[Ruc]],B:B,Data.[[#This Row],[Periodo]])>=15000)),AND(Data.[[#This Row],[Categoría]]="Elite",OR(SUMIFS(AF:AF,H:H,Data.[[#This Row],[Ruc]],B:B,Data.[[#This Row],[Periodo]])>=25000,SUMIFS(AI:AI,H:H,Data.[[#This Row],[Ruc]],B:B,Data.[[#This Row],[Periodo]])>=25000,SUMIFS(AL:AL,H:H,Data.[[#This Row],[Ruc]],B:B,Data.[[#This Row],[Periodo]])>=25000,SUMIFS(AO:AO,H:H,Data.[[#This Row],[Ruc]],B:B,Data.[[#This Row],[Periodo]])>=25000))),1,0)/COUNTIFS(H:H,Data.[[#This Row],[Ruc]],B:B,Data.[[#This Row],[Periodo]]),0) -> 0
A27: =CONCATENATE(Data.[[#This Row],[Código]],Data.[[#This Row],[Ruc]]) -> 105864220611972246 | B27: 46143 | C27: =IFERROR(VLOOKUP(Data.[[#This Row],[Código LT]],Reportería.[],71,0),"") | D27: =IFERROR(VLOOKUP(Data.[[#This Row],[Código]],BV!A:C,2,0),"") -> 46163 | E27: =IFERROR(VLOOKUP(Data.[[#This Row],[Código]],BV!A:C,3,0),"") -> 46182 | F27: 1058642 | H27: 20611972246 | I27: CIMDOLOR PERU S.A.C. | J27: CIMDOLOR PERU SAC | K27: =IF(Data.[[#This Row],[Tipo de Venta]]<>"POS","Atendido",IF(Data.[[#This Row],[Fecha de Instalación]]<>"","Atendido","Ingresado")) -> Atendido | L27: =Data.[[#This Row],[Estado]] -> Atendido | M27: POS | N27: =IFERROR(VLOOKUP(Data.[[#This Row],[Código LT]],Reportería.[],20,0),"") | O27: =IFERROR(VLOOKUP(Data.[[#This Row],[Código LT]],Reportería.[],5,0),"") | P27: =Data.[[#This Row],[GPV Mensual LT]]/COUNTIFS(H:H,Data.[[#This Row],[Ruc]],B:B,Data.[[#This Row],[Periodo]]) -> 45000 | Q27: 45000 | R27: Giuliana Hereña | S27: =VLOOKUP(Data.[[#This Row],[Ejecutivo]],Productividad!D:N,11,0) -> 41419651 | T27: =VLOOKUP(Data.[[#This Row],[DNI Ejecutivo]],Productividad!C:U,8,0) -> giuliana.herena@lozapay.com.pe | U27: =VLOOKUP(Data.[[#This Row],[DNI Ejecutivo]],Productividad!C:U,4,0) -> Senior | V27: =IFERROR(VLOOKUP(Data.[[#This Row],[DNI Ejecutivo]],Ejecutivos.[],11,0),"") -> Lima Palomino | W27: Carlos Palomino | X27: {=IFERROR(_xlfn.IFS(Data.[[#This Row],[Supervisor]]="Jonathan Lapoint","Norte",Data.[[#This Row],[Supervisor]]="Jorge Fuentes","Norte"),"Lima")} -> Lima | Y27: =VLOOKUP(Data.[[#This Row],[Supervisor]],Ejecutivos!B:S,17,0) -> 41718975 | Z27: =VLOOKUP(Data.[[#This Row],[DNI Supervisor]],Productividad!C:U,8,0) -> carlos.palomino@lozapay.com.pe | AB27: GIULIANA HEREÑA DA SILVA | AC27: =IFERROR(CONCATENATE(Data.[[#This Row],[DNI Ejecutivo]],Data.[[#This Row],[Periodo]]),"") -> 4141965146143 | AD27: =IFERROR(VLOOKUP(Data.[[#This Row],[Código LT]],Reportería.[],10,0),"") | AE27: =IFERROR(VLOOKUP(Data.[[#This Row],[Código LT]],Reportería.[],11,0),"") | AF27: 0 | AI27: =IF(TEXT(Data.[[#This Row],[Periodo]],"mmm-yy")="may-26",VLOOKUP(Data.[[#This Row],[Código]],Reportería!A:BV,57,0),0) -> 0 | AL27: =IF(Data.[[#This Row],[Vol M0]]="",0,0) -> 0 | AM27: =IF(Data.[[#This Row],[Vol M0]]="",0,0) -> 0 | AN27: =IF(Data.[[#This Row],[Vol M0]]="",0,0) -> 0 | AO27: =IF(Data.[[#This Row],[Vol M0]]="",0,0) -> 0 | AP27: =IF(Data.[[#This Row],[Vol M0]]="",0,0) -> 0 | AQ27: =IF(Data.[[#This Row],[Vol M0]]="",0,0) -> 0 | AR27: =IFERROR(IF(OR(AND(OR(Data.[[#This Row],[Categoría]]="Hunter",Data.[[#This Row],[Categoría]]="Senior"),OR(SUMIFS(AF:AF,H:H,Data.[[#This Row],[Ruc]],B:B,Data.[[#This Row],[Periodo]])>=15000,SUMIFS(AI:AI,H:H,Data.[[#This Row],[Ruc]],B:B,Data.[[#This Row],[Periodo]])>=15000,SUMIFS(AL:AL,H:H,Data.[[#This Row],[Ruc]],B:B,Data.[[#This Row],[Periodo]])>=15000,SUMIFS(AO:AO,H:H,Data.[[#This Row],[Ruc]],B:B,Data.[[#This Row],[Periodo]])>=15000)),AND(Data.[[#This Row],[Categoría]]="Elite",OR(SUMIFS(AF:AF,H:H,Data.[[#This Row],[Ruc]],B:B,Data.[[#This Row],[Periodo]])>=25000,SUMIFS(AI:AI,H:H,Data.[[#This Row],[Ruc]],B:B,Data.[[#This Row],[Periodo]])>=25000,SUMIFS(AL:AL,H:H,Data.[[#This Row],[Ruc]],B:B,Data.[[#This Row],[Periodo]])>=25000,SUMIFS(AO:AO,H:H,Data.[[#This Row],[Ruc]],B:B,Data.[[#This Row],[Periodo]])>=25000))),1,0)/COUNTIFS(H:H,Data.[[#This Row],[Ruc]],B:B,Data.[[#This Row],[Periodo]]),0) -> 0
A28: =CONCATENATE(Data.[[#This Row],[Código]],Data.[[#This Row],[Ruc]]) -> 105861620615080901 | B28: 46143 | C28: =IFERROR(VLOOKUP(Data.[[#This Row],[Código LT]],Reportería.[],71,0),"") | D28: =IFERROR(VLOOKUP(Data.[[#This Row],[Código]],BV!A:C,2,0),"") -> 46163 | E28: =IFERROR(VLOOKUP(Data.[[#This Row],[Código]],BV!A:C,3,0),"") -> 46165 | F28: 1058616 | H28: 20615080901 | I28: CORPORACION LOBAL S.A.C. | J28: LIGA SPORT | K28: =IF(Data.[[#This Row],[Tipo de Venta]]<>"POS","Atendido",IF(Data.[[#This Row],[Fecha de Instalación]]<>"","Atendido","Ingresado")) -> Atendido | L28: =Data.[[#This Row],[Estado]] -> Atendido | M28: POS | N28: =IFERROR(VLOOKUP(Data.[[#This Row],[Código LT]],Reportería.[],20,0),"") | O28: =IFERROR(VLOOKUP(Data.[[#This Row],[Código LT]],Reportería.[],5,0),"") | P28: =Data.[[#This Row],[GPV Mensual LT]]/COUNTIFS(H:H,Data.[[#This Row],[Ruc]],B:B,Data.[[#This Row],[Periodo]]) -> 42000 | Q28: 42000 | R28: Jackeline Matos | S28: =VLOOKUP(Data.[[#This Row],[Ejecutivo]],Productividad!D:N,11,0) -> 44881019 | T28: =VLOOKUP(Data.[[#This Row],[DNI Ejecutivo]],Productividad!C:U,8,0) -> jackeline.matos@lozapay.com.pe | U28: =VLOOKUP(Data.[[#This Row],[DNI Ejecutivo]],Productividad!C:U,4,0) -> Senior | V28: =IFERROR(VLOOKUP(Data.[[#This Row],[DNI Ejecutivo]],Ejecutivos.[],11,0),"") -> Lima Hamm | W28: Hamm Ramirez | X28: {=IFERROR(_xlfn.IFS(Data.[[#This Row],[Supervisor]]="Jonathan Lapoint","Norte",Data.[[#This Row],[Supervisor]]="Jorge Fuentes","Norte"),"Lima")} -> Lima | Y28: =VLOOKUP(Data.[[#This Row],[Supervisor]],Ejecutivos!B:S,17,0) -> 44818200 | Z28: =VLOOKUP(Data.[[#This Row],[DNI Supervisor]],Productividad!C:U,8,0) -> hramirezp@lozapay.com.pe | AB28: JACKELINE SOLANGE MATOS QUIÑONES | AC28: =IFERROR(CONCATENATE(Data.[[#This Row],[DNI Ejecutivo]],Data.[[#This Row],[Periodo]]),"") -> 4488101946143 | AD28: =IFERROR(VLOOKUP(Data.[[#This Row],[Código LT]],Reportería.[],10,0),"") | AE28: =IFERROR(VLOOKUP(Data.[[#This Row],[Código LT]],Reportería.[],11,0),"") | AF28: 845 | AI28: =IF(TEXT(Data.[[#This Row],[Periodo]],"mmm-yy")="may-26",VLOOKUP(Data.[[#This Row],[Código]],Reportería!A:BV,57,0),0) -> 458.4 | AL28: =IF(Data.[[#This Row],[Vol M0]]="",0,0) -> 0 | AM28: =IF(Data.[[#This Row],[Vol M0]]="",0,0) -> 0 | AN28: =IF(Data.[[#This Row],[Vol M0]]="",0,0) -> 0 | AO28: =IF(Data.[[#This Row],[Vol M0]]="",0,0) -> 0 | AP28: =IF(Data.[[#This Row],[Vol M0]]="",0,0) -> 0 | AQ28: =IF(Data.[[#This Row],[Vol M0]]="",0,0) -> 0 | AR28: =IFERROR(IF(OR(AND(OR(Data.[[#This Row],[Categoría]]="Hunter",Data.[[#This Row],[Categoría]]="Senior"),OR(SUMIFS(AF:AF,H:H,Data.[[#This Row],[Ruc]],B:B,Data.[[#This Row],[Periodo]])>=15000,SUMIFS(AI:AI,H:H,Data.[[#This Row],[Ruc]],B:B,Data.[[#This Row],[Periodo]])>=15000,SUMIFS(AL:AL,H:H,Data.[[#This Row],[Ruc]],B:B,Data.[[#This Row],[Periodo]])>=15000,SUMIFS(AO:AO,H:H,Data.[[#This Row],[Ruc]],B:B,Data.[[#This Row],[Periodo]])>=15000)),AND(Data.[[#This Row],[Categoría]]="Elite",OR(SUMIFS(AF:AF,H:H,Data.[[#This Row],[Ruc]],B:B,Data.[[#This Row],[Periodo]])>=25000,SUMIFS(AI:AI,H:H,Data.[[#This Row],[Ruc]],B:B,Data.[[#This Row],[Periodo]])>=25000,SUMIFS(AL:AL,H:H,Data.[[#This Row],[Ruc]],B:B,Data.[[#This Row],[Periodo]])>=25000,SUMIFS(AO:AO,H:H,Data.[[#This Row],[Ruc]],B:B,Data.[[#This Row],[Periodo]])>=25000))),1,0)/COUNTIFS(H:H,Data.[[#This Row],[Ruc]],B:B,Data.[[#This Row],[Periodo]]),0) -> 0
A29: =CONCATENATE(Data.[[#This Row],[Código]],Data.[[#This Row],[Ruc]]) -> 105864820608874055 | B29: 46143 | C29: =IFERROR(VLOOKUP(Data.[[#This Row],[Código LT]],Reportería.[],71,0),"") | D29: =IFERROR(VLOOKUP(Data.[[#This Row],[Código]],BV!A:C,2,0),"") -> 46167 | E29: =IFERROR(VLOOKUP(Data.[[#This Row],[Código]],BV!A:C,3,0),"") -> 46172 | F29: 1058648 | H29: 20608874055 | I29: GROALPERU E.I.R.L. | J29: New Support (LA VICTORIA) | K29: =IF(Data.[[#This Row],[Tipo de Venta]]<>"POS","Atendido",IF(Data.[[#This Row],[Fecha de Instalación]]<>"","Atendido","Ingresado")) -> Atendido | L29: =Data.[[#This Row],[Estado]] -> Atendido | M29: POS | N29: =IFERROR(VLOOKUP(Data.[[#This Row],[Código LT]],Reportería.[],20,0),"") | O29: =IFERROR(VLOOKUP(Data.[[#This Row],[Código LT]],Reportería.[],5,0),"") | P29: =Data.[[#This Row],[GPV Mensual LT]]/COUNTIFS(H:H,Data.[[#This Row],[Ruc]],B:B,Data.[[#This Row],[Periodo]]) -> 40000 | Q29: 80000 | R29: Jackeline Matos | S29: =VLOOKUP(Data.[[#This Row],[Ejecutivo]],Productividad!D:N,11,0) -> 44881019 | T29: =VLOOKUP(Data.[[#This Row],[DNI Ejecutivo]],Productividad!C:U,8,0) -> jackeline.matos@lozapay.com.pe | U29: =VLOOKUP(Data.[[#This Row],[DNI Ejecutivo]],Productividad!C:U,4,0) -> Senior | V29: =IFERROR(VLOOKUP(Data.[[#This Row],[DNI Ejecutivo]],Ejecutivos.[],11,0),"") -> Lima Hamm | W29: Hamm Ramirez | X29: {=IFERROR(_xlfn.IFS(Data.[[#This Row],[Supervisor]]="Jonathan Lapoint","Norte",Data.[[#This Row],[Supervisor]]="Jorge Fuentes","Norte"),"Lima")} -> Lima | Y29: =VLOOKUP(Data.[[#This Row],[Supervisor]],Ejecutivos!B:S,17,0) -> 44818200 | Z29: =VLOOKUP(Data.[[#This Row],[DNI Supervisor]],Productividad!C:U,8,0) -> hramirezp@lozapay.com.pe | AB29: JACKELINE SOLANGE MATOS QUIÑONES | AC29: =IFERROR(CONCATENATE(Data.[[#This Row],[DNI Ejecutivo]],Data.[[#This Row],[Periodo]]),"") -> 4488101946143 | AD29: =IFERROR(VLOOKUP(Data.[[#This Row],[Código LT]],Reportería.[],10,0),"") | AE29: =IFERROR(VLOOKUP(Data.[[#This Row],[Código LT]],Reportería.[],11,0),"") | AF29: 0 | AI29: =IF(TEXT(Data.[[#This Row],[Periodo]],"mmm-yy")="may-26",VLOOKUP(Data.[[#This Row],[Código]],Reportería!A:BV,57,0),0) -> 0 | AL29: =IF(Data.[[#This Row],[Vol M0]]="",0,0) -> 0 | AM29: =IF(Data.[[#This Row],[Vol M0]]="",0,0) -> 0 | AN29: =IF(Data.[[#This Row],[Vol M0]]="",0,0) -> 0 | AO29: =IF(Data.[[#This Row],[Vol M0]]="",0,0) -> 0 | AP29: =IF(Data.[[#This Row],[Vol M0]]="",0,0) -> 0 | AQ29: =IF(Data.[[#This Row],[Vol M0]]="",0,0) -> 0 | AR29: =IFERROR(IF(OR(AND(OR(Data.[[#This Row],[Categoría]]="Hunter",Data.[[#This Row],[Categoría]]="Senior"),OR(SUMIFS(AF:AF,H:H,Data.[[#This Row],[Ruc]],B:B,Data.[[#This Row],[Periodo]])>=15000,SUMIFS(AI:AI,H:H,Data.[[#This Row],[Ruc]],B:B,Data.[[#This Row],[Periodo]])>=15000,SUMIFS(AL:AL,H:H,Data.[[#This Row],[Ruc]],B:B,Data.[[#This Row],[Periodo]])>=15000,SUMIFS(AO:AO,H:H,Data.[[#This Row],[Ruc]],B:B,Data.[[#This Row],[Periodo]])>=15000)),AND(Data.[[#This Row],[Categoría]]="Elite",OR(SUMIFS(AF:AF,H:H,Data.[[#This Row],[Ruc]],B:B,Data.[[#This Row],[Periodo]])>=25000,SUMIFS(AI:AI,H:H,Data.[[#This Row],[Ruc]],B:B,Data.[[#This Row],[Periodo]])>=25000,SUMIFS(AL:AL,H:H,Data.[[#This Row],[Ruc]],B:B,Data.[[#This Row],[Periodo]])>=25000,SUMIFS(AO:AO,H:H,Data.[[#This Row],[Ruc]],B:B,Data.[[#This Row],[Periodo]])>=25000))),1,0)/COUNTIFS(H:H,Data.[[#This Row],[Ruc]],B:B,Data.[[#This Row],[Periodo]]),0) -> 0
A30: =CONCATENATE(Data.[[#This Row],[Código]],Data.[[#This Row],[Ruc]]) -> 105866220608874055 | B30: 46143 | C30: =IFERROR(VLOOKUP(Data.[[#This Row],[Código LT]],Reportería.[],71,0),"") | D30: =IFERROR(VLOOKUP(Data.[[#This Row],[Código]],BV!A:C,2,0),"") -> 46167 | E30: =IFERROR(VLOOKUP(Data.[[#This Row],[Código]],BV!A:C,3,0),"") -> 46172 | F30: 1058662 | H30: 20608874055 | I30: GROALPERU E.I.R.L. | J30: New Support (SANTA ANITA) | K30: =IF(Data.[[#This Row],[Tipo de Venta]]<>"POS","Atendido",IF(Data.[[#This Row],[Fecha de Instalación]]<>"","Atendido","Ingresado")) -> Atendido | L30: =Data.[[#This Row],[Estado]] -> Atendido | M30: POS | N30: =IFERROR(VLOOKUP(Data.[[#This Row],[Código LT]],Reportería.[],20,0),"") | O30: =IFERROR(VLOOKUP(Data.[[#This Row],[Código LT]],Reportería.[],5,0),"") | P30: =Data.[[#This Row],[GPV Mensual LT]]/COUNTIFS(H:H,Data.[[#This Row],[Ruc]],B:B,Data.[[#This Row],[Periodo]]) -> 40000 | Q30: 80000 | R30: Jackeline Matos | S30: =VLOOKUP(Data.[[#This Row],[Ejecutivo]],Productividad!D:N,11,0) -> 44881019 | T30: =VLOOKUP(Data.[[#This Row],[DNI Ejecutivo]],Productividad!C:U,8,0) -> jackeline.matos@lozapay.com.pe | U30: =VLOOKUP(Data.[[#This Row],[DNI Ejecutivo]],Productividad!C:U,4,0) -> Senior | V30: =IFERROR(VLOOKUP(Data.[[#This Row],[DNI Ejecutivo]],Ejecutivos.[],11,0),"") -> Lima Hamm | W30: Hamm Ramirez | X30: {=IFERROR(_xlfn.IFS(Data.[[#This Row],[Supervisor]]="Jonathan Lapoint","Norte",Data.[[#This Row],[Supervisor]]="Jorge Fuentes","Norte"),"Lima")} -> Lima | Y30: =VLOOKUP(Data.[[#This Row],[Supervisor]],Ejecutivos!B:S,17,0) -> 44818200 | Z30: =VLOOKUP(Data.[[#This Row],[DNI Supervisor]],Productividad!C:U,8,0) -> hramirezp@lozapay.com.pe | AB30: JACKELINE SOLANGE MATOS QUIÑONES | AC30: =IFERROR(CONCATENATE(Data.[[#This Row],[DNI Ejecutivo]],Data.[[#This Row],[Periodo]]),"") -> 4488101946143 | AD30: =IFERROR(VLOOKUP(Data.[[#This Row],[Código LT]],Reportería.[],10,0),"") | AE30: =IFERROR(VLOOKUP(Data.[[#This Row],[Código LT]],Reportería.[],11,0),"") | AF30: 0 | AI30: =IF(TEXT(Data.[[#This Row],[Periodo]],"mmm-yy")="may-26",VLOOKUP(Data.[[#This Row],[Código]],Reportería!A:BV,57,0),0) -> 0 | AL30: =IF(Data.[[#This Row],[Vol M0]]="",0,0) -> 0 | AM30: =IF(Data.[[#This Row],[Vol M0]]="",0,0) -> 0 | AN30: =IF(Data.[[#This Row],[Vol M0]]="",0,0) -> 0 | AO30: =IF(Data.[[#This Row],[Vol M0]]="",0,0) -> 0 | AP30: =IF(Data.[[#This Row],[Vol M0]]="",0,0) -> 0 | AQ30: =IF(Data.[[#This Row],[Vol M0]]="",0,0) -> 0 | AR30: =IFERROR(IF(OR(AND(OR(Data.[[#This Row],[Categoría]]="Hunter",Data.[[#This Row],[Categoría]]="Senior"),OR(SUMIFS(AF:AF,H:H,Data.[[#This Row],[Ruc]],B:B,Data.[[#This Row],[Periodo]])>=15000,SUMIFS(AI:AI,H:H,Data.[[#This Row],[Ruc]],B:B,Data.[[#This Row],[Periodo]])>=15000,SUMIFS(AL:AL,H:H,Data.[[#This Row],[Ruc]],B:B,Data.[[#This Row],[Periodo]])>=15000,SUMIFS(AO:AO,H:H,Data.[[#This Row],[Ruc]],B:B,Data.[[#This Row],[Periodo]])>=15000)),AND(Data.[[#This Row],[Categoría]]="Elite",OR(SUMIFS(AF:AF,H:H,Data.[[#This Row],[Ruc]],B:B,Data.[[#This Row],[Periodo]])>=25000,SUMIFS(AI:AI,H:H,Data.[[#This Row],[Ruc]],B:B,Data.[[#This Row],[Periodo]])>=25000,SUMIFS(AL:AL,H:H,Data.[[#This Row],[Ruc]],B:B,Data.[[#This Row],[Periodo]])>=25000,SUMIFS(AO:AO,H:H,Data.[[#This Row],[Ruc]],B:B,Data.[[#This Row],[Periodo]])>=25000))),1,0)/COUNTIFS(H:H,Data.[[#This Row],[Ruc]],B:B,Data.[[#This Row],[Periodo]]),0) -> 0
A31: =CONCATENATE(Data.[[#This Row],[Código]],Data.[[#This Row],[Ruc]]) -> 595125620604305102 | B31: 46143 | C31: =IFERROR(VLOOKUP(Data.[[#This Row],[Código LT]],Reportería.[],71,0),"") | D31: =IFERROR(VLOOKUP(Data.[[#This Row],[Código]],BV!A:C,2,0),"") | E31: =IFERROR(VLOOKUP(Data.[[#This Row],[Código]],BV!A:C,3,0),"") | F31: 5951256 | G31: 80290684 | H31: 20604305102 | I31: CHARAPO REPUESTOS & AUTOPARTES E.I.R.L. | J31: CHARAPO REPUESTOS & AUTOPARTES | K31: =IF(Data.[[#This Row],[Tipo de Venta]]<>"POS","Atendido",IF(Data.[[#This Row],[Fecha de Instalación]]<>"","Atendido","Ingresado")) -> Atendido | L31: =Data.[[#This Row],[Estado]] -> Atendido | M31: PARLANTE | N31: =IFERROR(VLOOKUP(Data.[[#This Row],[Código LT]],Reportería.[],20,0),"") | O31: =IFERROR(VLOOKUP(Data.[[#This Row],[Código LT]],Reportería.[],5,0),"") | P31: =Data.[[#This Row],[GPV Mensual LT]]/COUNTIFS(H:H,Data.[[#This Row],[Ruc]],B:B,Data.[[#This Row],[Periodo]]) -> 30000 | Q31: 30000 | R31: Marlon Martinez | S31: =VLOOKUP(Data.[[#This Row],[Ejecutivo]],Productividad!D:N,11,0) -> 42858532 | T31: =VLOOKUP(Data.[[#This Row],[DNI Ejecutivo]],Productividad!C:U,8,0) -> marlon.martinez@lozapay.com.pe | U31: =VLOOKUP(Data.[[#This Row],[DNI Ejecutivo]],Productividad!C:U,4,0) -> Hunter | V31: =IFERROR(VLOOKUP(Data.[[#This Row],[DNI Ejecutivo]],Ejecutivos.[],11,0),"") -> Norte Lapoint | W31: Jonathan Lapoint | X31: {=IFERROR(_xlfn.IFS(Data.[[#This Row],[Supervisor]]="Jonathan Lapoint","Norte",Data.[[#This Row],[Supervisor]]="Jorge Fuentes","Norte"),"Lima")} -> Norte | Y31: =VLOOKUP(Data.[[#This Row],[Supervisor]],Ejecutivos!B:S,17,0) -> 70430554 | Z31: =VLOOKUP(Data.[[#This Row],[DNI Supervisor]],Productividad!C:U,8,0) -> jlapointp@lozapay.com.pe | AB31: MARLON ERICK MARTINEZ VALDERRAMA | AC31: =IFERROR(CONCATENATE(Data.[[#This Row],[DNI Ejecutivo]],Data.[[#This Row],[Periodo]]),"") -> 4285853246143 | AD31: =IFERROR(VLOOKUP(Data.[[#This Row],[Código LT]],Reportería.[],10,0),"") | AE31: =IFERROR(VLOOKUP(Data.[[#This Row],[Código LT]],Reportería.[],11,0),"") | AF31: 0 | AI31: =IF(TEXT(Data.[[#This Row],[Periodo]],"mmm-yy")="may-26",VLOOKUP(Data.[[#This Row],[Código]],Reportería!A:BV,57,0),0) -> 2961.4333 | AL31: =IF(Data.[[#This Row],[Vol M0]]="",0,0) -> 0 | AM31: =IF(Data.[[#This Row],[Vol M0]]="",0,0) -> 0 | AN31: =IF(Data.[[#This Row],[Vol M0]]="",0,0) -> 0 | AO31: =IF(Data.[[#This Row],[Vol M0]]="",0,0) -> 0 | AP31: =IF(Data.[[#This Row],[Vol M0]]="",0,0) -> 0 | AQ31: =IF(Data.[[#This Row],[Vol M0]]="",0,0) -> 0 | AR31: =IFERROR(IF(OR(AND(OR(Data.[[#This Row],[Categoría]]="Hunter",Data.[[#This Row],[Categoría]]="Senior"),OR(SUMIFS(AF:AF,H:H,Data.[[#This Row],[Ruc]],B:B,Data.[[#This Row],[Periodo]])>=15000,SUMIFS(AI:AI,H:H,Data.[[#This Row],[Ruc]],B:B,Data.[[#This Row],[Periodo]])>=15000,SUMIFS(AL:AL,H:H,Data.[[#This Row],[Ruc]],B:B,Data.[[#This Row],[Periodo]])>=15000,SUMIFS(AO:AO,H:H,Data.[[#This Row],[Ruc]],B:B,Data.[[#This Row],[Periodo]])>=15000)),AND(Data.[[#This Row],[Categoría]]="Elite",OR(SUMIFS(AF:AF,H:H,Data.[[#This Row],[Ruc]],B:B,Data.[[#This Row],[Periodo]])>=25000,SUMIFS(AI:AI,H:H,Data.[[#This Row],[Ruc]],B:B,Data.[[#This Row],[Periodo]])>=25000,SUMIFS(AL:AL,H:H,Data.[[#This Row],[Ruc]],B:B,Data.[[#This Row],[Periodo]])>=25000,SUMIFS(AO:AO,H:H,Data.[[#This Row],[Ruc]],B:B,Data.[[#This Row],[Periodo]])>=25000))),1,0)/COUNTIFS(H:H,Data.[[#This Row],[Ruc]],B:B,Data.[[#This Row],[Periodo]]),0) -> 0
A32: =CONCATENATE(Data.[[#This Row],[Código]],Data.[[#This Row],[Ruc]]) -> 595121720603692421 | B32: 46143 | C32: =IFERROR(VLOOKUP(Data.[[#This Row],[Código LT]],Reportería.[],71,0),"") | D32: =IFERROR(VLOOKUP(Data.[[#This Row],[Código]],BV!A:C,2,0),"") -> 46167 | E32: =IFERROR(VLOOKUP(Data.[[#This Row],[Código]],BV!A:C,3,0),"") -> 46174 | F32: 5951217 | G32: TJ33261C20847 | H32: 20603692421 | I32: DEA CARINA S.A.C. | J32: TIZZA REAL | K32: =IF(Data.[[#This Row],[Tipo de Venta]]<>"POS","Atendido",IF(Data.[[#This Row],[Fecha de Instalación]]<>"","Atendido","Ingresado")) -> Atendido | L32: =Data.[[#This Row],[Estado]] -> Atendido | M32: POS | N32: =IFERROR(VLOOKUP(Data.[[#This Row],[Código LT]],Reportería.[],20,0),"") | O32: =IFERROR(VLOOKUP(Data.[[#This Row],[Código LT]],Reportería.[],5,0),"") | P32: =Data.[[#This Row],[GPV Mensual LT]]/COUNTIFS(H:H,Data.[[#This Row],[Ruc]],B:B,Data.[[#This Row],[Periodo]]) -> 15000 | Q32: 30000 | R32: Richard Benites | S32: =VLOOKUP(Data.[[#This Row],[Ejecutivo]],Productividad!D:N,11,0) -> 70151010 | T32: =VLOOKUP(Data.[[#This Row],[DNI Ejecutivo]],Productividad!C:U,8,0) -> richard.benites@lozapay.com.pe | U32: =VLOOKUP(Data.[[#This Row],[DNI Ejecutivo]],Productividad!C:U,4,0) -> Hunter | V32: =IFERROR(VLOOKUP(Data.[[#This Row],[DNI Ejecutivo]],Ejecutivos.[],11,0),"") -> Lima Jean | W32: Jean Aguilar | X32: {=IFERROR(_xlfn.IFS(Data.[[#This Row],[Supervisor]]="Jonathan Lapoint","Norte",Data.[[#This Row],[Supervisor]]="Jorge Fuentes","Norte"),"Lima")} -> Lima | Y32: =VLOOKUP(Data.[[#This Row],[Supervisor]],Ejecutivos!B:S,17,0) -> 47688341 | Z32: =VLOOKUP(Data.[[#This Row],[DNI Supervisor]],Productividad!C:U,8,0) -> jaguilar@lozapay.com.pe | AB32: RICHARD PABLO BENITES JURADO | AC32: =IFERROR(CONCATENATE(Data.[[#This Row],[DNI Ejecutivo]],Data.[[#This Row],[Periodo]]),"") -> 7015101046143 | AD32: =IFERROR(VLOOKUP(Data.[[#This Row],[Código LT]],Reportería.[],10,0),"") | AE32: =IFERROR(VLOOKUP(Data.[[#This Row],[Código LT]],Reportería.[],11,0),"") | AF32: 0 | AI32: =IF(TEXT(Data.[[#This Row],[Periodo]],"mmm-yy")="may-26",VLOOKUP(Data.[[#This Row],[Código]],Reportería!A:BV,57,0),0) -> 0 | AL32: =IF(Data.[[#This Row],[Vol M0]]="",0,0) -> 0 | AM32: =IF(Data.[[#This Row],[Vol M0]]="",0,0) -> 0 | AN32: =IF(Data.[[#This Row],[Vol M0]]="",0,0) -> 0 | AO32: =IF(Data.[[#This Row],[Vol M0]]="",0,0) -> 0 | AP32: =IF(Data.[[#This Row],[Vol M0]]="",0,0) -> 0 | AQ32: =IF(Data.[[#This Row],[Vol M0]]="",0,0) -> 0 | AR32: =IFERROR(IF(OR(AND(OR(Data.[[#This Row],[Categoría]]="Hunter",Data.[[#This Row],[Categoría]]="Senior"),OR(SUMIFS(AF:AF,H:H,Data.[[#This Row],[Ruc]],B:B,Data.[[#This Row],[Periodo]])>=15000,SUMIFS(AI:AI,H:H,Data.[[#This Row],[Ruc]],B:B,Data.[[#This Row],[Periodo]])>=15000,SUMIFS(AL:AL,H:H,Data.[[#This Row],[Ruc]],B:B,Data.[[#This Row],[Periodo]])>=15000,SUMIFS(AO:AO,H:H,Data.[[#This Row],[Ruc]],B:B,Data.[[#This Row],[Periodo]])>=15000)),AND(Data.[[#This Row],[Categoría]]="Elite",OR(SUMIFS(AF:AF,H:H,Data.[[#This Row],[Ruc]],B:B,Data.[[#This Row],[Periodo]])>=25000,SUMIFS(AI:AI,H:H,Data.[[#This Row],[Ruc]],B:B,Data.[[#This Row],[Periodo]])>=25000,SUMIFS(AL:AL,H:H,Data.[[#This Row],[Ruc]],B:B,Data.[[#This Row],[Periodo]])>=25000,SUMIFS(AO:AO,H:H,Data.[[#This Row],[Ruc]],B:B,Data.[[#This Row],[Periodo]])>=25000))),1,0)/COUNTIFS(H:H,Data.[[#This Row],[Ruc]],B:B,Data.[[#This Row],[Periodo]]),0) -> 0
A33: =CONCATENATE(Data.[[#This Row],[Código]],Data.[[#This Row],[Ruc]]) -> 595123920603692421 | B33: 46143 | C33: =IFERROR(VLOOKUP(Data.[[#This Row],[Código LT]],Reportería.[],71,0),"") | D33: =IFERROR(VLOOKUP(Data.[[#This Row],[Código]],BV!A:C,2,0),"") -> 46167 | E33: =IFERROR(VLOOKUP(Data.[[#This Row],[Código]],BV!A:C,3,0),"") -> 46174 | F33: 5951239 | G33: TJ33262720033 | H33: 20603692421 | I33: DEA CARINA S.A.C. | J33: TIZZA AREQUIPA | K33: =IF(Data.[[#This Row],[Tipo de Venta]]<>"POS","Atendido",IF(Data.[[#This Row],[Fecha de Instalación]]<>"","Atendido","Ingresado")) -> Atendido | L33: =Data.[[#This Row],[Estado]] -> Atendido | M33: POS | N33: =IFERROR(VLOOKUP(Data.[[#This Row],[Código LT]],Reportería.[],20,0),"") | O33: =IFERROR(VLOOKUP(Data.[[#This Row],[Código LT]],Reportería.[],5,0),"") | P33: =Data.[[#This Row],[GPV Mensual LT]]/COUNTIFS(H:H,Data.[[#This Row],[Ruc]],B:B,Data.[[#This Row],[Periodo]]) -> 15000 | Q33: 30000 | R33: Richard Benites | S33: =VLOOKUP(Data.[[#This Row],[Ejecutivo]],Productividad!D:N,11,0) -> 70151010 | T33: =VLOOKUP(Data.[[#This Row],[DNI Ejecutivo]],Productividad!C:U,8,0) -> richard.benites@lozapay.com.pe | U33: =VLOOKUP(Data.[[#This Row],[DNI Ejecutivo]],Productividad!C:U,4,0) -> Hunter | V33: =IFERROR(VLOOKUP(Data.[[#This Row],[DNI Ejecutivo]],Ejecutivos.[],11,0),"") -> Lima Jean | W33: Jean Aguilar | X33: {=IFERROR(_xlfn.IFS(Data.[[#This Row],[Supervisor]]="Jonathan Lapoint","Norte",Data.[[#This Row],[Supervisor]]="Jorge Fuentes","Norte"),"Lima")} -> Lima | Y33: =VLOOKUP(Data.[[#This Row],[Supervisor]],Ejecutivos!B:S,17,0) -> 47688341 | Z33: =VLOOKUP(Data.[[#This Row],[DNI Supervisor]],Productividad!C:U,8,0) -> jaguilar@lozapay.com.pe | AB33: RICHARD PABLO BENITES JURADO | AC33: =IFERROR(CONCATENATE(Data.[[#This Row],[DNI Ejecutivo]],Data.[[#This Row],[Periodo]]),"") -> 7015101046143 | AD33: =IFERROR(VLOOKUP(Data.[[#This Row],[Código LT]],Reportería.[],10,0),"") | AE33: =IFERROR(VLOOKUP(Data.[[#This Row],[Código LT]],Reportería.[],11,0),"") | AF33: 0 | AI33: =IF(TEXT(Data.[[#This Row],[Periodo]],"mmm-yy")="may-26",VLOOKUP(Data.[[#This Row],[Código]],Reportería!A:BV,57,0),0) -> 597 | AL33: =IF(Data.[[#This Row],[Vol M0]]="",0,0) -> 0 | AM33: =IF(Data.[[#This Row],[Vol M0]]="",0,0) -> 0 | AN33: =IF(Data.[[#This Row],[Vol M0]]="",0,0) -> 0 | AO33: =IF(Data.[[#This Row],[Vol M0]]="",0,0) -> 0 | AP33: =IF(Data.[[#This Row],[Vol M0]]="",0,0) -> 0 | AQ33: =IF(Data.[[#This Row],[Vol M0]]="",0,0) -> 0 | AR33: =IFERROR(IF(OR(AND(OR(Data.[[#This Row],[Categoría]]="Hunter",Data.[[#This Row],[Categoría]]="Senior"),OR(SUMIFS(AF:AF,H:H,Data.[[#This Row],[Ruc]],B:B,Data.[[#This Row],[Periodo]])>=15000,SUMIFS(AI:AI,H:H,Data.[[#This Row],[Ruc]],B:B,Data.[[#This Row],[Periodo]])>=15000,SUMIFS(AL:AL,H:H,Data.[[#This Row],[Ruc]],B:B,Data.[[#This Row],[Periodo]])>=15000,SUMIFS(AO:AO,H:H,Data.[[#This Row],[Ruc]],B:B,Data.[[#This Row],[Periodo]])>=15000)),AND(Data.[[#This Row],[Categoría]]="Elite",OR(SUMIFS(AF:AF,H:H,Data.[[#This Row],[Ruc]],B:B,Data.[[#This Row],[Periodo]])>=25000,SUMIFS(AI:AI,H:H,Data.[[#This Row],[Ruc]],B:B,Data.[[#This Row],[Periodo]])>=25000,SUMIFS(AL:AL,H:H,Data.[[#This Row],[Ruc]],B:B,Data.[[#This Row],[Periodo]])>=25000,SUMIFS(AO:AO,H:H,Data.[[#This Row],[Ruc]],B:B,Data.[[#This Row],[Periodo]])>=25000))),1,0)/COUNTIFS(H:H,Data.[[#This Row],[Ruc]],B:B,Data.[[#This Row],[Periodo]]),0) -> 0
A34: =CONCATENATE(Data.[[#This Row],[Código]],Data.[[#This Row],[Ruc]]) -> 595153220611895110 | B34: 46143 | C34: =IFERROR(VLOOKUP(Data.[[#This Row],[Código LT]],Reportería.[],71,0),"") | D34: =IFERROR(VLOOKUP(Data.[[#This Row],[Código]],BV!A:C,2,0),"") -> 46168 | E34: =IFERROR(VLOOKUP(Data.[[#This Row],[Código]],BV!A:C,3,0),"") -> 46168 | F34: 5951532 | G34: TJ33261C21178 | H34: 20611895110 | I34: EL HORNITO BAKERY S.A.C. | J34: HORNITO BAKERY | K34: =IF(Data.[[#This Row],[Tipo de Venta]]<>"POS","Atendido",IF(Data.[[#This Row],[Fecha de Instalación]]<>"","Atendido","Ingresado")) -> Atendido | L34: =Data.[[#This Row],[Estado]] -> Atendido | M34: POS | N34: =IFERROR(VLOOKUP(Data.[[#This Row],[Código LT]],Reportería.[],20,0),"") | O34: =IFERROR(VLOOKUP(Data.[[#This Row],[Código LT]],Reportería.[],5,0),"") | P34: =Data.[[#This Row],[GPV Mensual LT]]/COUNTIFS(H:H,Data.[[#This Row],[Ruc]],B:B,Data.[[#This Row],[Periodo]]) -> 50000 | Q34: 50000 | R34: Milagros Zuniga | S34: =VLOOKUP(Data.[[#This Row],[Ejecutivo]],Productividad!D:N,11,0) -> 75167462 | T34: =VLOOKUP(Data.[[#This Row],[DNI Ejecutivo]],Productividad!C:U,8,0) -> milagros.zuniga@lozapay.com.pe | U34: =VLOOKUP(Data.[[#This Row],[DNI Ejecutivo]],Productividad!C:U,4,0) -> Hunter | V34: =IFERROR(VLOOKUP(Data.[[#This Row],[DNI Ejecutivo]],Ejecutivos.[],11,0),"") -> Norte Fuentes | W34: Jorge Fuentes | X34: {=IFERROR(_xlfn.IFS(Data.[[#This Row],[Supervisor]]="Jonathan Lapoint","Norte",Data.[[#This Row],[Supervisor]]="Jorge Fuentes","Norte"),"Lima")} -> Norte | Y34: =VLOOKUP(Data.[[#This Row],[Supervisor]],Ejecutivos!B:S,17,0) -> 70059865 | Z34: =VLOOKUP(Data.[[#This Row],[DNI Supervisor]],Productividad!C:U,8,0) -> jfuentes@lozapay.com.pe | AB34: MILAGROS STEFANY ZUNIGA TEJEDA | AC34: =IFERROR(CONCATENATE(Data.[[#This Row],[DNI Ejecutivo]],Data.[[#This Row],[Periodo]]),"") -> 7516746246143 | AD34: =IFERROR(VLOOKUP(Data.[[#This Row],[Código LT]],Reportería.[],10,0),"") | AE34: =IFERROR(VLOOKUP(Data.[[#This Row],[Código LT]],Reportería.[],11,0),"") | AF34: 2792.7 | AI34: =IF(TEXT(Data.[[#This Row],[Periodo]],"mmm-yy")="may-26",VLOOKUP(Data.[[#This Row],[Código]],Reportería!A:BV,57,0),0) -> 16903.2 | AL34: =IF(Data.[[#This Row],[Vol M0]]="",0,0) -> 0 | AM34: =IF(Data.[[#This Row],[Vol M0]]="",0,0) -> 0 | AN34: =IF(Data.[[#This Row],[Vol M0]]="",0,0) -> 0 | AO34: =IF(Data.[[#This Row],[Vol M0]]="",0,0) -> 0 | AP34: =IF(Data.[[#This Row],[Vol M0]]="",0,0) -> 0 | AQ34: =IF(Data.[[#This Row],[Vol M0]]="",0,0) -> 0 | AR34: =IFERROR(IF(OR(AND(OR(Data.[[#This Row],[Categoría]]="Hunter",Data.[[#This Row],[Categoría]]="Senior"),OR(SUMIFS(AF:AF,H:H,Data.[[#This Row],[Ruc]],B:B,Data.[[#This Row],[Periodo]])>=15000,SUMIFS(AI:AI,H:H,Data.[[#This Row],[Ruc]],B:B,Data.[[#This Row],[Periodo]])>=15000,SUMIFS(AL:AL,H:H,Data.[[#This Row],[Ruc]],B:B,Data.[[#This Row],[Periodo]])>=15000,SUMIFS(AO:AO,H:H,Data.[[#This Row],[Ruc]],B:B,Data.[[#This Row],[Periodo]])>=15000)),AND(Data.[[#This Row],[Categoría]]="Elite",OR(SUMIFS(AF:AF,H:H,Data.[[#This Row],[Ruc]],B:B,Data.[[#This Row],[Periodo]])>=25000,SUMIFS(AI:AI,H:H,Data.[[#This Row],[Ruc]],B:B,Data.[[#This Row],[Periodo]])>=25000,SUMIFS(AL:AL,H:H,Data.[[#This Row],[Ruc]],B:B,Data.[[#This Row],[Periodo]])>=25000,SUMIFS(AO:AO,H:H,Data.[[#This Row],[Ruc]],B:B,Data.[[#This Row],[Periodo]])>=25000))),1,0)/COUNTIFS(H:H,Data.[[#This Row],[Ruc]],B:B,Data.[[#This Row],[Periodo]]),0) -> 1
A35: =CONCATENATE(Data.[[#This Row],[Código]],Data.[[#This Row],[Ruc]]) -> 595169820613702629 | B35: 46143 | C35: =IFERROR(VLOOKUP(Data.[[#This Row],[Código LT]],Reportería.[],71,0),"") | D35: =IFERROR(VLOOKUP(Data.[[#This Row],[Código]],BV!A:C,2,0),"") -> 46168 | E35: =IFERROR(VLOOKUP(Data.[[#This Row],[Código]],BV!A:C,3,0),"") -> 46169 | F35: 5951698 | G35: TJ33262820241 | H35: 20613702629 | I35: FAVIPESA S.A.C. | J35: VICTORIA MARKT | K35: =IF(Data.[[#This Row],[Tipo de Venta]]<>"POS","Atendido",IF(Data.[[#This Row],[Fecha de Instalación]]<>"","Atendido","Ingresado")) -> Atendido | L35: =Data.[[#This Row],[Estado]] -> Atendido | M35: POS | N35: =IFERROR(VLOOKUP(Data.[[#This Row],[Código LT]],Reportería.[],20,0),"") | O35: =IFERROR(VLOOKUP(Data.[[#This Row],[Código LT]],Reportería.[],5,0),"") | P35: =Data.[[#This Row],[GPV Mensual LT]]/COUNTIFS(H:H,Data.[[#This Row],[Ruc]],B:B,Data.[[#This Row],[Periodo]]) -> 100000 | Q35: 200000 | R35: Guadalupe Del Pino | S35: =VLOOKUP(Data.[[#This Row],[Ejecutivo]],Productividad!D:N,11,0) -> 77016095 | T35: =VLOOKUP(Data.[[#This Row],[DNI Ejecutivo]],Productividad!C:U,8,0) -> nelly.delpino@lozapay.com.pe | U35: =VLOOKUP(Data.[[#This Row],[DNI Ejecutivo]],Productividad!C:U,4,0) -> Hunter | V35: =IFERROR(VLOOKUP(Data.[[#This Row],[DNI Ejecutivo]],Ejecutivos.[],11,0),"") -> Lima Jean | W35: Jean Aguilar | X35: {=IFERROR(_xlfn.IFS(Data.[[#This Row],[Supervisor]]="Jonathan Lapoint","Norte",Data.[[#This Row],[Supervisor]]="Jorge Fuentes","Norte"),"Lima")} -> Lima | Y35: =VLOOKUP(Data.[[#This Row],[Supervisor]],Ejecutivos!B:S,17,0) -> 47688341 | Z35: =VLOOKUP(Data.[[#This Row],[DNI Supervisor]],Productividad!C:U,8,0) -> jaguilar@lozapay.com.pe | AB35: NELLY GUADALUPE DEL PINO MONDRAGON | AC35: =IFERROR(CONCATENATE(Data.[[#This Row],[DNI Ejecutivo]],Data.[[#This Row],[Periodo]]),"") -> 7701609546143 | AD35: =IFERROR(VLOOKUP(Data.[[#This Row],[Código LT]],Reportería.[],10,0),"") | AE35: =IFERROR(VLOOKUP(Data.[[#This Row],[Código LT]],Reportería.[],11,0),"") | AF35: 3468.24 | AI35: =IF(TEXT(Data.[[#This Row],[Periodo]],"mmm-yy")="may-26",VLOOKUP(Data.[[#This Row],[Código]],Reportería!A:BV,57,0),0) -> 51080.35 | AL35: =IF(Data.[[#This Row],[Vol M0]]="",0,0) -> 0 | AM35: =IF(Data.[[#This Row],[Vol M0]]="",0,0) -> 0 | AN35: =IF(Data.[[#This Row],[Vol M0]]="",0,0) -> 0 | AO35: =IF(Data.[[#This Row],[Vol M0]]="",0,0) -> 0 | AP35: =IF(Data.[[#This Row],[Vol M0]]="",0,0) -> 0 | AQ35: =IF(Data.[[#This Row],[Vol M0]]="",0,0) -> 0 | AR35: =IFERROR(IF(OR(AND(OR(Data.[[#This Row],[Categoría]]="Hunter",Data.[[#This Row],[Categoría]]="Senior"),OR(SUMIFS(AF:AF,H:H,Data.[[#This Row],[Ruc]],B:B,Data.[[#This Row],[Periodo]])>=15000,SUMIFS(AI:AI,H:H,Data.[[#This Row],[Ruc]],B:B,Data.[[#This Row],[Periodo]])>=15000,SUMIFS(AL:AL,H:H,Data.[[#This Row],[Ruc]],B:B,Data.[[#This Row],[Periodo]])>=15000,SUMIFS(AO:AO,H:H,Data.[[#This Row],[Ruc]],B:B,Data.[[#This Row],[Periodo]])>=15000)),AND(Data.[[#This Row],[Categoría]]="Elite",OR(SUMIFS(AF:AF,H:H,Data.[[#This Row],[Ruc]],B:B,Data.[[#This Row],[Periodo]])>=25000,SUMIFS(AI:AI,H:H,Data.[[#This Row],[Ruc]],B:B,Data.[[#This Row],[Periodo]])>=25000,SUMIFS(AL:AL,H:H,Data.[[#This Row],[Ruc]],B:B,Data.[[#This Row],[Periodo]])>=25000,SUMIFS(AO:AO,H:H,Data.[[#This Row],[Ruc]],B:B,Data.[[#This Row],[Periodo]])>=25000))),1,0)/COUNTIFS(H:H,Data.[[#This Row],[Ruc]],B:B,Data.[[#This Row],[Periodo]]),0) -> 0.5
A36: =CONCATENATE(Data.[[#This Row],[Código]],Data.[[#This Row],[Ruc]]) -> 595172220613702629 | B36: 46143 | C36: =IFERROR(VLOOKUP(Data.[[#This Row],[Código LT]],Reportería.[],71,0),"") | D36: =IFERROR(VLOOKUP(Data.[[#This Row],[Código]],BV!A:C,2,0),"") -> 46168 | E36: =IFERROR(VLOOKUP(Data.[[#This Row],[Código]],BV!A:C,3,0),"") -> 46169 | F36: 5951722 | G36: TJ33261D20026 | H36: 20613702629 | I36: FAVIPESA S.A.C. | J36: VICTORIA MARKT | K36: =IF(Data.[[#This Row],[Tipo de Venta]]<>"POS","Atendido",IF(Data.[[#This Row],[Fecha de Instalación]]<>"","Atendido","Ingresado")) -> Atendido | L36: =Data.[[#This Row],[Estado]] -> Atendido | M36: POS | N36: =IFERROR(VLOOKUP(Data.[[#This Row],[Código LT]],Reportería.[],20,0),"") | O36: =IFERROR(VLOOKUP(Data.[[#This Row],[Código LT]],Reportería.[],5,0),"") | P36: =Data.[[#This Row],[GPV Mensual LT]]/COUNTIFS(H:H,Data.[[#This Row],[Ruc]],B:B,Data.[[#This Row],[Periodo]]) -> 100000 | Q36: 200000 | R36: Guadalupe Del Pino | S36: =VLOOKUP(Data.[[#This Row],[Ejecutivo]],Productividad!D:N,11,0) -> 77016095 | T36: =VLOOKUP(Data.[[#This Row],[DNI Ejecutivo]],Productividad!C:U,8,0) -> nelly.delpino@lozapay.com.pe | U36: =VLOOKUP(Data.[[#This Row],[DNI Ejecutivo]],Productividad!C:U,4,0) -> Hunter | V36: =IFERROR(VLOOKUP(Data.[[#This Row],[DNI Ejecutivo]],Ejecutivos.[],11,0),"") -> Lima Jean | W36: Jean Aguilar | X36: {=IFERROR(_xlfn.IFS(Data.[[#This Row],[Supervisor]]="Jonathan Lapoint","Norte",Data.[[#This Row],[Supervisor]]="Jorge Fuentes","Norte"),"Lima")} -> Lima | Y36: =VLOOKUP(Data.[[#This Row],[Supervisor]],Ejecutivos!B:S,17,0) -> 47688341 | Z36: =VLOOKUP(Data.[[#This Row],[DNI Supervisor]],Productividad!C:U,8,0) -> jaguilar@lozapay.com.pe | AB36: NELLY GUADALUPE DEL PINO MONDRAGON | AC36: =IFERROR(CONCATENATE(Data.[[#This Row],[DNI Ejecutivo]],Data.[[#This Row],[Periodo]]),"") -> 7701609546143 | AD36: =IFERROR(VLOOKUP(Data.[[#This Row],[Código LT]],Reportería.[],10,0),"") | AE36: =IFERROR(VLOOKUP(Data.[[#This Row],[Código LT]],Reportería.[],11,0),"") | AF36: 8456.14 | AI36: =IF(TEXT(Data.[[#This Row],[Periodo]],"mmm-yy")="may-26",VLOOKUP(Data.[[#This Row],[Código]],Reportería!A:BV,57,0),0) -> 33707.72 | AL36: =IF(Data.[[#This Row],[Vol M0]]="",0,0) -> 0 | AM36: =IF(Data.[[#This Row],[Vol M0]]="",0,0) -> 0 | AN36: =IF(Data.[[#This Row],[Vol M0]]="",0,0) -> 0 | AO36: =IF(Data.[[#This Row],[Vol M0]]="",0,0) -> 0 | AP36: =IF(Data.[[#This Row],[Vol M0]]="",0,0) -> 0 | AQ36: =IF(Data.[[#This Row],[Vol M0]]="",0,0) -> 0 | AR36: =IFERROR(IF(OR(AND(OR(Data.[[#This Row],[Categoría]]="Hunter",Data.[[#This Row],[Categoría]]="Senior"),OR(SUMIFS(AF:AF,H:H,Data.[[#This Row],[Ruc]],B:B,Data.[[#This Row],[Periodo]])>=15000,SUMIFS(AI:AI,H:H,Data.[[#This Row],[Ruc]],B:B,Data.[[#This Row],[Periodo]])>=15000,SUMIFS(AL:AL,H:H,Data.[[#This Row],[Ruc]],B:B,Data.[[#This Row],[Periodo]])>=15000,SUMIFS(AO:AO,H:H,Data.[[#This Row],[Ruc]],B:B,Data.[[#This Row],[Periodo]])>=15000)),AND(Data.[[#This Row],[Categoría]]="Elite",OR(SUMIFS(AF:AF,H:H,Data.[[#This Row],[Ruc]],B:B,Data.[[#This Row],[Periodo]])>=25000,SUMIFS(AI:AI,H:H,Data.[[#This Row],[Ruc]],B:B,Data.[[#This Row],[Periodo]])>=25000,SUMIFS(AL:AL,H:H,Data.[[#This Row],[Ruc]],B:B,Data.[[#This Row],[Periodo]])>=25000,SUMIFS(AO:AO,H:H,Data.[[#This Row],[Ruc]],B:B,Data.[[#This Row],[Periodo]])>=25000))),1,0)/COUNTIFS(H:H,Data.[[#This Row],[Ruc]],B:B,Data.[[#This Row],[Periodo]]),0) -> 0.5
A37: =CONCATENATE(Data.[[#This Row],[Código]],Data.[[#This Row],[Ruc]]) -> 105871220607818526 | B37: 46143 | C37: =IFERROR(VLOOKUP(Data.[[#This Row],[Código LT]],Reportería.[],71,0),"") | D37: =IFERROR(VLOOKUP(Data.[[#This Row],[Código]],BV!A:C,2,0),"") -> 46168 | E37: =IFERROR(VLOOKUP(Data.[[#This Row],[Código]],BV!A:C,3,0),"") -> 46170 | F37: 1058712 | H37: 20607818526 | I37: EUROSPORT AUTOMOTRIZ S.A.C. | J37: EUROSPORT | K37: =IF(Data.[[#This Row],[Tipo de Venta]]<>"POS","Atendido",IF(Data.[[#This Row],[Fecha de Instalación]]<>"","Atendido","Ingresado")) -> Atendido | L37: =Data.[[#This Row],[Estado]] -> Atendido | M37: POS | N37: =IFERROR(VLOOKUP(Data.[[#This Row],[Código LT]],Reportería.[],20,0),"") | O37: =IFERROR(VLOOKUP(Data.[[#This Row],[Código LT]],Reportería.[],5,0),"") | P37: =Data.[[#This Row],[GPV Mensual LT]]/COUNTIFS(H:H,Data.[[#This Row],[Ruc]],B:B,Data.[[#This Row],[Periodo]]) -> 40000 | Q37: 40000 | R37: Yessica Ruiz | S37: =VLOOKUP(Data.[[#This Row],[Ejecutivo]],Productividad!D:N,11,0) -> 40463169 | T37: =VLOOKUP(Data.[[#This Row],[DNI Ejecutivo]],Productividad!C:U,8,0) -> yessica.ruiz@lozapay.com.pe | U37: =VLOOKUP(Data.[[#This Row],[DNI Ejecutivo]],Productividad!C:U,4,0) -> Senior | V37: =IFERROR(VLOOKUP(Data.[[#This Row],[DNI Ejecutivo]],Ejecutivos.[],11,0),"") -> Lima Palomino | W37: Carlos Palomino | X37: {=IFERROR(_xlfn.IFS(Data.[[#This Row],[Supervisor]]="Jonathan Lapoint","Norte",Data.[[#This Row],[Supervisor]]="Jorge Fuentes","Norte"),"Lima")} -> Lima | Y37: =VLOOKUP(Data.[[#This Row],[Supervisor]],Ejecutivos!B:S,17,0) -> 41718975 | Z37: =VLOOKUP(Data.[[#This Row],[DNI Supervisor]],Productividad!C:U,8,0) -> carlos.palomino@lozapay.com.pe | AB37: YESSICA YVON RUIZ BAUTISTA | AC37: =IFERROR(CONCATENATE(Data.[[#This Row],[DNI Ejecutivo]],Data.[[#This Row],[Periodo]]),"") -> 4046316946143 | AD37: =IFERROR(VLOOKUP(Data.[[#This Row],[Código LT]],Reportería.[],10,0),"") | AE37: =IFERROR(VLOOKUP(Data.[[#This Row],[Código LT]],Reportería.[],11,0),"") | AF37: 0 | AI37: =IF(TEXT(Data.[[#This Row],[Periodo]],"mmm-yy")="may-26",VLOOKUP(Data.[[#This Row],[Código]],Reportería!A:BV,57,0),0) -> 8015 | AL37: =IF(Data.[[#This Row],[Vol M0]]="",0,0) -> 0 | AM37: =IF(Data.[[#This Row],[Vol M0]]="",0,0) -> 0 | AN37: =IF(Data.[[#This Row],[Vol M0]]="",0,0) -> 0 | AO37: =IF(Data.[[#This Row],[Vol M0]]="",0,0) -> 0 | AP37: =IF(Data.[[#This Row],[Vol M0]]="",0,0) -> 0 | AQ37: =IF(Data.[[#This Row],[Vol M0]]="",0,0) -> 0 | AR37: =IFERROR(IF(OR(AND(OR(Data.[[#This Row],[Categoría]]="Hunter",Data.[[#This Row],[Categoría]]="Senior"),OR(SUMIFS(AF:AF,H:H,Data.[[#This Row],[Ruc]],B:B,Data.[[#This Row],[Periodo]])>=15000,SUMIFS(AI:AI,H:H,Data.[[#This Row],[Ruc]],B:B,Data.[[#This Row],[Periodo]])>=15000,SUMIFS(AL:AL,H:H,Data.[[#This Row],[Ruc]],B:B,Data.[[#This Row],[Periodo]])>=15000,SUMIFS(AO:AO,H:H,Data.[[#This Row],[Ruc]],B:B,Data.[[#This Row],[Periodo]])>=15000)),AND(Data.[[#This Row],[Categoría]]="Elite",OR(SUMIFS(AF:AF,H:H,Data.[[#This Row],[Ruc]],B:B,Data.[[#This Row],[Periodo]])>=25000,SUMIFS(AI:AI,H:H,Data.[[#This Row],[Ruc]],B:B,Data.[[#This Row],[Periodo]])>=25000,SUMIFS(AL:AL,H:H,Data.[[#This Row],[Ruc]],B:B,Data.[[#This Row],[Periodo]])>=25000,SUMIFS(AO:AO,H:H,Data.[[#This Row],[Ruc]],B:B,Data.[[#This Row],[Periodo]])>=25000))),1,0)/COUNTIFS(H:H,Data.[[#This Row],[Ruc]],B:B,Data.[[#This Row],[Periodo]]),0) -> 0
A38: =CONCATENATE(Data.[[#This Row],[Código]],Data.[[#This Row],[Ruc]]) -> 595260720611374420 | B38: 46143 | C38: =IFERROR(VLOOKUP(Data.[[#This Row],[Código LT]],Reportería.[],71,0),"") | D38: =IFERROR(VLOOKUP(Data.[[#This Row],[Código]],BV!A:C,2,0),"") -> 46170 | E38: =IFERROR(VLOOKUP(Data.[[#This Row],[Código]],BV!A:C,3,0),"") -> 46170 | F38: 5952607 | G38: TJ33261C21730 | H38: 20611374420 | I38: SIX NAVARRO INVERSIONES E.I.R.L. | J38: SIX KARAOKE | K38: =IF(Data.[[#This Row],[Tipo de Venta]]<>"POS","Atendido",IF(Data.[[#This Row],[Fecha de Instalación]]<>"","Atendido","Ingresado")) -> Atendido | L38: =Data.[[#This Row],[Estado]] -> Atendido | M38: POS | N38: =IFERROR(VLOOKUP(Data.[[#This Row],[Código LT]],Reportería.[],20,0),"") | O38: =IFERROR(VLOOKUP(Data.[[#This Row],[Código LT]],Reportería.[],5,0),"") | P38: =Data.[[#This Row],[GPV Mensual LT]]/COUNTIFS(H:H,Data.[[#This Row],[Ruc]],B:B,Data.[[#This Row],[Periodo]]) -> 40000 | Q38: 40000 | R38: Marlon Martinez | S38: =VLOOKUP(Data.[[#This Row],[Ejecutivo]],Productividad!D:N,11,0) -> 42858532 | T38: =VLOOKUP(Data.[[#This Row],[DNI Ejecutivo]],Productividad!C:U,8,0) -> marlon.martinez@lozapay.com.pe | U38: =VLOOKUP(Data.[[#This Row],[DNI Ejecutivo]],Productividad!C:U,4,0) -> Hunter | V38: =IFERROR(VLOOKUP(Data.[[#This Row],[DNI Ejecutivo]],Ejecutivos.[],11,0),"") -> Norte Lapoint | W38: Jonathan Lapoint | X38: {=IFERROR(_xlfn.IFS(Data.[[#This Row],[Supervisor]]="Jonathan Lapoint","Norte",Data.[[#This Row],[Supervisor]]="Jorge Fuentes","Norte"),"Lima")} -> Norte | Y38: =VLOOKUP(Data.[[#This Row],[Supervisor]],Ejecutivos!B:S,17,0) -> 70430554 | Z38: =VLOOKUP(Data.[[#This Row],[DNI Supervisor]],Productividad!C:U,8,0) -> jlapointp@lozapay.com.pe | AB38: MARLON ERICK MARTINEZ VALDERRAMA | AC38: =IFERROR(CONCATENATE(Data.[[#This Row],[DNI Ejecutivo]],Data.[[#This Row],[Periodo]]),"") -> 4285853246143 | AD38: =IFERROR(VLOOKUP(Data.[[#This Row],[Código LT]],Reportería.[],10,0),"") | AE38: =IFERROR(VLOOKUP(Data.[[#This Row],[Código LT]],Reportería.[],11,0),"") | AF38: 1 | AI38: =IF(TEXT(Data.[[#This Row],[Periodo]],"mmm-yy")="may-26",VLOOKUP(Data.[[#This Row],[Código]],Reportería!A:BV,57,0),0) -> 1721.5 | AL38: =IF(Data.[[#This Row],[Vol M0]]="",0,0) -> 0 | AM38: =IF(Data.[[#This Row],[Vol M0]]="",0,0) -> 0 | AN38: =IF(Data.[[#This Row],[Vol M0]]="",0,0) -> 0 | AO38: =IF(Data.[[#This Row],[Vol M0]]="",0,0) -> 0 | AP38: =IF(Data.[[#This Row],[Vol M0]]="",0,0) -> 0 | AQ38: =IF(Data.[[#This Row],[Vol M0]]="",0,0) -> 0 | AR38: =IFERROR(IF(OR(AND(OR(Data.[[#This Row],[Categoría]]="Hunter",Data.[[#This Row],[Categoría]]="Senior"),OR(SUMIFS(AF:AF,H:H,Data.[[#This Row],[Ruc]],B:B,Data.[[#This Row],[Periodo]])>=15000,SUMIFS(AI:AI,H:H,Data.[[#This Row],[Ruc]],B:B,Data.[[#This Row],[Periodo]])>=15000,SUMIFS(AL:AL,H:H,Data.[[#This Row],[Ruc]],B:B,Data.[[#This Row],[Periodo]])>=15000,SUMIFS(AO:AO,H:H,Data.[[#This Row],[Ruc]],B:B,Data.[[#This Row],[Periodo]])>=15000)),AND(Data.[[#This Row],[Categoría]]="Elite",OR(SUMIFS(AF:AF,H:H,Data.[[#This Row],[Ruc]],B:B,Data.[[#This Row],[Periodo]])>=25000,SUMIFS(AI:AI,H:H,Data.[[#This Row],[Ruc]],B:B,Data.[[#This Row],[Periodo]])>=25000,SUMIFS(AL:AL,H:H,Data.[[#This Row],[Ruc]],B:B,Data.[[#This Row],[Periodo]])>=25000,SUMIFS(AO:AO,H:H,Data.[[#This Row],[Ruc]],B:B,Data.[[#This Row],[Periodo]])>=25000))),1,0)/COUNTIFS(H:H,Data.[[#This Row],[Ruc]],B:B,Data.[[#This Row],[Periodo]]),0) -> 0
A39: =CONCATENATE(Data.[[#This Row],[Código]],Data.[[#This Row],[Ruc]]) -> 595285310477313928 | B39: 46143 | C39: =IFERROR(VLOOKUP(Data.[[#This Row],[Código LT]],Reportería.[],71,0),"") | D39: =IFERROR(VLOOKUP(Data.[[#This Row],[Código]],BV!A:C,2,0),"") -> 46170 | E39: =IFERROR(VLOOKUP(Data.[[#This Row],[Código]],BV!A:C,3,0),"") -> 46170 | F39: 5952853 | G39: TJ33261A20349 | H39: 10477313928 | I39: CASTAÑEDA MARAVI PAMELA DEL PILAR | J39: Market San Roque | K39: =IF(Data.[[#This Row],[Tipo de Venta]]<>"POS","Atendido",IF(Data.[[#This Row],[Fecha de Instalación]]<>"","Atendido","Ingresado")) -> Atendido | L39: =Data.[[#This Row],[Estado]] -> Atendido | M39: POS | N39: =IFERROR(VLOOKUP(Data.[[#This Row],[Código LT]],Reportería.[],20,0),"") | O39: =IFERROR(VLOOKUP(Data.[[#This Row],[Código LT]],Reportería.[],5,0),"") | P39: =Data.[[#This Row],[GPV Mensual LT]]/COUNTIFS(H:H,Data.[[#This Row],[Ruc]],B:B,Data.[[#This Row],[Periodo]]) -> 50000 | Q39: 100000 | R39: Jorge Jaimes | S39: =VLOOKUP(Data.[[#This Row],[Ejecutivo]],Productividad!D:N,11,0) -> 76524006 | T39: =VLOOKUP(Data.[[#This Row],[DNI Ejecutivo]],Productividad!C:U,8,0) -> jjaimesb@lozapay.com.pe | U39: =VLOOKUP(Data.[[#This Row],[DNI Ejecutivo]],Productividad!C:U,4,0) -> Senior | V39: =IFERROR(VLOOKUP(Data.[[#This Row],[DNI Ejecutivo]],Ejecutivos.[],11,0),"") -> Lima Palomino | W39: Carlos Palomino | X39: {=IFERROR(_xlfn.IFS(Data.[[#This Row],[Supervisor]]="Jonathan Lapoint","Norte",Data.[[#This Row],[Supervisor]]="Jorge Fuentes","Norte"),"Lima")} -> Lima | Y39: =VLOOKUP(Data.[[#This Row],[Supervisor]],Ejecutivos!B:S,17,0) -> 41718975 | Z39: =VLOOKUP(Data.[[#This Row],[DNI Supervisor]],Productividad!C:U,8,0) -> carlos.palomino@lozapay.com.pe | AB39: JORGE LUIS JAIMES BARROSO | AC39: =IFERROR(CONCATENATE(Data.[[#This Row],[DNI Ejecutivo]],Data.[[#This Row],[Periodo]]),"") -> 7652400646143 | AD39: =IFERROR(VLOOKUP(Data.[[#This Row],[Código LT]],Reportería.[],10,0),"") | AE39: =IFERROR(VLOOKUP(Data.[[#This Row],[Código LT]],Reportería.[],11,0),"") | AF39: 7 | AI39: =IF(TEXT(Data.[[#This Row],[Periodo]],"mmm-yy")="may-26",VLOOKUP(Data.[[#This Row],[Código]],Reportería!A:BV,57,0),0) -> 5667.2 | AL39: =IF(Data.[[#This Row],[Vol M0]]="",0,0) -> 0 | AM39: =IF(Data.[[#This Row],[Vol M0]]="",0,0) -> 0 | AN39: =IF(Data.[[#This Row],[Vol M0]]="",0,0) -> 0 | AO39: =IF(Data.[[#This Row],[Vol M0]]="",0,0) -> 0 | AP39: =IF(Data.[[#This Row],[Vol M0]]="",0,0) -> 0 | AQ39: =IF(Data.[[#This Row],[Vol M0]]="",0,0) -> 0 | AR39: =IFERROR(IF(OR(AND(OR(Data.[[#This Row],[Categoría]]="Hunter",Data.[[#This Row],[Categoría]]="Senior"),OR(SUMIFS(AF:AF,H:H,Data.[[#This Row],[Ruc]],B:B,Data.[[#This Row],[Periodo]])>=15000,SUMIFS(AI:AI,H:H,Data.[[#This Row],[Ruc]],B:B,Data.[[#This Row],[Periodo]])>=15000,SUMIFS(AL:AL,H:H,Data.[[#This Row],[Ruc]],B:B,Data.[[#This Row],[Periodo]])>=15000,SUMIFS(AO:AO,H:H,Data.[[#This Row],[Ruc]],B:B,Data.[[#This Row],[Periodo]])>=15000)),AND(Data.[[#This Row],[Categoría]]="Elite",OR(SUMIFS(AF:AF,H:H,Data.[[#This Row],[Ruc]],B:B,Data.[[#This Row],[Periodo]])>=25000,SUMIFS(AI:AI,H:H,Data.[[#This Row],[Ruc]],B:B,Data.[[#This Row],[Periodo]])>=25000,SUMIFS(AL:AL,H:H,Data.[[#This Row],[Ruc]],B:B,Data.[[#This Row],[Periodo]])>=25000,SUMIFS(AO:AO,H:H,Data.[[#This Row],[Ruc]],B:B,Data.[[#This Row],[Periodo]])>=25000))),1,0)/COUNTIFS(H:H,Data.[[#This Row],[Ruc]],B:B,Data.[[#This Row],[Periodo]]),0) -> 0.5
A40: =CONCATENATE(Data.[[#This Row],[Código]],Data.[[#This Row],[Ruc]]) -> 595286610477313928 | B40: 46143 | C40: =IFERROR(VLOOKUP(Data.[[#This Row],[Código LT]],Reportería.[],71,0),"") | D40: =IFERROR(VLOOKUP(Data.[[#This Row],[Código]],BV!A:C,2,0),"") | E40: =IFERROR(VLOOKUP(Data.[[#This Row],[Código]],BV!A:C,3,0),"") | F40: 5952866 | G40: 80290935 | H40: 10477313928 | I40: CASTAÑEDA MARAVI PAMELA DEL PILAR | J40: Market San Roque | K40: =IF(Data.[[#This Row],[Tipo de Venta]]<>"POS","Atendido",IF(Data.[[#This Row],[Fecha de Instalación]]<>"","Atendido","Ingresado")) -> Atendido | L40: =Data.[[#This Row],[Estado]] -> Atendido | M40: PARLANTE | N40: =IFERROR(VLOOKUP(Data.[[#This Row],[Código LT]],Reportería.[],20,0),"") | O40: =IFERROR(VLOOKUP(Data.[[#This Row],[Código LT]],Reportería.[],5,0),"") | P40: =Data.[[#This Row],[GPV Mensual LT]]/COUNTIFS(H:H,Data.[[#This Row],[Ruc]],B:B,Data.[[#This Row],[Periodo]]) -> 50000 | Q40: 100000 | R40: Jorge Jaimes | S40: =VLOOKUP(Data.[[#This Row],[Ejecutivo]],Productividad!D:N,11,0) -> 76524006 | T40: =VLOOKUP(Data.[[#This Row],[DNI Ejecutivo]],Productividad!C:U,8,0) -> jjaimesb@lozapay.com.pe | U40: =VLOOKUP(Data.[[#This Row],[DNI Ejecutivo]],Productividad!C:U,4,0) -> Senior | V40: =IFERROR(VLOOKUP(Data.[[#This Row],[DNI Ejecutivo]],Ejecutivos.[],11,0),"") -> Lima Palomino | W40: Carlos Palomino | X40: {=IFERROR(_xlfn.IFS(Data.[[#This Row],[Supervisor]]="Jonathan Lapoint","Norte",Data.[[#This Row],[Supervisor]]="Jorge Fuentes","Norte"),"Lima")} -> Lima | Y40: =VLOOKUP(Data.[[#This Row],[Supervisor]],Ejecutivos!B:S,17,0) -> 41718975 | Z40: =VLOOKUP(Data.[[#This Row],[DNI Supervisor]],Productividad!C:U,8,0) -> carlos.palomino@lozapay.com.pe | AB40: JORGE LUIS JAIMES BARROSO | AC40: =IFERROR(CONCATENATE(Data.[[#This Row],[DNI Ejecutivo]],Data.[[#This Row],[Periodo]]),"") -> 7652400646143 | AD40: =IFERROR(VLOOKUP(Data.[[#This Row],[Código LT]],Reportería.[],10,0),"") | AE40: =IFERROR(VLOOKUP(Data.[[#This Row],[Código LT]],Reportería.[],11,0),"") | AF40: 9 | AI40: =IF(TEXT(Data.[[#This Row],[Periodo]],"mmm-yy")="may-26",VLOOKUP(Data.[[#This Row],[Código]],Reportería!A:BV,57,0),0) -> 10766.67 | AL40: =IF(Data.[[#This Row],[Vol M0]]="",0,0) -> 0 | AM40: =IF(Data.[[#This Row],[Vol M0]]="",0,0) -> 0 | AN40: =IF(Data.[[#This Row],[Vol M0]]="",0,0) -> 0 | AO40: =IF(Data.[[#This Row],[Vol M0]]="",0,0) -> 0 | AP40: =IF(Data.[[#This Row],[Vol M0]]="",0,0) -> 0 | AQ40: =IF(Data.[[#This Row],[Vol M0]]="",0,0) -> 0 | AR40: =IFERROR(IF(OR(AND(OR(Data.[[#This Row],[Categoría]]="Hunter",Data.[[#This Row],[Categoría]]="Senior"),OR(SUMIFS(AF:AF,H:H,Data.[[#This Row],[Ruc]],B:B,Data.[[#This Row],[Periodo]])>=15000,SUMIFS(AI:AI,H:H,Data.[[#This Row],[Ruc]],B:B,Data.[[#This Row],[Periodo]])>=15000,SUMIFS(AL:AL,H:H,Data.[[#This Row],[Ruc]],B:B,Data.[[#This Row],[Periodo]])>=15000,SUMIFS(AO:AO,H:H,Data.[[#This Row],[Ruc]],B:B,Data.[[#This Row],[Periodo]])>=15000)),AND(Data.[[#This Row],[Categoría]]="Elite",OR(SUMIFS(AF:AF,H:H,Data.[[#This Row],[Ruc]],B:B,Data.[[#This Row],[Periodo]])>=25000,SUMIFS(AI:AI,H:H,Data.[[#This Row],[Ruc]],B:B,Data.[[#This Row],[Periodo]])>=25000,SUMIFS(AL:AL,H:H,Data.[[#This Row],[Ruc]],B:B,Data.[[#This Row],[Periodo]])>=25000,SUMIFS(AO:AO,H:H,Data.[[#This Row],[Ruc]],B:B,Data.[[#This Row],[Periodo]])>=25000))),1,0)/COUNTIFS(H:H,Data.[[#This Row],[Ruc]],B:B,Data.[[#This Row],[Periodo]]),0) -> 0.5
A41: =CONCATENATE(Data.[[#This Row],[Código]],Data.[[#This Row],[Ruc]]) -> 595311120614355221 | B41: 46143 | C41: =IFERROR(VLOOKUP(Data.[[#This Row],[Código LT]],Reportería.[],71,0),"") | D41: =IFERROR(VLOOKUP(Data.[[#This Row],[Código]],BV!A:C,2,0),"") -> 46171 | E41: =IFERROR(VLOOKUP(Data.[[#This Row],[Código]],BV!A:C,3,0),"") -> 46171 | F41: 5953111 | G41: TJ33261C21213 | H41: 20614355221 | I41: RED GASTRONOMICA S.A.C. | J41: RED GASTRONOMICA SAC | K41: =IF(Data.[[#This Row],[Tipo de Venta]]<>"POS","Atendido",IF(Data.[[#This Row],[Fecha de Instalación]]<>"","Atendido","Ingresado")) -> Atendido | L41: =Data.[[#This Row],[Estado]] -> Atendido | M41: POS | N41: =IFERROR(VLOOKUP(Data.[[#This Row],[Código LT]],Reportería.[],20,0),"") | O41: =IFERROR(VLOOKUP(Data.[[#This Row],[Código LT]],Reportería.[],5,0),"") | P41: =Data.[[#This Row],[GPV Mensual LT]]/COUNTIFS(H:H,Data.[[#This Row],[Ruc]],B:B,Data.[[#This Row],[Periodo]]) -> 36000 | Q41: 180000 | R41: Angelo Zavala | S41: =VLOOKUP(Data.[[#This Row],[Ejecutivo]],Productividad!D:N,11,0) -> 46741483 | T41: =VLOOKUP(Data.[[#This Row],[DNI Ejecutivo]],Productividad!C:U,8,0) -> azavalaa@lozapay.com.pe | U41: =VLOOKUP(Data.[[#This Row],[DNI Ejecutivo]],Productividad!C:U,4,0) -> Hunter | V41: =IFERROR(VLOOKUP(Data.[[#This Row],[DNI Ejecutivo]],Ejecutivos.[],11,0),"") -> Lima Jean | W41: Jean Aguilar | X41: {=IFERROR(_xlfn.IFS(Data.[[#This Row],[Supervisor]]="Jonathan Lapoint","Norte",Data.[[#This Row],[Supervisor]]="Jorge Fuentes","Norte"),"Lima")} -> Lima | Y41: =VLOOKUP(Data.[[#This Row],[Supervisor]],Ejecutivos!B:S,17,0) -> 47688341 | Z41: =VLOOKUP(Data.[[#This Row],[DNI Supervisor]],Productividad!C:U,8,0) -> jaguilar@lozapay.com.pe | AB41: ANGELO JESUS ZAVALA ANICAMA | AC41: =IFERROR(CONCATENATE(Data.[[#This Row],[DNI Ejecutivo]],Data.[[#This Row],[Periodo]]),"") -> 4674148346143 | AD41: =IFERROR(VLOOKUP(Data.[[#This Row],[Código LT]],Reportería.[],10,0),"") | AE41: =IFERROR(VLOOKUP(Data.[[#This Row],[Código LT]],Reportería.[],11,0),"") | AF41: 3719 | AI41: =IF(TEXT(Data.[[#This Row],[Periodo]],"mmm-yy")="may-26",VLOOKUP(Data.[[#This Row],[Código]],Reportería!A:BV,57,0),0) -> 7008.3 | AL41: =IF(Data.[[#This Row],[Vol M0]]="",0,0) -> 0 | AM41: =IF(Data.[[#This Row],[Vol M0]]="",0,0) -> 0 | AN41: =IF(Data.[[#This Row],[Vol M0]]="",0,0) -> 0 | AO41: =IF(Data.[[#This Row],[Vol M0]]="",0,0) -> 0 | AP41: =IF(Data.[[#This Row],[Vol M0]]="",0,0) -> 0 | AQ41: =IF(Data.[[#This Row],[Vol M0]]="",0,0) -> 0 | AR41: =IFERROR(IF(OR(AND(OR(Data.[[#This Row],[Categoría]]="Hunter",Data.[[#This Row],[Categoría]]="Senior"),OR(SUMIFS(AF:AF,H:H,Data.[[#This Row],[Ruc]],B:B,Data.[[#This Row],[Periodo]])>=15000,SUMIFS(AI:AI,H:H,Data.[[#This Row],[Ruc]],B:B,Data.[[#This Row],[Periodo]])>=15000,SUMIFS(AL:AL,H:H,Data.[[#This Row],[Ruc]],B:B,Data.[[#This Row],[Periodo]])>=15000,SUMIFS(AO:AO,H:H,Data.[[#This Row],[Ruc]],B:B,Data.[[#This Row],[Periodo]])>=15000)),AND(Data.[[#This Row],[Categoría]]="Elite",OR(SUMIFS(AF:AF,H:H,Data.[[#This Row],[Ruc]],B:B,Data.[[#This Row],[Periodo]])>=25000,SUMIFS(AI:AI,H:H,Data.[[#This Row],[Ruc]],B:B,Data.[[#This Row],[Periodo]])>=25000,SUMIFS(AL:AL,H:H,Data.[[#This Row],[Ruc]],B:B,Data.[[#This Row],[Periodo]])>=25000,SUMIFS(AO:AO,H:H,Data.[[#This Row],[Ruc]],B:B,Data.[[#This Row],[Periodo]])>=25000))),1,0)/COUNTIFS(H:H,Data.[[#This Row],[Ruc]],B:B,Data.[[#This Row],[Periodo]]),0) -> 0.2
A42: =CONCATENATE(Data.[[#This Row],[Código]],Data.[[#This Row],[Ruc]]) -> 595311420614355221 | B42: 46143 | C42: =IFERROR(VLOOKUP(Data.[[#This Row],[Código LT]],Reportería.[],71,0),"") | D42: =IFERROR(VLOOKUP(Data.[[#This Row],[Código]],BV!A:C,2,0),"") -> 46171 | E42: =IFERROR(VLOOKUP(Data.[[#This Row],[Código]],BV!A:C,3,0),"") -> 46171 | F42: 5953114 | G42: TJ33261C21024 | H42: 20614355221 | I42: RED GASTRONOMICA S.A.C. | J42: RED GASTRONOMICA SAC | K42: =IF(Data.[[#This Row],[Tipo de Venta]]<>"POS","Atendido",IF(Data.[[#This Row],[Fecha de Instalación]]<>"","Atendido","Ingresado")) -> Atendido | L42: =Data.[[#This Row],[Estado]] -> Atendido | M42: POS | N42: =IFERROR(VLOOKUP(Data.[[#This Row],[Código LT]],Reportería.[],20,0),"") | O42: =IFERROR(VLOOKUP(Data.[[#This Row],[Código LT]],Reportería.[],5,0),"") | P42: =Data.[[#This Row],[GPV Mensual LT]]/COUNTIFS(H:H,Data.[[#This Row],[Ruc]],B:B,Data.[[#This Row],[Periodo]]) -> 36000 | Q42: 180000 | R42: Angelo Zavala | S42: =VLOOKUP(Data.[[#This Row],[Ejecutivo]],Productividad!D:N,11,0) -> 46741483 | T42: =VLOOKUP(Data.[[#This Row],[DNI Ejecutivo]],Productividad!C:U,8,0) -> azavalaa@lozapay.com.pe | U42: =VLOOKUP(Data.[[#This Row],[DNI Ejecutivo]],Productividad!C:U,4,0) -> Hunter | V42: =IFERROR(VLOOKUP(Data.[[#This Row],[DNI Ejecutivo]],Ejecutivos.[],11,0),"") -> Lima Jean | W42: Jean Aguilar | X42: {=IFERROR(_xlfn.IFS(Data.[[#This Row],[Supervisor]]="Jonathan Lapoint","Norte",Data.[[#This Row],[Supervisor]]="Jorge Fuentes","Norte"),"Lima")} -> Lima | Y42: =VLOOKUP(Data.[[#This Row],[Supervisor]],Ejecutivos!B:S,17,0) -> 47688341 | Z42: =VLOOKUP(Data.[[#This Row],[DNI Supervisor]],Productividad!C:U,8,0) -> jaguilar@lozapay.com.pe | AB42: ANGELO JESUS ZAVALA ANICAMA | AC42: =IFERROR(CONCATENATE(Data.[[#This Row],[DNI Ejecutivo]],Data.[[#This Row],[Periodo]]),"") -> 4674148346143 | AD42: =IFERROR(VLOOKUP(Data.[[#This Row],[Código LT]],Reportería.[],10,0),"") | AE42: =IFERROR(VLOOKUP(Data.[[#This Row],[Código LT]],Reportería.[],11,0),"") | AF42: 0 | AI42: =IF(TEXT(Data.[[#This Row],[Periodo]],"mmm-yy")="may-26",VLOOKUP(Data.[[#This Row],[Código]],Reportería!A:BV,57,0),0) -> 5501.3 | AL42: =IF(Data.[[#This Row],[Vol M0]]="",0,0) -> 0 | AM42: =IF(Data.[[#This Row],[Vol M0]]="",0,0) -> 0 | AN42: =IF(Data.[[#This Row],[Vol M0]]="",0,0) -> 0 | AO42: =IF(Data.[[#This Row],[Vol M0]]="",0,0) -> 0 | AP42: =IF(Data.[[#This Row],[Vol M0]]="",0,0) -> 0 | AQ42: =IF(Data.[[#This Row],[Vol M0]]="",0,0) -> 0 | AR42: =IFERROR(IF(OR(AND(OR(Data.[[#This Row],[Categoría]]="Hunter",Data.[[#This Row],[Categoría]]="Senior"),OR(SUMIFS(AF:AF,H:H,Data.[[#This Row],[Ruc]],B:B,Data.[[#This Row],[Periodo]])>=15000,SUMIFS(AI:AI,H:H,Data.[[#This Row],[Ruc]],B:B,Data.[[#This Row],[Periodo]])>=15000,SUMIFS(AL:AL,H:H,Data.[[#This Row],[Ruc]],B:B,Data.[[#This Row],[Periodo]])>=15000,SUMIFS(AO:AO,H:H,Data.[[#This Row],[Ruc]],B:B,Data.[[#This Row],[Periodo]])>=15000)),AND(Data.[[#This Row],[Categoría]]="Elite",OR(SUMIFS(AF:AF,H:H,Data.[[#This Row],[Ruc]],B:B,Data.[[#This Row],[Periodo]])>=25000,SUMIFS(AI:AI,H:H,Data.[[#This Row],[Ruc]],B:B,Data.[[#This Row],[Periodo]])>=25000,SUMIFS(AL:AL,H:H,Data.[[#This Row],[Ruc]],B:B,Data.[[#This Row],[Periodo]])>=25000,SUMIFS(AO:AO,H:H,Data.[[#This Row],[Ruc]],B:B,Data.[[#This Row],[Periodo]])>=25000))),1,0)/COUNTIFS(H:H,Data.[[#This Row],[Ruc]],B:B,Data.[[#This Row],[Periodo]]),0) -> 0.2
A43: =CONCATENATE(Data.[[#This Row],[Código]],Data.[[#This Row],[Ruc]]) -> 595312920614355221 | B43: 46143 | C43: =IFERROR(VLOOKUP(Data.[[#This Row],[Código LT]],Reportería.[],71,0),"") | D43: =IFERROR(VLOOKUP(Data.[[#This Row],[Código]],BV!A:C,2,0),"") -> 46171 | E43: =IFERROR(VLOOKUP(Data.[[#This Row],[Código]],BV!A:C,3,0),"") -> 46171 | F43: 5953129 | G43: TJ33261A20875 | H43: 20614355221 | I43: RED GASTRONOMICA S.A.C. | J43: RED GASTRONOMICA SAC | K43: =IF(Data.[[#This Row],[Tipo de Venta]]<>"POS","Atendido",IF(Data.[[#This Row],[Fecha de Instalación]]<>"","Atendido","Ingresado")) -> Atendido | L43: =Data.[[#This Row],[Estado]] -> Atendido | M43: POS | N43: =IFERROR(VLOOKUP(Data.[[#This Row],[Código LT]],Reportería.[],20,0),"") | O43: =IFERROR(VLOOKUP(Data.[[#This Row],[Código LT]],Reportería.[],5,0),"") | P43: =Data.[[#This Row],[GPV Mensual LT]]/COUNTIFS(H:H,Data.[[#This Row],[Ruc]],B:B,Data.[[#This Row],[Periodo]]) -> 36000 | Q43: 180000 | R43: Angelo Zavala | S43: =VLOOKUP(Data.[[#This Row],[Ejecutivo]],Productividad!D:N,11,0) -> 46741483 | T43: =VLOOKUP(Data.[[#This Row],[DNI Ejecutivo]],Productividad!C:U,8,0) -> azavalaa@lozapay.com.pe | U43: =VLOOKUP(Data.[[#This Row],[DNI Ejecutivo]],Productividad!C:U,4,0) -> Hunter | V43: =IFERROR(VLOOKUP(Data.[[#This Row],[DNI Ejecutivo]],Ejecutivos.[],11,0),"") -> Lima Jean | W43: Jean Aguilar | X43: {=IFERROR(_xlfn.IFS(Data.[[#This Row],[Supervisor]]="Jonathan Lapoint","Norte",Data.[[#This Row],[Supervisor]]="Jorge Fuentes","Norte"),"Lima")} -> Lima | Y43: =VLOOKUP(Data.[[#This Row],[Supervisor]],Ejecutivos!B:S,17,0) -> 47688341 | Z43: =VLOOKUP(Data.[[#This Row],[DNI Supervisor]],Productividad!C:U,8,0) -> jaguilar@lozapay.com.pe | AB43: ANGELO JESUS ZAVALA ANICAMA | AC43: =IFERROR(CONCATENATE(Data.[[#This Row],[DNI Ejecutivo]],Data.[[#This Row],[Periodo]]),"") -> 4674148346143 | AD43: =IFERROR(VLOOKUP(Data.[[#This Row],[Código LT]],Reportería.[],10,0),"") | AE43: =IFERROR(VLOOKUP(Data.[[#This Row],[Código LT]],Reportería.[],11,0),"") | AF43: 0 | AI43: =IF(TEXT(Data.[[#This Row],[Periodo]],"mmm-yy")="may-26",VLOOKUP(Data.[[#This Row],[Código]],Reportería!A:BV,57,0),0) -> 0 | AL43: =IF(Data.[[#This Row],[Vol M0]]="",0,0) -> 0 | AM43: =IF(Data.[[#This Row],[Vol M0]]="",0,0) -> 0 | AN43: =IF(Data.[[#This Row],[Vol M0]]="",0,0) -> 0 | AO43: =IF(Data.[[#This Row],[Vol M0]]="",0,0) -> 0 | AP43: =IF(Data.[[#This Row],[Vol M0]]="",0,0) -> 0 | AQ43: =IF(Data.[[#This Row],[Vol M0]]="",0,0) -> 0 | AR43: =IFERROR(IF(OR(AND(OR(Data.[[#This Row],[Categoría]]="Hunter",Data.[[#This Row],[Categoría]]="Senior"),OR(SUMIFS(AF:AF,H:H,Data.[[#This Row],[Ruc]],B:B,Data.[[#This Row],[Periodo]])>=15000,SUMIFS(AI:AI,H:H,Data.[[#This Row],[Ruc]],B:B,Data.[[#This Row],[Periodo]])>=15000,SUMIFS(AL:AL,H:H,Data.[[#This Row],[Ruc]],B:B,Data.[[#This Row],[Periodo]])>=15000,SUMIFS(AO:AO,H:H,Data.[[#This Row],[Ruc]],B:B,Data.[[#This Row],[Periodo]])>=15000)),AND(Data.[[#This Row],[Categoría]]="Elite",OR(SUMIFS(AF:AF,H:H,Data.[[#This Row],[Ruc]],B:B,Data.[[#This Row],[Periodo]])>=25000,SUMIFS(AI:AI,H:H,Data.[[#This Row],[Ruc]],B:B,Data.[[#This Row],[Periodo]])>=25000,SUMIFS(AL:AL,H:H,Data.[[#This Row],[Ruc]],B:B,Data.[[#This Row],[Periodo]])>=25000,SUMIFS(AO:AO,H:H,Data.[[#This Row],[Ruc]],B:B,Data.[[#This Row],[Periodo]])>=25000))),1,0)/COUNTIFS(H:H,Data.[[#This Row],[Ruc]],B:B,Data.[[#This Row],[Periodo]]),0) -> 0.2
A44: =CONCATENATE(Data.[[#This Row],[Código]],Data.[[#This Row],[Ruc]]) -> 595314220614355221 | B44: 46143 | C44: =IFERROR(VLOOKUP(Data.[[#This Row],[Código LT]],Reportería.[],71,0),"") | D44: =IFERROR(VLOOKUP(Data.[[#This Row],[Código]],BV!A:C,2,0),"") -> 46171 | E44: =IFERROR(VLOOKUP(Data.[[#This Row],[Código]],BV!A:C,3,0),"") -> 46171 | F44: 5953142 | G44: TJ33261C20341 | H44: 20614355221 | I44: RED GASTRONOMICA S.A.C. | J44: RED GASTRONOMICA SAC | K44: =IF(Data.[[#This Row],[Tipo de Venta]]<>"POS","Atendido",IF(Data.[[#This Row],[Fecha de Instalación]]<>"","Atendido","Ingresado")) -> Atendido | L44: =Data.[[#This Row],[Estado]] -> Atendido | M44: POS | N44: =IFERROR(VLOOKUP(Data.[[#This Row],[Código LT]],Reportería.[],20,0),"") | O44: =IFERROR(VLOOKUP(Data.[[#This Row],[Código LT]],Reportería.[],5,0),"") | P44: =Data.[[#This Row],[GPV Mensual LT]]/COUNTIFS(H:H,Data.[[#This Row],[Ruc]],B:B,Data.[[#This Row],[Periodo]]) -> 36000 | Q44: 180000 | R44: Angelo Zavala | S44: =VLOOKUP(Data.[[#This Row],[Ejecutivo]],Productividad!D:N,11,0) -> 46741483 | T44: =VLOOKUP(Data.[[#This Row],[DNI Ejecutivo]],Productividad!C:U,8,0) -> azavalaa@lozapay.com.pe | U44: =VLOOKUP(Data.[[#This Row],[DNI Ejecutivo]],Productividad!C:U,4,0) -> Hunter | V44: =IFERROR(VLOOKUP(Data.[[#This Row],[DNI Ejecutivo]],Ejecutivos.[],11,0),"") -> Lima Jean | W44: Jean Aguilar | X44: {=IFERROR(_xlfn.IFS(Data.[[#This Row],[Supervisor]]="Jonathan Lapoint","Norte",Data.[[#This Row],[Supervisor]]="Jorge Fuentes","Norte"),"Lima")} -> Lima | Y44: =VLOOKUP(Data.[[#This Row],[Supervisor]],Ejecutivos!B:S,17,0) -> 47688341 | Z44: =VLOOKUP(Data.[[#This Row],[DNI Supervisor]],Productividad!C:U,8,0) -> jaguilar@lozapay.com.pe | AB44: ANGELO JESUS ZAVALA ANICAMA | AC44: =IFERROR(CONCATENATE(Data.[[#This Row],[DNI Ejecutivo]],Data.[[#This Row],[Periodo]]),"") -> 4674148346143 | AD44: =IFERROR(VLOOKUP(Data.[[#This Row],[Código LT]],Reportería.[],10,0),"") | AE44: =IFERROR(VLOOKUP(Data.[[#This Row],[Código LT]],Reportería.[],11,0),"") | AF44: 1 | AI44: =IF(TEXT(Data.[[#This Row],[Periodo]],"mmm-yy")="may-26",VLOOKUP(Data.[[#This Row],[Código]],Reportería!A:BV,57,0),0) -> 3603.65 | AL44: =IF(Data.[[#This Row],[Vol M0]]="",0,0) -> 0 | AM44: =IF(Data.[[#This Row],[Vol M0]]="",0,0) -> 0 | AN44: =IF(Data.[[#This Row],[Vol M0]]="",0,0) -> 0 | AO44: =IF(Data.[[#This Row],[Vol M0]]="",0,0) -> 0 | AP44: =IF(Data.[[#This Row],[Vol M0]]="",0,0) -> 0 | AQ44: =IF(Data.[[#This Row],[Vol M0]]="",0,0) -> 0 | AR44: =IFERROR(IF(OR(AND(OR(Data.[[#This Row],[Categoría]]="Hunter",Data.[[#This Row],[Categoría]]="Senior"),OR(SUMIFS(AF:AF,H:H,Data.[[#This Row],[Ruc]],B:B,Data.[[#This Row],[Periodo]])>=15000,SUMIFS(AI:AI,H:H,Data.[[#This Row],[Ruc]],B:B,Data.[[#This Row],[Periodo]])>=15000,SUMIFS(AL:AL,H:H,Data.[[#This Row],[Ruc]],B:B,Data.[[#This Row],[Periodo]])>=15000,SUMIFS(AO:AO,H:H,Data.[[#This Row],[Ruc]],B:B,Data.[[#This Row],[Periodo]])>=15000)),AND(Data.[[#This Row],[Categoría]]="Elite",OR(SUMIFS(AF:AF,H:H,Data.[[#This Row],[Ruc]],B:B,Data.[[#This Row],[Periodo]])>=25000,SUMIFS(AI:AI,H:H,Data.[[#This Row],[Ruc]],B:B,Data.[[#This Row],[Periodo]])>=25000,SUMIFS(AL:AL,H:H,Data.[[#This Row],[Ruc]],B:B,Data.[[#This Row],[Periodo]])>=25000,SUMIFS(AO:AO,H:H,Data.[[#This Row],[Ruc]],B:B,Data.[[#This Row],[Periodo]])>=25000))),1,0)/COUNTIFS(H:H,Data.[[#This Row],[Ruc]],B:B,Data.[[#This Row],[Periodo]]),0) -> 0.2
A45: =CONCATENATE(Data.[[#This Row],[Código]],Data.[[#This Row],[Ruc]]) -> 595315520614355221 | B45: 46143 | C45: =IFERROR(VLOOKUP(Data.[[#This Row],[Código LT]],Reportería.[],71,0),"") | D45: =IFERROR(VLOOKUP(Data.[[#This Row],[Código]],BV!A:C,2,0),"") -> 46171 | E45: =IFERROR(VLOOKUP(Data.[[#This Row],[Código]],BV!A:C,3,0),"") -> 46171 | F45: 5953155 | G45: TJ33261C21689 | H45: 20614355221 | I45: RED GASTRONOMICA S.A.C. | J45: RED GASTRONOMICA SAC | K45: =IF(Data.[[#This Row],[Tipo de Venta]]<>"POS","Atendido",IF(Data.[[#This Row],[Fecha de Instalación]]<>"","Atendido","Ingresado")) -> Atendido | L45: =Data.[[#This Row],[Estado]] -> Atendido | M45: POS | N45: =IFERROR(VLOOKUP(Data.[[#This Row],[Código LT]],Reportería.[],20,0),"") | O45: =IFERROR(VLOOKUP(Data.[[#This Row],[Código LT]],Reportería.[],5,0),"") | P45: =Data.[[#This Row],[GPV Mensual LT]]/COUNTIFS(H:H,Data.[[#This Row],[Ruc]],B:B,Data.[[#This Row],[Periodo]]) -> 36000 | Q45: 180000 | R45: Angelo Zavala | S45: =VLOOKUP(Data.[[#This Row],[Ejecutivo]],Productividad!D:N,11,0) -> 46741483 | T45: =VLOOKUP(Data.[[#This Row],[DNI Ejecutivo]],Productividad!C:U,8,0) -> azavalaa@lozapay.com.pe | U45: =VLOOKUP(Data.[[#This Row],[DNI Ejecutivo]],Productividad!C:U,4,0) -> Hunter | V45: =IFERROR(VLOOKUP(Data.[[#This Row],[DNI Ejecutivo]],Ejecutivos.[],11,0),"") -> Lima Jean | W45: Jean Aguilar | X45: {=IFERROR(_xlfn.IFS(Data.[[#This Row],[Supervisor]]="Jonathan Lapoint","Norte",Data.[[#This Row],[Supervisor]]="Jorge Fuentes","Norte"),"Lima")} -> Lima | Y45: =VLOOKUP(Data.[[#This Row],[Supervisor]],Ejecutivos!B:S,17,0) -> 47688341 | Z45: =VLOOKUP(Data.[[#This Row],[DNI Supervisor]],Productividad!C:U,8,0) -> jaguilar@lozapay.com.pe | AB45: ANGELO JESUS ZAVALA ANICAMA | AC45: =IFERROR(CONCATENATE(Data.[[#This Row],[DNI Ejecutivo]],Data.[[#This Row],[Periodo]]),"") -> 4674148346143 | AD45: =IFERROR(VLOOKUP(Data.[[#This Row],[Código LT]],Reportería.[],10,0),"") | AE45: =IFERROR(VLOOKUP(Data.[[#This Row],[Código LT]],Reportería.[],11,0),"") | AF45: 0 | AI45: =IF(TEXT(Data.[[#This Row],[Periodo]],"mmm-yy")="may-26",VLOOKUP(Data.[[#This Row],[Código]],Reportería!A:BV,57,0),0) -> 2989.5 | AL45: =IF(Data.[[#This Row],[Vol M0]]="",0,0) -> 0 | AM45: =IF(Data.[[#This Row],[Vol M0]]="",0,0) -> 0 | AN45: =IF(Data.[[#This Row],[Vol M0]]="",0,0) -> 0 | AO45: =IF(Data.[[#This Row],[Vol M0]]="",0,0) -> 0 | AP45: =IF(Data.[[#This Row],[Vol M0]]="",0,0) -> 0 | AQ45: =IF(Data.[[#This Row],[Vol M0]]="",0,0) -> 0 | AR45: =IFERROR(IF(OR(AND(OR(Data.[[#This Row],[Categoría]]="Hunter",Data.[[#This Row],[Categoría]]="Senior"),OR(SUMIFS(AF:AF,H:H,Data.[[#This Row],[Ruc]],B:B,Data.[[#This Row],[Periodo]])>=15000,SUMIFS(AI:AI,H:H,Data.[[#This Row],[Ruc]],B:B,Data.[[#This Row],[Periodo]])>=15000,SUMIFS(AL:AL,H:H,Data.[[#This Row],[Ruc]],B:B,Data.[[#This Row],[Periodo]])>=15000,SUMIFS(AO:AO,H:H,Data.[[#This Row],[Ruc]],B:B,Data.[[#This Row],[Periodo]])>=15000)),AND(Data.[[#This Row],[Categoría]]="Elite",OR(SUMIFS(AF:AF,H:H,Data.[[#This Row],[Ruc]],B:B,Data.[[#This Row],[Periodo]])>=25000,SUMIFS(AI:AI,H:H,Data.[[#This Row],[Ruc]],B:B,Data.[[#This Row],[Periodo]])>=25000,SUMIFS(AL:AL,H:H,Data.[[#This Row],[Ruc]],B:B,Data.[[#This Row],[Periodo]])>=25000,SUMIFS(AO:AO,H:H,Data.[[#This Row],[Ruc]],B:B,Data.[[#This Row],[Periodo]])>=25000))),1,0)/COUNTIFS(H:H,Data.[[#This Row],[Ruc]],B:B,Data.[[#This Row],[Periodo]]),0) -> 0.2
A46: =CONCATENATE(Data.[[#This Row],[Código]],Data.[[#This Row],[Ruc]]) -> 503595620509678244 | B46: 46174 | C46: =IFERROR(VLOOKUP(Data.[[#This Row],[Código LT]],Reportería.[],71,0),"") | D46: =IFERROR(VLOOKUP(Data.[[#This Row],[Código]],BV!A:C,2,0),"") -> 46171 | E46: =IFERROR(VLOOKUP(Data.[[#This Row],[Código]],BV!A:C,3,0),"") -> 46174 | F46: 5035956 | G46: 22ANKD8E0779 | H46: 20509678244 | I46: MAJOCA SOCIEDAD ANONIMA CERRADA | J46: USHIA | K46: =IF(Data.[[#This Row],[Tipo de Venta]]<>"POS","Atendido",IF(Data.[[#This Row],[Fecha de Instalación]]<>"","Atendido","Ingresado")) -> Atendido | L46: =Data.[[#This Row],[Estado]] -> Atendido | M46: POS | N46: =IFERROR(VLOOKUP(Data.[[#This Row],[Código LT]],Reportería.[],20,0),"") | O46: =IFERROR(VLOOKUP(Data.[[#This Row],[Código LT]],Reportería.[],5,0),"") | P46: =Data.[[#This Row],[GPV Mensual LT]]/COUNTIFS(H:H,Data.[[#This Row],[Ruc]],B:B,Data.[[#This Row],[Periodo]]) -> 50000 | Q46: 50000 | R46: Jose Mujica | S46: =VLOOKUP(Data.[[#This Row],[Ejecutivo]],Productividad!D:N,11,0) -> 002409208 | T46: =VLOOKUP(Data.[[#This Row],[DNI Ejecutivo]],Productividad!C:U,8,0) -> jose.mujica@lozapay.com.pe | U46: =VLOOKUP(Data.[[#This Row],[DNI Ejecutivo]],Productividad!C:U,4,0) -> Senior | V46: =IFERROR(VLOOKUP(Data.[[#This Row],[DNI Ejecutivo]],Ejecutivos.[],11,0),"") -> Norte Fuentes | W46: Jorge Fuentes | X46: {=IFERROR(_xlfn.IFS(Data.[[#This Row],[Supervisor]]="Jonathan Lapoint","Norte",Data.[[#This Row],[Supervisor]]="Jorge Fuentes","Norte"),"Lima")} -> Norte | Y46: =VLOOKUP(Data.[[#This Row],[Supervisor]],Ejecutivos!B:S,17,0) -> 70059865 | Z46: =VLOOKUP(Data.[[#This Row],[DNI Supervisor]],Productividad!C:U,8,0) -> jfuentes@lozapay.com.pe | AB46: JOSE GREGORIO MUJICA RUIZ | AC46: =IFERROR(CONCATENATE(Data.[[#This Row],[DNI Ejecutivo]],Data.[[#This Row],[Periodo]]),"") -> 00240920846174 | AD46: =IFERROR(VLOOKUP(Data.[[#This Row],[Código LT]],Reportería.[],10,0),"") | AE46: =IFERROR(VLOOKUP(Data.[[#This Row],[Código LT]],Reportería.[],11,0),"") | AF46: 37430 | AI46: =IF(TEXT(Data.[[#This Row],[Periodo]],"mmm-yy")="may-26",VLOOKUP(Data.[[#This Row],[Código]],Reportería!A:BV,57,0),0) -> 0 | AL46: =IF(Data.[[#This Row],[Vol M0]]="",0,0) -> 0 | AM46: =IF(Data.[[#This Row],[Vol M0]]="",0,0) -> 0 | AN46: =IF(Data.[[#This Row],[Vol M0]]="",0,0) -> 0 | AO46: =IF(Data.[[#This Row],[Vol M0]]="",0,0) -> 0 | AP46: =IF(Data.[[#This Row],[Vol M0]]="",0,0) -> 0 | AQ46: =IF(Data.[[#This Row],[Vol M0]]="",0,0) -> 0 | AR46: =IFERROR(IF(OR(AND(OR(Data.[[#This Row],[Categoría]]="Hunter",Data.[[#This Row],[Categoría]]="Senior"),OR(SUMIFS(AF:AF,H:H,Data.[[#This Row],[Ruc]],B:B,Data.[[#This Row],[Periodo]])>=15000,SUMIFS(AI:AI,H:H,Data.[[#This Row],[Ruc]],B:B,Data.[[#This Row],[Periodo]])>=15000,SUMIFS(AL:AL,H:H,Data.[[#This Row],[Ruc]],B:B,Data.[[#This Row],[Periodo]])>=15000,SUMIFS(AO:AO,H:H,Data.[[#This Row],[Ruc]],B:B,Data.[[#This Row],[Periodo]])>=15000)),AND(Data.[[#This Row],[Categoría]]="Elite",OR(SUMIFS(AF:AF,H:H,Data.[[#This Row],[Ruc]],B:B,Data.[[#This Row],[Periodo]])>=25000,SUMIFS(AI:AI,H:H,Data.[[#This Row],[Ruc]],B:B,Data.[[#This Row],[Periodo]])>=25000,SUMIFS(AL:AL,H:H,Data.[[#This Row],[Ruc]],B:B,Data.[[#This Row],[Periodo]])>=25000,SUMIFS(AO:AO,H:H,Data.[[#This Row],[Ruc]],B:B,Data.[[#This Row],[Periodo]])>=25000))),1,0)/COUNTIFS(H:H,Data.[[#This Row],[Ruc]],B:B,Data.[[#This Row],[Periodo]]),0) -> 1
A47: =CONCATENATE(Data.[[#This Row],[Código]],Data.[[#This Row],[Ruc]]) -> 105882620609012197 | B47: 46174 | C47: =IFERROR(VLOOKUP(Data.[[#This Row],[Código LT]],Reportería.[],71,0),"") | D47: =IFERROR(VLOOKUP(Data.[[#This Row],[Código]],BV!A:C,2,0),"") -> 46174 | E47: =IFERROR(VLOOKUP(Data.[[#This Row],[Código]],BV!A:C,3,0),"") -> 0 | F47: 1058826 | H47: 20609012197 | I47: ASTURIAS BUSINESS S.A.C. | J47: ASTURIAS BUSINESS S.A.C. | K47: =IF(Data.[[#This Row],[Tipo de Venta]]<>"POS","Atendido",IF(Data.[[#This Row],[Fecha de Instalación]]<>"","Atendido","Ingresado")) -> Atendido | L47: =Data.[[#This Row],[Estado]] -> Atendido | M47: POS | N47: =IFERROR(VLOOKUP(Data.[[#This Row],[Código LT]],Reportería.[],20,0),"") | O47: =IFERROR(VLOOKUP(Data.[[#This Row],[Código LT]],Reportería.[],5,0),"") | P47: =Data.[[#This Row],[GPV Mensual LT]]/COUNTIFS(H:H,Data.[[#This Row],[Ruc]],B:B,Data.[[#This Row],[Periodo]]) -> 250000 | Q47: 250000 | R47: Maria Godoy | S47: =VLOOKUP(Data.[[#This Row],[Ejecutivo]],Productividad!D:N,11,0) -> 46998250 | T47: =VLOOKUP(Data.[[#This Row],[DNI Ejecutivo]],Productividad!C:U,8,0) -> mgodoyc@lozapay.com.pe | U47: =VLOOKUP(Data.[[#This Row],[DNI Ejecutivo]],Productividad!C:U,4,0) -> Elite | V47: =IFERROR(VLOOKUP(Data.[[#This Row],[DNI Ejecutivo]],Ejecutivos.[],11,0),"") -> Lima Palomino | W47: Carlos Palomino | X47: {=IFERROR(_xlfn.IFS(Data.[[#This Row],[Supervisor]]="Jonathan Lapoint","Norte",Data.[[#This Row],[Supervisor]]="Jorge Fuentes","Norte"),"Lima")} -> Lima | Y47: =VLOOKUP(Data.[[#This Row],[Supervisor]],Ejecutivos!B:S,17,0) -> 41718975 | Z47: =VLOOKUP(Data.[[#This Row],[DNI Supervisor]],Productividad!C:U,8,0) -> carlos.palomino@lozapay.com.pe | AB47: MARIA JOHANA GODOY CRUZ | AC47: =IFERROR(CONCATENATE(Data.[[#This Row],[DNI Ejecutivo]],Data.[[#This Row],[Periodo]]),"") -> 4699825046174 | AD47: =IFERROR(VLOOKUP(Data.[[#This Row],[Código LT]],Reportería.[],10,0),"") | AE47: =IFERROR(VLOOKUP(Data.[[#This Row],[Código LT]],Reportería.[],11,0),"") | AF47: =IFERROR(VLOOKUP(Data.[[#This Row],[Código]],Reportería!A:BV,57,0),0) -> 126304 | AI47: =IF(TEXT(Data.[[#This Row],[Periodo]],"mmm-yy")="may-26",VLOOKUP(Data.[[#This Row],[Código]],Reportería!A:BV,57,0),0) -> 0 | AL47: =IF(Data.[[#This Row],[Vol M0]]="",0,0) -> 0 | AM47: =IF(Data.[[#This Row],[Vol M0]]="",0,0) -> 0 | AN47: =IF(Data.[[#This Row],[Vol M0]]="",0,0) -> 0 | AO47: =IF(Data.[[#This Row],[Vol M0]]="",0,0) -> 0 | AP47: =IF(Data.[[#This Row],[Vol M0]]="",0,0) -> 0 | AQ47: =IF(Data.[[#This Row],[Vol M0]]="",0,0) -> 0 | AR47: =IFERROR(IF(OR(AND(OR(Data.[[#This Row],[Categoría]]="Hunter",Data.[[#This Row],[Categoría]]="Senior"),OR(SUMIFS(AF:AF,H:H,Data.[[#This Row],[Ruc]],B:B,Data.[[#This Row],[Periodo]])>=15000,SUMIFS(AI:AI,H:H,Data.[[#This Row],[Ruc]],B:B,Data.[[#This Row],[Periodo]])>=15000,SUMIFS(AL:AL,H:H,Data.[[#This Row],[Ruc]],B:B,Data.[[#This Row],[Periodo]])>=15000,SUMIFS(AO:AO,H:H,Data.[[#This Row],[Ruc]],B:B,Data.[[#This Row],[Periodo]])>=15000)),AND(Data.[[#This Row],[Categoría]]="Elite",OR(SUMIFS(AF:AF,H:H,Data.[[#This Row],[Ruc]],B:B,Data.[[#This Row],[Periodo]])>=25000,SUMIFS(AI:AI,H:H,Data.[[#This Row],[Ruc]],B:B,Data.[[#This Row],[Periodo]])>=25000,SUMIFS(AL:AL,H:H,Data.[[#This Row],[Ruc]],B:B,Data.[[#This Row],[Periodo]])>=25000,SUMIFS(AO:AO,H:H,Data.[[#This Row],[Ruc]],B:B,Data.[[#This Row],[Periodo]])>=25000))),1,0)/COUNTIFS(H:H,Data.[[#This Row],[Ruc]],B:B,Data.[[#This Row],[Periodo]]),0) -> 1
A48: =CONCATENATE(Data.[[#This Row],[Código]],Data.[[#This Row],[Ruc]]) -> 595442610402573452 | B48: 46174 | C48: =IFERROR(VLOOKUP(Data.[[#This Row],[Código LT]],Reportería.[],71,0),"") | D48: =IFERROR(VLOOKUP(Data.[[#This Row],[Código]],BV!A:C,2,0),"") -> 46174 | E48: =IFERROR(VLOOKUP(Data.[[#This Row],[Código]],BV!A:C,3,0),"") -> 46175 | F48: 5954426 | G48: TJ33261C20681 | H48: 10402573452 | I48: BENAVENTE MURILLO MERCEDES PAOLA | J48: Clínica Dra. Mercedes Benavente Murillo | K48: =IF(Data.[[#This Row],[Tipo de Venta]]<>"POS","Atendido",IF(Data.[[#This Row],[Fecha de Instalación]]<>"","Atendido","Ingresado")) -> Atendido | L48: =Data.[[#This Row],[Estado]] -> Atendido | M48: POS | N48: =IFERROR(VLOOKUP(Data.[[#This Row],[Código LT]],Reportería.[],20,0),"") | O48: =IFERROR(VLOOKUP(Data.[[#This Row],[Código LT]],Reportería.[],5,0),"") | P48: =Data.[[#This Row],[GPV Mensual LT]]/COUNTIFS(H:H,Data.[[#This Row],[Ruc]],B:B,Data.[[#This Row],[Periodo]]) -> 25000 | Q48: 25000 | R48: Nestor Jarama | S48: =VLOOKUP(Data.[[#This Row],[Ejecutivo]],Productividad!D:N,11,0) -> 40610358 | T48: =VLOOKUP(Data.[[#This Row],[DNI Ejecutivo]],Productividad!C:U,8,0) -> najaramar@lozapay.com.pe | U48: =VLOOKUP(Data.[[#This Row],[DNI Ejecutivo]],Productividad!C:U,4,0) -> Hunter | V48: =IFERROR(VLOOKUP(Data.[[#This Row],[DNI Ejecutivo]],Ejecutivos.[],11,0),"") -> Lima Hamm | W48: Hamm Ramirez | X48: {=IFERROR(_xlfn.IFS(Data.[[#This Row],[Supervisor]]="Jonathan Lapoint","Norte",Data.[[#This Row],[Supervisor]]="Jorge Fuentes","Norte"),"Lima")} -> Lima | Y48: =VLOOKUP(Data.[[#This Row],[Supervisor]],Ejecutivos!B:S,17,0) -> 44818200 | Z48: =VLOOKUP(Data.[[#This Row],[DNI Supervisor]],Productividad!C:U,8,0) -> hramirezp@lozapay.com.pe | AB48: NESTOR RAUL JARAMA REATEGUI | AC48: =IFERROR(CONCATENATE(Data.[[#This Row],[DNI Ejecutivo]],Data.[[#This Row],[Periodo]]),"") -> 4061035846174 | AD48: =IFERROR(VLOOKUP(Data.[[#This Row],[Código LT]],Reportería.[],10,0),"") | AE48: =IFERROR(VLOOKUP(Data.[[#This Row],[Código LT]],Reportería.[],11,0),"") | AF48: =IFERROR(VLOOKUP(Data.[[#This Row],[Código]],Reportería!A:BV,57,0),0) -> 0 | AI48: =IF(TEXT(Data.[[#This Row],[Periodo]],"mmm-yy")="may-26",VLOOKUP(Data.[[#This Row],[Código]],Reportería!A:BV,57,0),0) -> 0 | AL48: =IF(Data.[[#This Row],[Vol M0]]="",0,0) -> 0 | AM48: =IF(Data.[[#This Row],[Vol M0]]="",0,0) -> 0 | AN48: =IF(Data.[[#This Row],[Vol M0]]="",0,0) -> 0 | AO48: =IF(Data.[[#This Row],[Vol M0]]="",0,0) -> 0 | AP48: =IF(Data.[[#This Row],[Vol M0]]="",0,0) -> 0 | AQ48: =IF(Data.[[#This Row],[Vol M0]]="",0,0) -> 0 | AR48: =IFERROR(IF(OR(AND(OR(Data.[[#This Row],[Categoría]]="Hunter",Data.[[#This Row],[Categoría]]="Senior"),OR(SUMIFS(AF:AF,H:H,Data.[[#This Row],[Ruc]],B:B,Data.[[#This Row],[Periodo]])>=15000,SUMIFS(AI:AI,H:H,Data.[[#This Row],[Ruc]],B:B,Data.[[#This Row],[Periodo]])>=15000,SUMIFS(AL:AL,H:H,Data.[[#This Row],[Ruc]],B:B,Data.[[#This Row],[Periodo]])>=15000,SUMIFS(AO:AO,H:H,Data.[[#This Row],[Ruc]],B:B,Data.[[#This Row],[Periodo]])>=15000)),AND(Data.[[#This Row],[Categoría]]="Elite",OR(SUMIFS(AF:AF,H:H,Data.[[#This Row],[Ruc]],B:B,Data.[[#This Row],[Periodo]])>=25000,SUMIFS(AI:AI,H:H,Data.[[#This Row],[Ruc]],B:B,Data.[[#This Row],[Periodo]])>=25000,SUMIFS(AL:AL,H:H,Data.[[#This Row],[Ruc]],B:B,Data.[[#This Row],[Periodo]])>=25000,SUMIFS(AO:AO,H:H,Data.[[#This Row],[Ruc]],B:B,Data.[[#This Row],[Periodo]])>=25000))),1,0)/COUNTIFS(H:H,Data.[[#This Row],[Ruc]],B:B,Data.[[#This Row],[Periodo]]),0) -> 0
A49: =CONCATENATE(Data.[[#This Row],[Código]],Data.[[#This Row],[Ruc]]) -> 595468020615781003 | B49: 46174 | C49: =IFERROR(VLOOKUP(Data.[[#This Row],[Código LT]],Reportería.[],71,0),"") | D49: =IFERROR(VLOOKUP(Data.[[#This Row],[Código]],BV!A:C,2,0),"") -> 46175 | E49: =IFERROR(VLOOKUP(Data.[[#This Row],[Código]],BV!A:C,3,0),"") -> 46175 | F49: 5954680 | G49: TJ33261M20020 | H49: 20615781003 | I49: NEGOCIOS E INVERSIONES MCQH SOCIEDAD ANONIMA CERRADA | J49: MAS CARNE QUE HUESO | K49: =IF(Data.[[#This Row],[Tipo de Venta]]<>"POS","Atendido",IF(Data.[[#This Row],[Fecha de Instalación]]<>"","Atendido","Ingresado")) -> Atendido | L49: =Data.[[#This Row],[Estado]] -> Atendido | M49: POS | N49: =IFERROR(VLOOKUP(Data.[[#This Row],[Código LT]],Reportería.[],20,0),"") | O49: =IFERROR(VLOOKUP(Data.[[#This Row],[Código LT]],Reportería.[],5,0),"") | P49: =Data.[[#This Row],[GPV Mensual LT]]/COUNTIFS(H:H,Data.[[#This Row],[Ruc]],B:B,Data.[[#This Row],[Periodo]]) -> 20000 | Q49: 40000 | R49: Angelo Zavala | S49: =VLOOKUP(Data.[[#This Row],[Ejecutivo]],Productividad!D:N,11,0) -> 46741483 | T49: =VLOOKUP(Data.[[#This Row],[DNI Ejecutivo]],Productividad!C:U,8,0) -> azavalaa@lozapay.com.pe | U49: =VLOOKUP(Data.[[#This Row],[DNI Ejecutivo]],Productividad!C:U,4,0) -> Hunter | V49: =IFERROR(VLOOKUP(Data.[[#This Row],[DNI Ejecutivo]],Ejecutivos.[],11,0),"") -> Lima Jean | W49: Jean Aguilar | X49: {=IFERROR(_xlfn.IFS(Data.[[#This Row],[Supervisor]]="Jonathan Lapoint","Norte",Data.[[#This Row],[Supervisor]]="Jorge Fuentes","Norte"),"Lima")} -> Lima | Y49: =VLOOKUP(Data.[[#This Row],[Supervisor]],Ejecutivos!B:S,17,0) -> 47688341 | Z49: =VLOOKUP(Data.[[#This Row],[DNI Supervisor]],Productividad!C:U,8,0) -> jaguilar@lozapay.com.pe | AB49: ANGELO JESUS ZAVALA ANICAMA | AC49: =IFERROR(CONCATENATE(Data.[[#This Row],[DNI Ejecutivo]],Data.[[#This Row],[Periodo]]),"") -> 4674148346174 | AD49: =IFERROR(VLOOKUP(Data.[[#This Row],[Código LT]],Reportería.[],10,0),"") | AE49: =IFERROR(VLOOKUP(Data.[[#This Row],[Código LT]],Reportería.[],11,0),"") | AF49: =IFERROR(VLOOKUP(Data.[[#This Row],[Código]],Reportería!A:BV,57,0),0) -> 13158.7 | AI49: =IF(TEXT(Data.[[#This Row],[Periodo]],"mmm-yy")="may-26",VLOOKUP(Data.[[#This Row],[Código]],Reportería!A:BV,57,0),0) -> 0 | AL49: =IF(Data.[[#This Row],[Vol M0]]="",0,0) -> 0 | AM49: =IF(Data.[[#This Row],[Vol M0]]="",0,0) -> 0 | AN49: =IF(Data.[[#This Row],[Vol M0]]="",0,0) -> 0 | AO49: =IF(Data.[[#This Row],[Vol M0]]="",0,0) -> 0 | AP49: =IF(Data.[[#This Row],[Vol M0]]="",0,0) -> 0 | AQ49: =IF(Data.[[#This Row],[Vol M0]]="",0,0) -> 0 | AR49: =IFERROR(IF(OR(AND(OR(Data.[[#This Row],[Categoría]]="Hunter",Data.[[#This Row],[Categoría]]="Senior"),OR(SUMIFS(AF:AF,H:H,Data.[[#This Row],[Ruc]],B:B,Data.[[#This Row],[Periodo]])>=15000,SUMIFS(AI:AI,H:H,Data.[[#This Row],[Ruc]],B:B,Data.[[#This Row],[Periodo]])>=15000,SUMIFS(AL:AL,H:H,Data.[[#This Row],[Ruc]],B:B,Data.[[#This Row],[Periodo]])>=15000,SUMIFS(AO:AO,H:H,Data.[[#This Row],[Ruc]],B:B,Data.[[#This Row],[Periodo]])>=15000)),AND(Data.[[#This Row],[Categoría]]="Elite",OR(SUMIFS(AF:AF,H:H,Data.[[#This Row],[Ruc]],B:B,Data.[[#This Row],[Periodo]])>=25000,SUMIFS(AI:AI,H:H,Data.[[#This Row],[Ruc]],B:B,Data.[[#This Row],[Periodo]])>=25000,SUMIFS(AL:AL,H:H,Data.[[#This Row],[Ruc]],B:B,Data.[[#This Row],[Periodo]])>=25000,SUMIFS(AO:AO,H:H,Data.[[#This Row],[Ruc]],B:B,Data.[[#This Row],[Periodo]])>=25000))),1,0)/COUNTIFS(H:H,Data.[[#This Row],[Ruc]],B:B,Data.[[#This Row],[Periodo]]),0) -> 0.5
A50: =CONCATENATE(Data.[[#This Row],[Código]],Data.[[#This Row],[Ruc]]) -> 595468620615781003 | B50: 46174 | C50: =IFERROR(VLOOKUP(Data.[[#This Row],[Código LT]],Reportería.[],71,0),"") | D50: =IFERROR(VLOOKUP(Data.[[#This Row],[Código]],BV!A:C,2,0),"") -> 46175 | E50: =IFERROR(VLOOKUP(Data.[[#This Row],[Código]],BV!A:C,3,0),"") -> 46175 | F50: 5954686 | G50: TJ33261A20091 | H50: 20615781003 | I50: NEGOCIOS E INVERSIONES MCQH SOCIEDAD ANONIMA CERRADA | J50: MAS CARNE QUE HUESO | K50: =IF(Data.[[#This Row],[Tipo de Venta]]<>"POS","Atendido",IF(Data.[[#This Row],[Fecha de Instalación]]<>"","Atendido","Ingresado")) -> Atendido | L50: =Data.[[#This Row],[Estado]] -> Atendido | M50: POS | N50: =IFERROR(VLOOKUP(Data.[[#This Row],[Código LT]],Reportería.[],20,0),"") | O50: =IFERROR(VLOOKUP(Data.[[#This Row],[Código LT]],Reportería.[],5,0),"") | P50: =Data.[[#This Row],[GPV Mensual LT]]/COUNTIFS(H:H,Data.[[#This Row],[Ruc]],B:B,Data.[[#This Row],[Periodo]]) -> 20000 | Q50: 40000 | R50: Angelo Zavala | S50: =VLOOKUP(Data.[[#This Row],[Ejecutivo]],Productividad!D:N,11,0) -> 46741483 | T50: =VLOOKUP(Data.[[#This Row],[DNI Ejecutivo]],Productividad!C:U,8,0) -> azavalaa@lozapay.com.pe | U50: =VLOOKUP(Data.[[#This Row],[DNI Ejecutivo]],Productividad!C:U,4,0) -> Hunter | V50: =IFERROR(VLOOKUP(Data.[[#This Row],[DNI Ejecutivo]],Ejecutivos.[],11,0),"") -> Lima Jean | W50: Jean Aguilar | X50: {=IFERROR(_xlfn.IFS(Data.[[#This Row],[Supervisor]]="Jonathan Lapoint","Norte",Data.[[#This Row],[Supervisor]]="Jorge Fuentes","Norte"),"Lima")} -> Lima | Y50: =VLOOKUP(Data.[[#This Row],[Supervisor]],Ejecutivos!B:S,17,0) -> 47688341 | Z50: =VLOOKUP(Data.[[#This Row],[DNI Supervisor]],Productividad!C:U,8,0) -> jaguilar@lozapay.com.pe | AB50: ANGELO JESUS ZAVALA ANICAMA | AC50: =IFERROR(CONCATENATE(Data.[[#This Row],[DNI Ejecutivo]],Data.[[#This Row],[Periodo]]),"") -> 4674148346174 | AD50: =IFERROR(VLOOKUP(Data.[[#This Row],[Código LT]],Reportería.[],10,0),"") | AE50: =IFERROR(VLOOKUP(Data.[[#This Row],[Código LT]],Reportería.[],11,0),"") | AF50: =IFERROR(VLOOKUP(Data.[[#This Row],[Código]],Reportería!A:BV,57,0),0) -> 17332.6 | AI50: =IF(TEXT(Data.[[#This Row],[Periodo]],"mmm-yy")="may-26",VLOOKUP(Data.[[#This Row],[Código]],Reportería!A:BV,57,0),0) -> 0 | AL50: =IF(Data.[[#This Row],[Vol M0]]="",0,0) -> 0 | AM50: =IF(Data.[[#This Row],[Vol M0]]="",0,0) -> 0 | AN50: =IF(Data.[[#This Row],[Vol M0]]="",0,0) -> 0 | AO50: =IF(Data.[[#This Row],[Vol M0]]="",0,0) -> 0 | AP50: =IF(Data.[[#This Row],[Vol M0]]="",0,0) -> 0 | AQ50: =IF(Data.[[#This Row],[Vol M0]]="",0,0) -> 0 | AR50: =IFERROR(IF(OR(AND(OR(Data.[[#This Row],[Categoría]]="Hunter",Data.[[#This Row],[Categoría]]="Senior"),OR(SUMIFS(AF:AF,H:H,Data.[[#This Row],[Ruc]],B:B,Data.[[#This Row],[Periodo]])>=15000,SUMIFS(AI:AI,H:H,Data.[[#This Row],[Ruc]],B:B,Data.[[#This Row],[Periodo]])>=15000,SUMIFS(AL:AL,H:H,Data.[[#This Row],[Ruc]],B:B,Data.[[#This Row],[Periodo]])>=15000,SUMIFS(AO:AO,H:H,Data.[[#This Row],[Ruc]],B:B,Data.[[#This Row],[Periodo]])>=15000)),AND(Data.[[#This Row],[Categoría]]="Elite",OR(SUMIFS(AF:AF,H:H,Data.[[#This Row],[Ruc]],B:B,Data.[[#This Row],[Periodo]])>=25000,SUMIFS(AI:AI,H:H,Data.[[#This Row],[Ruc]],B:B,Data.[[#This Row],[Periodo]])>=25000,SUMIFS(AL:AL,H:H,Data.[[#This Row],[Ruc]],B:B,Data.[[#This Row],[Periodo]])>=25000,SUMIFS(AO:AO,H:H,Data.[[#This Row],[Ruc]],B:B,Data.[[#This Row],[Periodo]])>=25000))),1,0)/COUNTIFS(H:H,Data.[[#This Row],[Ruc]],B:B,Data.[[#This Row],[Periodo]]),0) -> 0.5
A51: =CONCATENATE(Data.[[#This Row],[Código]],Data.[[#This Row],[Ruc]]) -> 105900120488026641 | B51: 46174 | C51: =IFERROR(VLOOKUP(Data.[[#This Row],[Código LT]],Reportería.[],71,0),"") | D51: =IFERROR(VLOOKUP(Data.[[#This Row],[Código]],BV!A:C,2,0),"") -> 46175 | E51: =IFERROR(VLOOKUP(Data.[[#This Row],[Código]],BV!A:C,3,0),"") -> 46190 | F51: 1059001 | H51: 20488026641 | I51: MULTIPLACAS & ACCESORIOS EL HACEDOR S.A.C. | J51: EL HACEDOR SAC | K51: =IF(Data.[[#This Row],[Tipo de Venta]]<>"POS","Atendido",IF(Data.[[#This Row],[Fecha de Instalación]]<>"","Atendido","Ingresado")) -> Atendido | L51: =Data.[[#This Row],[Estado]] -> Atendido | M51: POS | N51: =IFERROR(VLOOKUP(Data.[[#This Row],[Código LT]],Reportería.[],20,0),"") | O51: =IFERROR(VLOOKUP(Data.[[#This Row],[Código LT]],Reportería.[],5,0),"") | P51: =Data.[[#This Row],[GPV Mensual LT]]/COUNTIFS(H:H,Data.[[#This Row],[Ruc]],B:B,Data.[[#This Row],[Periodo]]) -> 120000 | Q51: 120000 | R51: Katherine Zuloeta | S51: =VLOOKUP(Data.[[#This Row],[Ejecutivo]],Productividad!D:N,11,0) -> 72641569 | T51: =VLOOKUP(Data.[[#This Row],[DNI Ejecutivo]],Productividad!C:U,8,0) -> katherine.zuloeta@lozapay.com.pe | U51: =VLOOKUP(Data.[[#This Row],[DNI Ejecutivo]],Productividad!C:U,4,0) -> Hunter | V51: =IFERROR(VLOOKUP(Data.[[#This Row],[DNI Ejecutivo]],Ejecutivos.[],11,0),"") -> Norte Lapoint | W51: Jonathan Lapoint | X51: {=IFERROR(_xlfn.IFS(Data.[[#This Row],[Supervisor]]="Jonathan Lapoint","Norte",Data.[[#This Row],[Supervisor]]="Jorge Fuentes","Norte"),"Lima")} -> Norte | Y51: =VLOOKUP(Data.[[#This Row],[Supervisor]],Ejecutivos!B:S,17,0) -> 70430554 | Z51: =VLOOKUP(Data.[[#This Row],[DNI Supervisor]],Productividad!C:U,8,0) -> jlapointp@lozapay.com.pe | AB51: KATHERINE DEL CARMEN ZULOETA MALCA | AC51: =IFERROR(CONCATENATE(Data.[[#This Row],[DNI Ejecutivo]],Data.[[#This Row],[Periodo]]),"") -> 7264156946174 | AD51: =IFERROR(VLOOKUP(Data.[[#This Row],[Código LT]],Reportería.[],10,0),"") | AE51: =IFERROR(VLOOKUP(Data.[[#This Row],[Código LT]],Reportería.[],11,0),"") | AF51: =IFERROR(VLOOKUP(Data.[[#This Row],[Código]],Reportería!A:BV,57,0),0) -> 0 | AI51: =IF(TEXT(Data.[[#This Row],[Periodo]],"mmm-yy")="may-26",VLOOKUP(Data.[[#This Row],[Código]],Reportería!A:BV,57,0),0) -> 0 | AL51: =IF(Data.[[#This Row],[Vol M0]]="",0,0) -> 0 | AM51: =IF(Data.[[#This Row],[Vol M0]]="",0,0) -> 0 | AN51: =IF(Data.[[#This Row],[Vol M0]]="",0,0) -> 0 | AO51: =IF(Data.[[#This Row],[Vol M0]]="",0,0) -> 0 | AP51: =IF(Data.[[#This Row],[Vol M0]]="",0,0) -> 0 | AQ51: =IF(Data.[[#This Row],[Vol M0]]="",0,0) -> 0 | AR51: =IFERROR(IF(OR(AND(OR(Data.[[#This Row],[Categoría]]="Hunter",Data.[[#This Row],[Categoría]]="Senior"),OR(SUMIFS(AF:AF,H:H,Data.[[#This Row],[Ruc]],B:B,Data.[[#This Row],[Periodo]])>=15000,SUMIFS(AI:AI,H:H,Data.[[#This Row],[Ruc]],B:B,Data.[[#This Row],[Periodo]])>=15000,SUMIFS(AL:AL,H:H,Data.[[#This Row],[Ruc]],B:B,Data.[[#This Row],[Periodo]])>=15000,SUMIFS(AO:AO,H:H,Data.[[#This Row],[Ruc]],B:B,Data.[[#This Row],[Periodo]])>=15000)),AND(Data.[[#This Row],[Categoría]]="Elite",OR(SUMIFS(AF:AF,H:H,Data.[[#This Row],[Ruc]],B:B,Data.[[#This Row],[Periodo]])>=25000,SUMIFS(AI:AI,H:H,Data.[[#This Row],[Ruc]],B:B,Data.[[#This Row],[Periodo]])>=25000,SUMIFS(AL:AL,H:H,Data.[[#This Row],[Ruc]],B:B,Data.[[#This Row],[Periodo]])>=25000,SUMIFS(AO:AO,H:H,Data.[[#This Row],[Ruc]],B:B,Data.[[#This Row],[Periodo]])>=25000))),1,0)/COUNTIFS(H:H,Data.[[#This Row],[Ruc]],B:B,Data.[[#This Row],[Periodo]]),0) -> 0
A52: =CONCATENATE(Data.[[#This Row],[Código]],Data.[[#This Row],[Ruc]]) -> 595489520614514338 | B52: 46174 | C52: =IFERROR(VLOOKUP(Data.[[#This Row],[Código LT]],Reportería.[],71,0),"") | D52: =IFERROR(VLOOKUP(Data.[[#This Row],[Código]],BV!A:C,2,0),"") -> 46175 | E52: =IFERROR(VLOOKUP(Data.[[#This Row],[Código]],BV!A:C,3,0),"") -> 46176 | F52: 5954895 | G52: TJ33261A20018 | H52: 20614514338 | I52: S. Y M. GRUPO CORPORACION INTERAMERICANA S.A.C. | J52: BRANS CHICKEN 1 | K52: =IF(Data.[[#This Row],[Tipo de Venta]]<>"POS","Atendido",IF(Data.[[#This Row],[Fecha de Instalación]]<>"","Atendido","Ingresado")) -> Atendido | L52: =Data.[[#This Row],[Estado]] -> Atendido | M52: POS | N52: =IFERROR(VLOOKUP(Data.[[#This Row],[Código LT]],Reportería.[],20,0),"") | O52: =IFERROR(VLOOKUP(Data.[[#This Row],[Código LT]],Reportería.[],5,0),"") | P52: =Data.[[#This Row],[GPV Mensual LT]]/COUNTIFS(H:H,Data.[[#This Row],[Ruc]],B:B,Data.[[#This Row],[Periodo]]) -> 20000 | Q52: 80000 | R52: Edinson Chuyes | S52: =VLOOKUP(Data.[[#This Row],[Ejecutivo]],Productividad!D:N,11,0) -> 45311691 | T52: =VLOOKUP(Data.[[#This Row],[DNI Ejecutivo]],Productividad!C:U,8,0) -> edinson.chuyes@lozapay.com.pe | U52: =VLOOKUP(Data.[[#This Row],[DNI Ejecutivo]],Productividad!C:U,4,0) -> Elite | V52: =IFERROR(VLOOKUP(Data.[[#This Row],[DNI Ejecutivo]],Ejecutivos.[],11,0),"") -> Lima Jean | W52: Jean Aguilar | X52: {=IFERROR(_xlfn.IFS(Data.[[#This Row],[Supervisor]]="Jonathan Lapoint","Norte",Data.[[#This Row],[Supervisor]]="Jorge Fuentes","Norte"),"Lima")} -> Lima | Y52: =VLOOKUP(Data.[[#This Row],[Supervisor]],Ejecutivos!B:S,17,0) -> 47688341 | Z52: =VLOOKUP(Data.[[#This Row],[DNI Supervisor]],Productividad!C:U,8,0) -> jaguilar@lozapay.com.pe | AB52: EDINSON WILLIAMS CHUYES ALDANA | AC52: =IFERROR(CONCATENATE(Data.[[#This Row],[DNI Ejecutivo]],Data.[[#This Row],[Periodo]]),"") -> 4531169146174 | AD52: =IFERROR(VLOOKUP(Data.[[#This Row],[Código LT]],Reportería.[],10,0),"") | AE52: =IFERROR(VLOOKUP(Data.[[#This Row],[Código LT]],Reportería.[],11,0),"") | AF52: =IFERROR(VLOOKUP(Data.[[#This Row],[Código]],Reportería!A:BV,57,0),0) -> 9136.3539 | AI52: =IF(TEXT(Data.[[#This Row],[Periodo]],"mmm-yy")="may-26",VLOOKUP(Data.[[#This Row],[Código]],Reportería!A:BV,57,0),0) -> 0 | AL52: =IF(Data.[[#This Row],[Vol M0]]="",0,0) -> 0 | AM52: =IF(Data.[[#This Row],[Vol M0]]="",0,0) -> 0 | AN52: =IF(Data.[[#This Row],[Vol M0]]="",0,0) -> 0 | AO52: =IF(Data.[[#This Row],[Vol M0]]="",0,0) -> 0 | AP52: =IF(Data.[[#This Row],[Vol M0]]="",0,0) -> 0 | AQ52: =IF(Data.[[#This Row],[Vol M0]]="",0,0) -> 0 | AR52: =IFERROR(IF(OR(AND(OR(Data.[[#This Row],[Categoría]]="Hunter",Data.[[#This Row],[Categoría]]="Senior"),OR(SUMIFS(AF:AF,H:H,Data.[[#This Row],[Ruc]],B:B,Data.[[#This Row],[Periodo]])>=15000,SUMIFS(AI:AI,H:H,Data.[[#This Row],[Ruc]],B:B,Data.[[#This Row],[Periodo]])>=15000,SUMIFS(AL:AL,H:H,Data.[[#This Row],[Ruc]],B:B,Data.[[#This Row],[Periodo]])>=15000,SUMIFS(AO:AO,H:H,Data.[[#This Row],[Ruc]],B:B,Data.[[#This Row],[Periodo]])>=15000)),AND(Data.[[#This Row],[Categoría]]="Elite",OR(SUMIFS(AF:AF,H:H,Data.[[#This Row],[Ruc]],B:B,Data.[[#This Row],[Periodo]])>=25000,SUMIFS(AI:AI,H:H,Data.[[#This Row],[Ruc]],B:B,Data.[[#This Row],[Periodo]])>=25000,SUMIFS(AL:AL,H:H,Data.[[#This Row],[Ruc]],B:B,Data.[[#This Row],[Periodo]])>=25000,SUMIFS(AO:AO,H:H,Data.[[#This Row],[Ruc]],B:B,Data.[[#This Row],[Periodo]])>=25000))),1,0)/COUNTIFS(H:H,Data.[[#This Row],[Ruc]],B:B,Data.[[#This Row],[Periodo]]),0) -> 0.25
A53: =CONCATENATE(Data.[[#This Row],[Código]],Data.[[#This Row],[Ruc]]) -> 595490220614514338 | B53: 46174 | C53: =IFERROR(VLOOKUP(Data.[[#This Row],[Código LT]],Reportería.[],71,0),"") | D53: =IFERROR(VLOOKUP(Data.[[#This Row],[Código]],BV!A:C,2,0),"") -> 46175 | E53: =IFERROR(VLOOKUP(Data.[[#This Row],[Código]],BV!A:C,3,0),"") -> 46176 | F53: 5954902 | G53: TJ33261A20712 | H53: 20614514338 | I53: S. Y M. GRUPO CORPORACION INTERAMERICANA S.A.C. | J53: BRANS CHICKEN 1 | K53: =IF(Data.[[#This Row],[Tipo de Venta]]<>"POS","Atendido",IF(Data.[[#This Row],[Fecha de Instalación]]<>"","Atendido","Ingresado")) -> Atendido | L53: =Data.[[#This Row],[Estado]] -> Atendido | M53: POS | N53: =IFERROR(VLOOKUP(Data.[[#This Row],[Código LT]],Reportería.[],20,0),"") | O53: =IFERROR(VLOOKUP(Data.[[#This Row],[Código LT]],Reportería.[],5,0),"") | P53: =Data.[[#This Row],[GPV Mensual LT]]/COUNTIFS(H:H,Data.[[#This Row],[Ruc]],B:B,Data.[[#This Row],[Periodo]]) -> 20000 | Q53: 80000 | R53: Edinson Chuyes | S53: =VLOOKUP(Data.[[#This Row],[Ejecutivo]],Productividad!D:N,11,0) -> 45311691 | T53: =VLOOKUP(Data.[[#This Row],[DNI Ejecutivo]],Productividad!C:U,8,0) -> edinson.chuyes@lozapay.com.pe | U53: =VLOOKUP(Data.[[#This Row],[DNI Ejecutivo]],Productividad!C:U,4,0) -> Elite | V53: =IFERROR(VLOOKUP(Data.[[#This Row],[DNI Ejecutivo]],Ejecutivos.[],11,0),"") -> Lima Jean | W53: Jean Aguilar | X53: {=IFERROR(_xlfn.IFS(Data.[[#This Row],[Supervisor]]="Jonathan Lapoint","Norte",Data.[[#This Row],[Supervisor]]="Jorge Fuentes","Norte"),"Lima")} -> Lima | Y53: =VLOOKUP(Data.[[#This Row],[Supervisor]],Ejecutivos!B:S,17,0) -> 47688341 | Z53: =VLOOKUP(Data.[[#This Row],[DNI Supervisor]],Productividad!C:U,8,0) -> jaguilar@lozapay.com.pe | AB53: EDINSON WILLIAMS CHUYES ALDANA | AC53: =IFERROR(CONCATENATE(Data.[[#This Row],[DNI Ejecutivo]],Data.[[#This Row],[Periodo]]),"") -> 4531169146174 | AD53: =IFERROR(VLOOKUP(Data.[[#This Row],[Código LT]],Reportería.[],10,0),"") | AE53: =IFERROR(VLOOKUP(Data.[[#This Row],[Código LT]],Reportería.[],11,0),"") | AF53: =IFERROR(VLOOKUP(Data.[[#This Row],[Código]],Reportería!A:BV,57,0),0) -> 9302.691 | AI53: =IF(TEXT(Data.[[#This Row],[Periodo]],"mmm-yy")="may-26",VLOOKUP(Data.[[#This Row],[Código]],Reportería!A:BV,57,0),0) -> 0 | AL53: =IF(Data.[[#This Row],[Vol M0]]="",0,0) -> 0 | AM53: =IF(Data.[[#This Row],[Vol M0]]="",0,0) -> 0 | AN53: =IF(Data.[[#This Row],[Vol M0]]="",0,0) -> 0 | AO53: =IF(Data.[[#This Row],[Vol M0]]="",0,0) -> 0 | AP53: =IF(Data.[[#This Row],[Vol M0]]="",0,0) -> 0 | AQ53: =IF(Data.[[#This Row],[Vol M0]]="",0,0) -> 0 | AR53: =IFERROR(IF(OR(AND(OR(Data.[[#This Row],[Categoría]]="Hunter",Data.[[#This Row],[Categoría]]="Senior"),OR(SUMIFS(AF:AF,H:H,Data.[[#This Row],[Ruc]],B:B,Data.[[#This Row],[Periodo]])>=15000,SUMIFS(AI:AI,H:H,Data.[[#This Row],[Ruc]],B:B,Data.[[#This Row],[Periodo]])>=15000,SUMIFS(AL:AL,H:H,Data.[[#This Row],[Ruc]],B:B,Data.[[#This Row],[Periodo]])>=15000,SUMIFS(AO:AO,H:H,Data.[[#This Row],[Ruc]],B:B,Data.[[#This Row],[Periodo]])>=15000)),AND(Data.[[#This Row],[Categoría]]="Elite",OR(SUMIFS(AF:AF,H:H,Data.[[#This Row],[Ruc]],B:B,Data.[[#This Row],[Periodo]])>=25000,SUMIFS(AI:AI,H:H,Data.[[#This Row],[Ruc]],B:B,Data.[[#This Row],[Periodo]])>=25000,SUMIFS(AL:AL,H:H,Data.[[#This Row],[Ruc]],B:B,Data.[[#This Row],[Periodo]])>=25000,SUMIFS(AO:AO,H:H,Data.[[#This Row],[Ruc]],B:B,Data.[[#This Row],[Periodo]])>=25000))),1,0)/COUNTIFS(H:H,Data.[[#This Row],[Ruc]],B:B,Data.[[#This Row],[Periodo]]),0) -> 0.25
A54: =CONCATENATE(Data.[[#This Row],[Código]],Data.[[#This Row],[Ruc]]) -> 595490520614514338 | B54: 46174 | C54: =IFERROR(VLOOKUP(Data.[[#This Row],[Código LT]],Reportería.[],71,0),"") | D54: =IFERROR(VLOOKUP(Data.[[#This Row],[Código]],BV!A:C,2,0),"") -> 46175 | E54: =IFERROR(VLOOKUP(Data.[[#This Row],[Código]],BV!A:C,3,0),"") -> 46176 | F54: 5954905 | G54: TJ33261A20250 | H54: 20614514338 | I54: S. Y M. GRUPO CORPORACION INTERAMERICANA S.A.C. | J54: BRANS CHICKEN 1 | K54: =IF(Data.[[#This Row],[Tipo de Venta]]<>"POS","Atendido",IF(Data.[[#This Row],[Fecha de Instalación]]<>"","Atendido","Ingresado")) -> Atendido | L54: =Data.[[#This Row],[Estado]] -> Atendido | M54: POS | N54: =IFERROR(VLOOKUP(Data.[[#This Row],[Código LT]],Reportería.[],20,0),"") | O54: =IFERROR(VLOOKUP(Data.[[#This Row],[Código LT]],Reportería.[],5,0),"") | P54: =Data.[[#This Row],[GPV Mensual LT]]/COUNTIFS(H:H,Data.[[#This Row],[Ruc]],B:B,Data.[[#This Row],[Periodo]]) -> 20000 | Q54: 80000 | R54: Edinson Chuyes | S54: =VLOOKUP(Data.[[#This Row],[Ejecutivo]],Productividad!D:N,11,0) -> 45311691 | T54: =VLOOKUP(Data.[[#This Row],[DNI Ejecutivo]],Productividad!C:U,8,0) -> edinson.chuyes@lozapay.com.pe | U54: =VLOOKUP(Data.[[#This Row],[DNI Ejecutivo]],Productividad!C:U,4,0) -> Elite | V54: =IFERROR(VLOOKUP(Data.[[#This Row],[DNI Ejecutivo]],Ejecutivos.[],11,0),"") -> Lima Jean | W54: Jean Aguilar | X54: {=IFERROR(_xlfn.IFS(Data.[[#This Row],[Supervisor]]="Jonathan Lapoint","Norte",Data.[[#This Row],[Supervisor]]="Jorge Fuentes","Norte"),"Lima")} -> Lima | Y54: =VLOOKUP(Data.[[#This Row],[Supervisor]],Ejecutivos!B:S,17,0) -> 47688341 | Z54: =VLOOKUP(Data.[[#This Row],[DNI Supervisor]],Productividad!C:U,8,0) -> jaguilar@lozapay.com.pe | AB54: EDINSON WILLIAMS CHUYES ALDANA | AC54: =IFERROR(CONCATENATE(Data.[[#This Row],[DNI Ejecutivo]],Data.[[#This Row],[Periodo]]),"") -> 4531169146174 | AD54: =IFERROR(VLOOKUP(Data.[[#This Row],[Código LT]],Reportería.[],10,0),"") | AE54: =IFERROR(VLOOKUP(Data.[[#This Row],[Código LT]],Reportería.[],11,0),"") | AF54: =IFERROR(VLOOKUP(Data.[[#This Row],[Código]],Reportería!A:BV,57,0),0) -> 9125.9959 | AI54: =IF(TEXT(Data.[[#This Row],[Periodo]],"mmm-yy")="may-26",VLOOKUP(Data.[[#This Row],[Código]],Reportería!A:BV,57,0),0) -> 0 | AL54: =IF(Data.[[#This Row],[Vol M0]]="",0,0) -> 0 | AM54: =IF(Data.[[#This Row],[Vol M0]]="",0,0) -> 0 | AN54: =IF(Data.[[#This Row],[Vol M0]]="",0,0) -> 0 | AO54: =IF(Data.[[#This Row],[Vol M0]]="",0,0) -> 0 | AP54: =IF(Data.[[#This Row],[Vol M0]]="",0,0) -> 0 | AQ54: =IF(Data.[[#This Row],[Vol M0]]="",0,0) -> 0 | AR54: =IFERROR(IF(OR(AND(OR(Data.[[#This Row],[Categoría]]="Hunter",Data.[[#This Row],[Categoría]]="Senior"),OR(SUMIFS(AF:AF,H:H,Data.[[#This Row],[Ruc]],B:B,Data.[[#This Row],[Periodo]])>=15000,SUMIFS(AI:AI,H:H,Data.[[#This Row],[Ruc]],B:B,Data.[[#This Row],[Periodo]])>=15000,SUMIFS(AL:AL,H:H,Data.[[#This Row],[Ruc]],B:B,Data.[[#This Row],[Periodo]])>=15000,SUMIFS(AO:AO,H:H,Data.[[#This Row],[Ruc]],B:B,Data.[[#This Row],[Periodo]])>=15000)),AND(Data.[[#This Row],[Categoría]]="Elite",OR(SUMIFS(AF:AF,H:H,Data.[[#This Row],[Ruc]],B:B,Data.[[#This Row],[Periodo]])>=25000,SUMIFS(AI:AI,H:H,Data.[[#This Row],[Ruc]],B:B,Data.[[#This Row],[Periodo]])>=25000,SUMIFS(AL:AL,H:H,Data.[[#This Row],[Ruc]],B:B,Data.[[#This Row],[Periodo]])>=25000,SUMIFS(AO:AO,H:H,Data.[[#This Row],[Ruc]],B:B,Data.[[#This Row],[Periodo]])>=25000))),1,0)/COUNTIFS(H:H,Data.[[#This Row],[Ruc]],B:B,Data.[[#This Row],[Periodo]]),0) -> 0.25
A55: =CONCATENATE(Data.[[#This Row],[Código]],Data.[[#This Row],[Ruc]]) -> 595487820614514338 | B55: 46174 | C55: =IFERROR(VLOOKUP(Data.[[#This Row],[Código LT]],Reportería.[],71,0),"") | D55: =IFERROR(VLOOKUP(Data.[[#This Row],[Código]],BV!A:C,2,0),"") -> 46175 | E55: =IFERROR(VLOOKUP(Data.[[#This Row],[Código]],BV!A:C,3,0),"") -> 46176 | F55: 5954878 | G55: TJ33261C21476 | H55: 20614514338 | I55: S. Y M. GRUPO CORPORACION INTERAMERICANA S.A.C. | J55: BRANS CHICKEN 1 | K55: =IF(Data.[[#This Row],[Tipo de Venta]]<>"POS","Atendido",IF(Data.[[#This Row],[Fecha de Instalación]]<>"","Atendido","Ingresado")) -> Atendido | L55: =Data.[[#This Row],[Estado]] -> Atendido | M55: POS | N55: =IFERROR(VLOOKUP(Data.[[#This Row],[Código LT]],Reportería.[],20,0),"") | O55: =IFERROR(VLOOKUP(Data.[[#This Row],[Código LT]],Reportería.[],5,0),"") | P55: =Data.[[#This Row],[GPV Mensual LT]]/COUNTIFS(H:H,Data.[[#This Row],[Ruc]],B:B,Data.[[#This Row],[Periodo]]) -> 20000 | Q55: 80000 | R55: Edinson Chuyes | S55: =VLOOKUP(Data.[[#This Row],[Ejecutivo]],Productividad!D:N,11,0) -> 45311691 | T55: =VLOOKUP(Data.[[#This Row],[DNI Ejecutivo]],Productividad!C:U,8,0) -> edinson.chuyes@lozapay.com.pe | U55: =VLOOKUP(Data.[[#This Row],[DNI Ejecutivo]],Productividad!C:U,4,0) -> Elite | V55: =IFERROR(VLOOKUP(Data.[[#This Row],[DNI Ejecutivo]],Ejecutivos.[],11,0),"") -> Lima Jean | W55: Jean Aguilar | X55: {=IFERROR(_xlfn.IFS(Data.[[#This Row],[Supervisor]]="Jonathan Lapoint","Norte",Data.[[#This Row],[Supervisor]]="Jorge Fuentes","Norte"),"Lima")} -> Lima | Y55: =VLOOKUP(Data.[[#This Row],[Supervisor]],Ejecutivos!B:S,17,0) -> 47688341 | Z55: =VLOOKUP(Data.[[#This Row],[DNI Supervisor]],Productividad!C:U,8,0) -> jaguilar@lozapay.com.pe | AB55: EDINSON WILLIAMS CHUYES ALDANA | AC55: =IFERROR(CONCATENATE(Data.[[#This Row],[DNI Ejecutivo]],Data.[[#This Row],[Periodo]]),"") -> 4531169146174 | AD55: =IFERROR(VLOOKUP(Data.[[#This Row],[Código LT]],Reportería.[],10,0),"") | AE55: =IFERROR(VLOOKUP(Data.[[#This Row],[Código LT]],Reportería.[],11,0),"") | AF55: =IFERROR(VLOOKUP(Data.[[#This Row],[Código]],Reportería!A:BV,57,0),0) -> 10798.709 | AI55: =IF(TEXT(Data.[[#This Row],[Periodo]],"mmm-yy")="may-26",VLOOKUP(Data.[[#This Row],[Código]],Reportería!A:BV,57,0),0) -> 0 | AL55: =IF(Data.[[#This Row],[Vol M0]]="",0,0) -> 0 | AM55: =IF(Data.[[#This Row],[Vol M0]]="",0,0) -> 0 | AN55: =IF(Data.[[#This Row],[Vol M0]]="",0,0) -> 0 | AO55: =IF(Data.[[#This Row],[Vol M0]]="",0,0) -> 0 | AP55: =IF(Data.[[#This Row],[Vol M0]]="",0,0) -> 0 | AQ55: =IF(Data.[[#This Row],[Vol M0]]="",0,0) -> 0 | AR55: =IFERROR(IF(OR(AND(OR(Data.[[#This Row],[Categoría]]="Hunter",Data.[[#This Row],[Categoría]]="Senior"),OR(SUMIFS(AF:AF,H:H,Data.[[#This Row],[Ruc]],B:B,Data.[[#This Row],[Periodo]])>=15000,SUMIFS(AI:AI,H:H,Data.[[#This Row],[Ruc]],B:B,Data.[[#This Row],[Periodo]])>=15000,SUMIFS(AL:AL,H:H,Data.[[#This Row],[Ruc]],B:B,Data.[[#This Row],[Periodo]])>=15000,SUMIFS(AO:AO,H:H,Data.[[#This Row],[Ruc]],B:B,Data.[[#This Row],[Periodo]])>=15000)),AND(Data.[[#This Row],[Categoría]]="Elite",OR(SUMIFS(AF:AF,H:H,Data.[[#This Row],[Ruc]],B:B,Data.[[#This Row],[Periodo]])>=25000,SUMIFS(AI:AI,H:H,Data.[[#This Row],[Ruc]],B:B,Data.[[#This Row],[Periodo]])>=25000,SUMIFS(AL:AL,H:H,Data.[[#This Row],[Ruc]],B:B,Data.[[#This Row],[Periodo]])>=25000,SUMIFS(AO:AO,H:H,Data.[[#This Row],[Ruc]],B:B,Data.[[#This Row],[Periodo]])>=25000))),1,0)/COUNTIFS(H:H,Data.[[#This Row],[Ruc]],B:B,Data.[[#This Row],[Periodo]]),0) -> 0.25
A56: =CONCATENATE(Data.[[#This Row],[Código]],Data.[[#This Row],[Ruc]]) -> 595495720449499540 | B56: 46174 | C56: =IFERROR(VLOOKUP(Data.[[#This Row],[Código LT]],Reportería.[],71,0),"") | D56: =IFERROR(VLOOKUP(Data.[[#This Row],[Código]],BV!A:C,2,0),"") -> 46175 | E56: =IFERROR(VLOOKUP(Data.[[#This Row],[Código]],BV!A:C,3,0),"") -> 46179 | F56: 5954957 | G56: TJ33261D20228 | H56: 20449499540 | I56: SERVOX S.R.L. | J56: SERVOX SRL | K56: =IF(Data.[[#This Row],[Tipo de Venta]]<>"POS","Atendido",IF(Data.[[#This Row],[Fecha de Instalación]]<>"","Atendido","Ingresado")) -> Atendido | L56: =Data.[[#This Row],[Estado]] -> Atendido | M56: POS | N56: =IFERROR(VLOOKUP(Data.[[#This Row],[Código LT]],Reportería.[],20,0),"") | O56: =IFERROR(VLOOKUP(Data.[[#This Row],[Código LT]],Reportería.[],5,0),"") | P56: =Data.[[#This Row],[GPV Mensual LT]]/COUNTIFS(H:H,Data.[[#This Row],[Ruc]],B:B,Data.[[#This Row],[Periodo]]) -> 80000 | Q56: 80000 | R56: Marlon Martinez | S56: =VLOOKUP(Data.[[#This Row],[Ejecutivo]],Productividad!D:N,11,0) -> 42858532 | T56: =VLOOKUP(Data.[[#This Row],[DNI Ejecutivo]],Productividad!C:U,8,0) -> marlon.martinez@lozapay.com.pe | U56: =VLOOKUP(Data.[[#This Row],[DNI Ejecutivo]],Productividad!C:U,4,0) -> Hunter | V56: =IFERROR(VLOOKUP(Data.[[#This Row],[DNI Ejecutivo]],Ejecutivos.[],11,0),"") -> Norte Lapoint | W56: Jonathan Lapoint | X56: {=IFERROR(_xlfn.IFS(Data.[[#This Row],[Supervisor]]="Jonathan Lapoint","Norte",Data.[[#This Row],[Supervisor]]="Jorge Fuentes","Norte"),"Lima")} -> Norte | Y56: =VLOOKUP(Data.[[#This Row],[Supervisor]],Ejecutivos!B:S,17,0) -> 70430554 | Z56: =VLOOKUP(Data.[[#This Row],[DNI Supervisor]],Productividad!C:U,8,0) -> jlapointp@lozapay.com.pe | AB56: KATHERINE DEL CARMEN ZULOETA MALCA | AC56: =IFERROR(CONCATENATE(Data.[[#This Row],[DNI Ejecutivo]],Data.[[#This Row],[Periodo]]),"") -> 4285853246174 | AD56: =IFERROR(VLOOKUP(Data.[[#This Row],[Código LT]],Reportería.[],10,0),"") | AE56: =IFERROR(VLOOKUP(Data.[[#This Row],[Código LT]],Reportería.[],11,0),"") | AF56: =IFERROR(VLOOKUP(Data.[[#This Row],[Código]],Reportería!A:BV,57,0),0) -> 0 | AI56: =IF(TEXT(Data.[[#This Row],[Periodo]],"mmm-yy")="may-26",VLOOKUP(Data.[[#This Row],[Código]],Reportería!A:BV,57,0),0) -> 0 | AL56: =IF(Data.[[#This Row],[Vol M0]]="",0,0) -> 0 | AM56: =IF(Data.[[#This Row],[Vol M0]]="",0,0) -> 0 | AN56: =IF(Data.[[#This Row],[Vol M0]]="",0,0) -> 0 | AO56: =IF(Data.[[#This Row],[Vol M0]]="",0,0) -> 0 | AP56: =IF(Data.[[#This Row],[Vol M0]]="",0,0) -> 0 | AQ56: =IF(Data.[[#This Row],[Vol M0]]="",0,0) -> 0 | AR56: =IFERROR(IF(OR(AND(OR(Data.[[#This Row],[Categoría]]="Hunter",Data.[[#This Row],[Categoría]]="Senior"),OR(SUMIFS(AF:AF,H:H,Data.[[#This Row],[Ruc]],B:B,Data.[[#This Row],[Periodo]])>=15000,SUMIFS(AI:AI,H:H,Data.[[#This Row],[Ruc]],B:B,Data.[[#This Row],[Periodo]])>=15000,SUMIFS(AL:AL,H:H,Data.[[#This Row],[Ruc]],B:B,Data.[[#This Row],[Periodo]])>=15000,SUMIFS(AO:AO,H:H,Data.[[#This Row],[Ruc]],B:B,Data.[[#This Row],[Periodo]])>=15000)),AND(Data.[[#This Row],[Categoría]]="Elite",OR(SUMIFS(AF:AF,H:H,Data.[[#This Row],[Ruc]],B:B,Data.[[#This Row],[Periodo]])>=25000,SUMIFS(AI:AI,H:H,Data.[[#This Row],[Ruc]],B:B,Data.[[#This Row],[Periodo]])>=25000,SUMIFS(AL:AL,H:H,Data.[[#This Row],[Ruc]],B:B,Data.[[#This Row],[Periodo]])>=25000,SUMIFS(AO:AO,H:H,Data.[[#This Row],[Ruc]],B:B,Data.[[#This Row],[Periodo]])>=25000))),1,0)/COUNTIFS(H:H,Data.[[#This Row],[Ruc]],B:B,Data.[[#This Row],[Periodo]]),0) -> 0
A57: =CONCATENATE(Data.[[#This Row],[Código]],Data.[[#This Row],[Ruc]]) -> 408142720612053384 | B57: 46174 | C57: =IFERROR(VLOOKUP(Data.[[#This Row],[Código LT]],Reportería.[],71,0),"") | D57: =IFERROR(VLOOKUP(Data.[[#This Row],[Código]],BV!A:C,2,0),"") -> 46176 | E57: =IFERROR(VLOOKUP(Data.[[#This Row],[Código]],BV!A:C,3,0),"") -> 0 | F57: 4081427 | H57: 20612053384 | I57: SOFTLANDERO S.A.C. | J57: SOFTLANDERO SAC | K57: =IF(Data.[[#This Row],[Tipo de Venta]]<>"POS","Atendido",IF(Data.[[#This Row],[Fecha de Instalación]]<>"","Atendido","Ingresado")) -> Atendido | L57: =Data.[[#This Row],[Estado]] -> Atendido | M57: PAGO WEB | N57: =IFERROR(VLOOKUP(Data.[[#This Row],[Código LT]],Reportería.[],20,0),"") | O57: =IFERROR(VLOOKUP(Data.[[#This Row],[Código LT]],Reportería.[],5,0),"") | P57: =Data.[[#This Row],[GPV Mensual LT]]/COUNTIFS(H:H,Data.[[#This Row],[Ruc]],B:B,Data.[[#This Row],[Periodo]]) -> 20000 | Q57: 80000 | R57: William Cortez | S57: =VLOOKUP(Data.[[#This Row],[Ejecutivo]],Productividad!D:N,11,0) -> 71870286 | T57: =VLOOKUP(Data.[[#This Row],[DNI Ejecutivo]],Productividad!C:U,8,0) -> william.cortez@lozapay.com.pe | U57: =VLOOKUP(Data.[[#This Row],[DNI Ejecutivo]],Productividad!C:U,4,0) -> Senior | V57: =IFERROR(VLOOKUP(Data.[[#This Row],[DNI Ejecutivo]],Ejecutivos.[],11,0),"") -> Norte Lapoint | W57: Jonathan Lapoint | X57: {=IFERROR(_xlfn.IFS(Data.[[#This Row],[Supervisor]]="Jonathan Lapoint","Norte",Data.[[#This Row],[Supervisor]]="Jorge Fuentes","Norte"),"Lima")} -> Norte | Y57: =VLOOKUP(Data.[[#This Row],[Supervisor]],Ejecutivos!B:S,17,0) -> 70430554 | Z57: =VLOOKUP(Data.[[#This Row],[DNI Supervisor]],Productividad!C:U,8,0) -> jlapointp@lozapay.com.pe | AB57: WILLIAN OMAR CORTEZ PARRILLA | AC57: =IFERROR(CONCATENATE(Data.[[#This Row],[DNI Ejecutivo]],Data.[[#This Row],[Periodo]]),"") -> 7187028646174 | AD57: =IFERROR(VLOOKUP(Data.[[#This Row],[Código LT]],Reportería.[],10,0),"") | AE57: =IFERROR(VLOOKUP(Data.[[#This Row],[Código LT]],Reportería.[],11,0),"") | AF57: =IFERROR(VLOOKUP(Data.[[#This Row],[Código]],Reportería!A:BV,57,0),0) -> 0 | AI57: =IF(TEXT(Data.[[#This Row],[Periodo]],"mmm-yy")="may-26",VLOOKUP(Data.[[#This Row],[Código]],Reportería!A:BV,57,0),0) -> 0 | AL57: =IF(Data.[[#This Row],[Vol M0]]="",0,0) -> 0 | AM57: =IF(Data.[[#This Row],[Vol M0]]="",0,0) -> 0 | AN57: =IF(Data.[[#This Row],[Vol M0]]="",0,0) -> 0 | AO57: =IF(Data.[[#This Row],[Vol M0]]="",0,0) -> 0 | AP57: =IF(Data.[[#This Row],[Vol M0]]="",0,0) -> 0 | AQ57: =IF(Data.[[#This Row],[Vol M0]]="",0,0) -> 0 | AR57: =IFERROR(IF(OR(AND(OR(Data.[[#This Row],[Categoría]]="Hunter",Data.[[#This Row],[Categoría]]="Senior"),OR(SUMIFS(AF:AF,H:H,Data.[[#This Row],[Ruc]],B:B,Data.[[#This Row],[Periodo]])>=15000,SUMIFS(AI:AI,H:H,Data.[[#This Row],[Ruc]],B:B,Data.[[#This Row],[Periodo]])>=15000,SUMIFS(AL:AL,H:H,Data.[[#This Row],[Ruc]],B:B,Data.[[#This Row],[Periodo]])>=15000,SUMIFS(AO:AO,H:H,Data.[[#This Row],[Ruc]],B:B,Data.[[#This Row],[Periodo]])>=15000)),AND(Data.[[#This Row],[Categoría]]="Elite",OR(SUMIFS(AF:AF,H:H,Data.[[#This Row],[Ruc]],B:B,Data.[[#This Row],[Periodo]])>=25000,SUMIFS(AI:AI,H:H,Data.[[#This Row],[Ruc]],B:B,Data.[[#This Row],[Periodo]])>=25000,SUMIFS(AL:AL,H:H,Data.[[#This Row],[Ruc]],B:B,Data.[[#This Row],[Periodo]])>=25000,SUMIFS(AO:AO,H:H,Data.[[#This Row],[Ruc]],B:B,Data.[[#This Row],[Periodo]])>=25000))),1,0)/COUNTIFS(H:H,Data.[[#This Row],[Ruc]],B:B,Data.[[#This Row],[Periodo]]),0) -> 0
A58: =CONCATENATE(Data.[[#This Row],[Código]],Data.[[#This Row],[Ruc]]) -> 408142820612053384 | B58: 46174 | C58: =IFERROR(VLOOKUP(Data.[[#This Row],[Código LT]],Reportería.[],71,0),"") | D58: =IFERROR(VLOOKUP(Data.[[#This Row],[Código]],BV!A:C,2,0),"") -> 46176 | E58: =IFERROR(VLOOKUP(Data.[[#This Row],[Código]],BV!A:C,3,0),"") -> 0 | F58: 4081428 | H58: 20612053384 | I58: SOFTLANDERO S.A.C. | J58: SOFTLANDERO SAC | K58: =IF(Data.[[#This Row],[Tipo de Venta]]<>"POS","Atendido",IF(Data.[[#This Row],[Fecha de Instalación]]<>"","Atendido","Ingresado")) -> Atendido | L58: =Data.[[#This Row],[Estado]] -> Atendido | M58: PAGO WEB | N58: =IFERROR(VLOOKUP(Data.[[#This Row],[Código LT]],Reportería.[],20,0),"") | O58: =IFERROR(VLOOKUP(Data.[[#This Row],[Código LT]],Reportería.[],5,0),"") | P58: =Data.[[#This Row],[GPV Mensual LT]]/COUNTIFS(H:H,Data.[[#This Row],[Ruc]],B:B,Data.[[#This Row],[Periodo]]) -> 20000 | Q58: 80000 | R58: William Cortez | S58: =VLOOKUP(Data.[[#This Row],[Ejecutivo]],Productividad!D:N,11,0) -> 71870286 | T58: =VLOOKUP(Data.[[#This Row],[DNI Ejecutivo]],Productividad!C:U,8,0) -> william.cortez@lozapay.com.pe | U58: =VLOOKUP(Data.[[#This Row],[DNI Ejecutivo]],Productividad!C:U,4,0) -> Senior | V58: =IFERROR(VLOOKUP(Data.[[#This Row],[DNI Ejecutivo]],Ejecutivos.[],11,0),"") -> Norte Lapoint | W58: Jonathan Lapoint | X58: {=IFERROR(_xlfn.IFS(Data.[[#This Row],[Supervisor]]="Jonathan Lapoint","Norte",Data.[[#This Row],[Supervisor]]="Jorge Fuentes","Norte"),"Lima")} -> Norte | Y58: =VLOOKUP(Data.[[#This Row],[Supervisor]],Ejecutivos!B:S,17,0) -> 70430554 | Z58: =VLOOKUP(Data.[[#This Row],[DNI Supervisor]],Productividad!C:U,8,0) -> jlapointp@lozapay.com.pe | AB58: WILLIAN OMAR CORTEZ PARRILLA | AC58: =IFERROR(CONCATENATE(Data.[[#This Row],[DNI Ejecutivo]],Data.[[#This Row],[Periodo]]),"") -> 7187028646174 | AD58: =IFERROR(VLOOKUP(Data.[[#This Row],[Código LT]],Reportería.[],10,0),"") | AE58: =IFERROR(VLOOKUP(Data.[[#This Row],[Código LT]],Reportería.[],11,0),"") | AF58: =IFERROR(VLOOKUP(Data.[[#This Row],[Código]],Reportería!A:BV,57,0),0) -> 0 | AI58: =IF(TEXT(Data.[[#This Row],[Periodo]],"mmm-yy")="may-26",VLOOKUP(Data.[[#This Row],[Código]],Reportería!A:BV,57,0),0) -> 0 | AL58: =IF(Data.[[#This Row],[Vol M0]]="",0,0) -> 0 | AM58: =IF(Data.[[#This Row],[Vol M0]]="",0,0) -> 0 | AN58: =IF(Data.[[#This Row],[Vol M0]]="",0,0) -> 0 | AO58: =IF(Data.[[#This Row],[Vol M0]]="",0,0) -> 0 | AP58: =IF(Data.[[#This Row],[Vol M0]]="",0,0) -> 0 | AQ58: =IF(Data.[[#This Row],[Vol M0]]="",0,0) -> 0 | AR58: =IFERROR(IF(OR(AND(OR(Data.[[#This Row],[Categoría]]="Hunter",Data.[[#This Row],[Categoría]]="Senior"),OR(SUMIFS(AF:AF,H:H,Data.[[#This Row],[Ruc]],B:B,Data.[[#This Row],[Periodo]])>=15000,SUMIFS(AI:AI,H:H,Data.[[#This Row],[Ruc]],B:B,Data.[[#This Row],[Periodo]])>=15000,SUMIFS(AL:AL,H:H,Data.[[#This Row],[Ruc]],B:B,Data.[[#This Row],[Periodo]])>=15000,SUMIFS(AO:AO,H:H,Data.[[#This Row],[Ruc]],B:B,Data.[[#This Row],[Periodo]])>=15000)),AND(Data.[[#This Row],[Categoría]]="Elite",OR(SUMIFS(AF:AF,H:H,Data.[[#This Row],[Ruc]],B:B,Data.[[#This Row],[Periodo]])>=25000,SUMIFS(AI:AI,H:H,Data.[[#This Row],[Ruc]],B:B,Data.[[#This Row],[Periodo]])>=25000,SUMIFS(AL:AL,H:H,Data.[[#This Row],[Ruc]],B:B,Data.[[#This Row],[Periodo]])>=25000,SUMIFS(AO:AO,H:H,Data.[[#This Row],[Ruc]],B:B,Data.[[#This Row],[Periodo]])>=25000))),1,0)/COUNTIFS(H:H,Data.[[#This Row],[Ruc]],B:B,Data.[[#This Row],[Periodo]]),0) -> 0
A59: =CONCATENATE(Data.[[#This Row],[Código]],Data.[[#This Row],[Ruc]]) -> 408143520612053384 | B59: 46174 | C59: =IFERROR(VLOOKUP(Data.[[#This Row],[Código LT]],Reportería.[],71,0),"") | D59: =IFERROR(VLOOKUP(Data.[[#This Row],[Código]],BV!A:C,2,0),"") -> 46176 | E59: =IFERROR(VLOOKUP(Data.[[#This Row],[Código]],BV!A:C,3,0),"") -> 0 | F59: 4081435 | H59: 20612053384 | I59: SOFTLANDERO S.A.C. | J59: SOFTLANDERO SAC (SOLES) | K59: =IF(Data.[[#This Row],[Tipo de Venta]]<>"POS","Atendido",IF(Data.[[#This Row],[Fecha de Instalación]]<>"","Atendido","Ingresado")) -> Atendido | L59: =Data.[[#This Row],[Estado]] -> Atendido | M59: PAGO LINK | N59: =IFERROR(VLOOKUP(Data.[[#This Row],[Código LT]],Reportería.[],20,0),"") | O59: =IFERROR(VLOOKUP(Data.[[#This Row],[Código LT]],Reportería.[],5,0),"") | P59: =Data.[[#This Row],[GPV Mensual LT]]/COUNTIFS(H:H,Data.[[#This Row],[Ruc]],B:B,Data.[[#This Row],[Periodo]]) -> 20000 | Q59: 80000 | R59: William Cortez | S59: =VLOOKUP(Data.[[#This Row],[Ejecutivo]],Productividad!D:N,11,0) -> 71870286 | T59: =VLOOKUP(Data.[[#This Row],[DNI Ejecutivo]],Productividad!C:U,8,0) -> william.cortez@lozapay.com.pe | U59: =VLOOKUP(Data.[[#This Row],[DNI Ejecutivo]],Productividad!C:U,4,0) -> Senior | V59: =IFERROR(VLOOKUP(Data.[[#This Row],[DNI Ejecutivo]],Ejecutivos.[],11,0),"") -> Norte Lapoint | W59: Jonathan Lapoint | X59: {=IFERROR(_xlfn.IFS(Data.[[#This Row],[Supervisor]]="Jonathan Lapoint","Norte",Data.[[#This Row],[Supervisor]]="Jorge Fuentes","Norte"),"Lima")} -> Norte | Y59: =VLOOKUP(Data.[[#This Row],[Supervisor]],Ejecutivos!B:S,17,0) -> 70430554 | Z59: =VLOOKUP(Data.[[#This Row],[DNI Supervisor]],Productividad!C:U,8,0) -> jlapointp@lozapay.com.pe | AB59: WILLIAN OMAR CORTEZ PARRILLA | AC59: =IFERROR(CONCATENATE(Data.[[#This Row],[DNI Ejecutivo]],Data.[[#This Row],[Periodo]]),"") -> 7187028646174 | AD59: =IFERROR(VLOOKUP(Data.[[#This Row],[Código LT]],Reportería.[],10,0),"") | AE59: =IFERROR(VLOOKUP(Data.[[#This Row],[Código LT]],Reportería.[],11,0),"") | AF59: =IFERROR(VLOOKUP(Data.[[#This Row],[Código]],Reportería!A:BV,57,0),0) -> 0 | AI59: =IF(TEXT(Data.[[#This Row],[Periodo]],"mmm-yy")="may-26",VLOOKUP(Data.[[#This Row],[Código]],Reportería!A:BV,57,0),0) -> 0 | AL59: =IF(Data.[[#This Row],[Vol M0]]="",0,0) -> 0 | AM59: =IF(Data.[[#This Row],[Vol M0]]="",0,0) -> 0 | AN59: =IF(Data.[[#This Row],[Vol M0]]="",0,0) -> 0 | AO59: =IF(Data.[[#This Row],[Vol M0]]="",0,0) -> 0 | AP59: =IF(Data.[[#This Row],[Vol M0]]="",0,0) -> 0 | AQ59: =IF(Data.[[#This Row],[Vol M0]]="",0,0) -> 0 | AR59: =IFERROR(IF(OR(AND(OR(Data.[[#This Row],[Categoría]]="Hunter",Data.[[#This Row],[Categoría]]="Senior"),OR(SUMIFS(AF:AF,H:H,Data.[[#This Row],[Ruc]],B:B,Data.[[#This Row],[Periodo]])>=15000,SUMIFS(AI:AI,H:H,Data.[[#This Row],[Ruc]],B:B,Data.[[#This Row],[Periodo]])>=15000,SUMIFS(AL:AL,H:H,Data.[[#This Row],[Ruc]],B:B,Data.[[#This Row],[Periodo]])>=15000,SUMIFS(AO:AO,H:H,Data.[[#This Row],[Ruc]],B:B,Data.[[#This Row],[Periodo]])>=15000)),AND(Data.[[#This Row],[Categoría]]="Elite",OR(SUMIFS(AF:AF,H:H,Data.[[#This Row],[Ruc]],B:B,Data.[[#This Row],[Periodo]])>=25000,SUMIFS(AI:AI,H:H,Data.[[#This Row],[Ruc]],B:B,Data.[[#This Row],[Periodo]])>=25000,SUMIFS(AL:AL,H:H,Data.[[#This Row],[Ruc]],B:B,Data.[[#This Row],[Periodo]])>=25000,SUMIFS(AO:AO,H:H,Data.[[#This Row],[Ruc]],B:B,Data.[[#This Row],[Periodo]])>=25000))),1,0)/COUNTIFS(H:H,Data.[[#This Row],[Ruc]],B:B,Data.[[#This Row],[Periodo]]),0) -> 0
A60: =CONCATENATE(Data.[[#This Row],[Código]],Data.[[#This Row],[Ruc]]) -> 408143620612053384 | B60: 46174 | C60: =IFERROR(VLOOKUP(Data.[[#This Row],[Código LT]],Reportería.[],71,0),"") | D60: =IFERROR(VLOOKUP(Data.[[#This Row],[Código]],BV!A:C,2,0),"") -> 46176 | E60: =IFERROR(VLOOKUP(Data.[[#This Row],[Código]],BV!A:C,3,0),"") -> 0 | F60: 4081436 | H60: 20612053384 | I60: SOFTLANDERO S.A.C. | J60: SOFTLANDERO SAC (DÓLARES) | K60: =IF(Data.[[#This Row],[Tipo de Venta]]<>"POS","Atendido",IF(Data.[[#This Row],[Fecha de Instalación]]<>"","Atendido","Ingresado")) -> Atendido | L60: =Data.[[#This Row],[Estado]] -> Atendido | M60: PAGO LINK | N60: =IFERROR(VLOOKUP(Data.[[#This Row],[Código LT]],Reportería.[],20,0),"") | O60: =IFERROR(VLOOKUP(Data.[[#This Row],[Código LT]],Reportería.[],5,0),"") | P60: =Data.[[#This Row],[GPV Mensual LT]]/COUNTIFS(H:H,Data.[[#This Row],[Ruc]],B:B,Data.[[#This Row],[Periodo]]) -> 20000 | Q60: 80000 | R60: William Cortez | S60: =VLOOKUP(Data.[[#This Row],[Ejecutivo]],Productividad!D:N,11,0) -> 71870286 | T60: =VLOOKUP(Data.[[#This Row],[DNI Ejecutivo]],Productividad!C:U,8,0) -> william.cortez@lozapay.com.pe | U60: =VLOOKUP(Data.[[#This Row],[DNI Ejecutivo]],Productividad!C:U,4,0) -> Senior | V60: =IFERROR(VLOOKUP(Data.[[#This Row],[DNI Ejecutivo]],Ejecutivos.[],11,0),"") -> Norte Lapoint | W60: Jonathan Lapoint | X60: {=IFERROR(_xlfn.IFS(Data.[[#This Row],[Supervisor]]="Jonathan Lapoint","Norte",Data.[[#This Row],[Supervisor]]="Jorge Fuentes","Norte"),"Lima")} -> Norte | Y60: =VLOOKUP(Data.[[#This Row],[Supervisor]],Ejecutivos!B:S,17,0) -> 70430554 | Z60: =VLOOKUP(Data.[[#This Row],[DNI Supervisor]],Productividad!C:U,8,0) -> jlapointp@lozapay.com.pe | AB60: WILLIAN OMAR CORTEZ PARRILLA | AC60: =IFERROR(CONCATENATE(Data.[[#This Row],[DNI Ejecutivo]],Data.[[#This Row],[Periodo]]),"") -> 7187028646174 | AD60: =IFERROR(VLOOKUP(Data.[[#This Row],[Código LT]],Reportería.[],10,0),"") | AE60: =IFERROR(VLOOKUP(Data.[[#This Row],[Código LT]],Reportería.[],11,0),"") | AF60: =IFERROR(VLOOKUP(Data.[[#This Row],[Código]],Reportería!A:BV,57,0),0) -> 0 | AI60: =IF(TEXT(Data.[[#This Row],[Periodo]],"mmm-yy")="may-26",VLOOKUP(Data.[[#This Row],[Código]],Reportería!A:BV,57,0),0) -> 0 | AL60: =IF(Data.[[#This Row],[Vol M0]]="",0,0) -> 0 | AM60: =IF(Data.[[#This Row],[Vol M0]]="",0,0) -> 0 | AN60: =IF(Data.[[#This Row],[Vol M0]]="",0,0) -> 0 | AO60: =IF(Data.[[#This Row],[Vol M0]]="",0,0) -> 0 | AP60: =IF(Data.[[#This Row],[Vol M0]]="",0,0) -> 0 | AQ60: =IF(Data.[[#This Row],[Vol M0]]="",0,0) -> 0 | AR60: =IFERROR(IF(OR(AND(OR(Data.[[#This Row],[Categoría]]="Hunter",Data.[[#This Row],[Categoría]]="Senior"),OR(SUMIFS(AF:AF,H:H,Data.[[#This Row],[Ruc]],B:B,Data.[[#This Row],[Periodo]])>=15000,SUMIFS(AI:AI,H:H,Data.[[#This Row],[Ruc]],B:B,Data.[[#This Row],[Periodo]])>=15000,SUMIFS(AL:AL,H:H,Data.[[#This Row],[Ruc]],B:B,Data.[[#This Row],[Periodo]])>=15000,SUMIFS(AO:AO,H:H,Data.[[#This Row],[Ruc]],B:B,Data.[[#This Row],[Periodo]])>=15000)),AND(Data.[[#This Row],[Categoría]]="Elite",OR(SUMIFS(AF:AF,H:H,Data.[[#This Row],[Ruc]],B:B,Data.[[#This Row],[Periodo]])>=25000,SUMIFS(AI:AI,H:H,Data.[[#This Row],[Ruc]],B:B,Data.[[#This Row],[Periodo]])>=25000,SUMIFS(AL:AL,H:H,Data.[[#This Row],[Ruc]],B:B,Data.[[#This Row],[Periodo]])>=25000,SUMIFS(AO:AO,H:H,Data.[[#This Row],[Ruc]],B:B,Data.[[#This Row],[Periodo]])>=25000))),1,0)/COUNTIFS(H:H,Data.[[#This Row],[Ruc]],B:B,Data.[[#This Row],[Periodo]]),0) -> 0
A61: =CONCATENATE(Data.[[#This Row],[Código]],Data.[[#This Row],[Ruc]]) -> 595546020613633601 | B61: 46174 | C61: =IFERROR(VLOOKUP(Data.[[#This Row],[Código LT]],Reportería.[],71,0),"") | D61: =IFERROR(VLOOKUP(Data.[[#This Row],[Código]],BV!A:C,2,0),"") -> 46176 | E61: =IFERROR(VLOOKUP(Data.[[#This Row],[Código]],BV!A:C,3,0),"") -> 46176 | F61: 5955460 | G61: TJ33262720200 | H61: 20613633601 | I61: BAR WASH LOCO BOSH E.I.R.L. | J61: LOCO BOSH | K61: =IF(Data.[[#This Row],[Tipo de Venta]]<>"POS","Atendido",IF(Data.[[#This Row],[Fecha de Instalación]]<>"","Atendido","Ingresado")) -> Atendido | L61: =Data.[[#This Row],[Estado]] -> Atendido | M61: POS | N61: =IFERROR(VLOOKUP(Data.[[#This Row],[Código LT]],Reportería.[],20,0),"") | O61: =IFERROR(VLOOKUP(Data.[[#This Row],[Código LT]],Reportería.[],5,0),"") | P61: =Data.[[#This Row],[GPV Mensual LT]]/COUNTIFS(H:H,Data.[[#This Row],[Ruc]],B:B,Data.[[#This Row],[Periodo]]) -> 25000 | Q61: 200000 | R61: Lin Ley Casique | S61: =VLOOKUP(Data.[[#This Row],[Ejecutivo]],Productividad!D:N,11,0) -> 00100436 | T61: =VLOOKUP(Data.[[#This Row],[DNI Ejecutivo]],Productividad!C:U,8,0) -> Linley.casique@lozapay.com.pe | U61: =VLOOKUP(Data.[[#This Row],[DNI Ejecutivo]],Productividad!C:U,4,0) -> Hunter | V61: =IFERROR(VLOOKUP(Data.[[#This Row],[DNI Ejecutivo]],Ejecutivos.[],11,0),"") -> Norte Lapoint | W61: Jonathan Lapoint | X61: {=IFERROR(_xlfn.IFS(Data.[[#This Row],[Supervisor]]="Jonathan Lapoint","Norte",Data.[[#This Row],[Supervisor]]="Jorge Fuentes","Norte"),"Lima")} -> Norte | Y61: =VLOOKUP(Data.[[#This Row],[Supervisor]],Ejecutivos!B:S,17,0) -> 70430554 | Z61: =VLOOKUP(Data.[[#This Row],[DNI Supervisor]],Productividad!C:U,8,0) -> jlapointp@lozapay.com.pe | AB61: WILLIAN OMAR CORTEZ PARRILLA | AC61: =IFERROR(CONCATENATE(Data.[[#This Row],[DNI Ejecutivo]],Data.[[#This Row],[Periodo]]),"") -> 0010043646174 | AD61: =IFERROR(VLOOKUP(Data.[[#This Row],[Código LT]],Reportería.[],10,0),"") | AE61: =IFERROR(VLOOKUP(Data.[[#This Row],[Código LT]],Reportería.[],11,0),"") | AF61: =IFERROR(VLOOKUP(Data.[[#This Row],[Código]],Reportería!A:BV,57,0),0) -> 2902 | AI61: =IF(TEXT(Data.[[#This Row],[Periodo]],"mmm-yy")="may-26",VLOOKUP(Data.[[#This Row],[Código]],Reportería!A:BV,57,0),0) -> 0 | AL61: =IF(Data.[[#This Row],[Vol M0]]="",0,0) -> 0 | AM61: =IF(Data.[[#This Row],[Vol M0]]="",0,0) -> 0 | AN61: =IF(Data.[[#This Row],[Vol M0]]="",0,0) -> 0 | AO61: =IF(Data.[[#This Row],[Vol M0]]="",0,0) -> 0 | AP61: =IF(Data.[[#This Row],[Vol M0]]="",0,0) -> 0 | AQ61: =IF(Data.[[#This Row],[Vol M0]]="",0,0) -> 0 | AR61: =IFERROR(IF(OR(AND(OR(Data.[[#This Row],[Categoría]]="Hunter",Data.[[#This Row],[Categoría]]="Senior"),OR(SUMIFS(AF:AF,H:H,Data.[[#This Row],[Ruc]],B:B,Data.[[#This Row],[Periodo]])>=15000,SUMIFS(AI:AI,H:H,Data.[[#This Row],[Ruc]],B:B,Data.[[#This Row],[Periodo]])>=15000,SUMIFS(AL:AL,H:H,Data.[[#This Row],[Ruc]],B:B,Data.[[#This Row],[Periodo]])>=15000,SUMIFS(AO:AO,H:H,Data.[[#This Row],[Ruc]],B:B,Data.[[#This Row],[Periodo]])>=15000)),AND(Data.[[#This Row],[Categoría]]="Elite",OR(SUMIFS(AF:AF,H:H,Data.[[#This Row],[Ruc]],B:B,Data.[[#This Row],[Periodo]])>=25000,SUMIFS(AI:AI,H:H,Data.[[#This Row],[Ruc]],B:B,Data.[[#This Row],[Periodo]])>=25000,SUMIFS(AL:AL,H:H,Data.[[#This Row],[Ruc]],B:B,Data.[[#This Row],[Periodo]])>=25000,SUMIFS(AO:AO,H:H,Data.[[#This Row],[Ruc]],B:B,Data.[[#This Row],[Periodo]])>=25000))),1,0)/COUNTIFS(H:H,Data.[[#This Row],[Ruc]],B:B,Data.[[#This Row],[Periodo]]),0) -> 0.125
